package org.powerbot.bot.cache;

import java.util.Arrays;
import org.powerbot.bot.rt6.HashTable;
import z.aux;

























































































class Whirlpool
{
  private static final int jdField_char = 512;
  public static final int jdField_true = 64;
  private static final int jdField_case = 10;
  private static final String jdField_for = aux.jdMethod_this("᠉웯螒ň㚌틲祅酕悖鮉ꌦ笲᷊ퟅ⹡﹐ᕝ㟢鿚䫝壣⤍놊殂뵷ჳ쬔ՠ䆌ꝗ闟﯄籡?䞙쨇뼀군茴挨ꩶ젳䧞宏騌㊷햇뻧㑏ｐ遘⁂᪩둾錥擛猕䀢쏫?贺霪켬皨혜떅橗䗙ヨ㽿ꋭ斐⿇?﵊鉟ڍ닌ธ拾ꢑ璘╞葘㥋幒㢋톏댋鰙䏭ﰃ决洊﫵縣㮁츖轤러㲫铰뤹Ⳕ쐄噮羮⪑셔?鵫ㅞ겣ᓦᘐ椎炜탪챨颣⡶"); static { 1; int tmp17_16 = 1;tmp17_16;long = new long['Ā'][tmp17_16];
    1; int tmp34_33 = 1;tmp34_33;int = tmp34_33; int 
    

      tmp41_40 = 1;tmp41_40;int i = tmp41_40;1; int 
      tmp62_61 = 1;tmp62_61;int j = i.charAt(2 / tmp62_61); int 
      tmp71_70 = 1; int tmp72_71 = tmp71_70;tmp72_71; if ((tmp71_70 & tmp72_71) == 0) { int tmp82_81 = 1;tmp82_81;tmpTernaryOp = (8 >>> tmp82_81; break label99; throw j; } else { 1; } label99: long l1 = 0xFF & tmp95_94;
    int tmp102_101 = 1; int tmp103_102 = tmp102_101;tmp103_102;
    long l2; if ((l2 = tmp102_101 << tmp103_102) >= 256L) {
      l2 ^= 0x11D;
    }
    int tmp127_126 = 1; int tmp128_127 = tmp127_126;tmp128_127;
    long l3; if ((l3 = tmp127_126 << tmp128_127) >= 256L) {
      l3 ^= 0x11D;
    }
    long l4 = l3 ^ l1; int 
      tmp158_157 = 1; int tmp159_158 = tmp158_157;tmp159_158;
    long l5; if ((l5 = tmp158_157 << tmp159_158) >= 256L) {
      l5 ^= 0x11D;
    }
    long l6 = l5 ^ l1;
    


    1;1;1;1;1; int tmp232_231 = 1;tmp232_231; int tmp241_240 = 1;tmp241_240; int tmp250_249 = 1;tmp250_249;(l5 | 24 << tmp232_231)[(l4 | 16 << tmp241_240)] = (l2 | 8 << tmp250_249 | l6); int 
    




      tmp260_258 = 1;tmp260_258; for (int k = tmp260_258;; tmpTernaryOp = k) { int tmp267_266 = 1;tmp267_266; if (8 >= tmp267_266) break;
      1;1; int tmp301_300 = 1; int tmp302_301 = tmp301_300;tmp302_301; int tmp311_310 = 1;tmp311_310;long[(k[(tmp301_300 - tmp302_301)][i] | 56 << tmp311_310)] = (k++);
    }
    throw 
      (8 >>> tmp293_292);i++; int 
    





      tmp336_335 = 1;tmp336_335;0[tmp336_335] = 0L; int 
      tmp342_340 = 1;tmp342_340;i = tmp342_340;1;
    1; int tmp361_360 = 1; int tmp362_361 = tmp361_360;tmp362_361;j = i * (tmp361_360 - tmp362_361);
    1;1;1;1;1;1;1;1;1;1;1;1;1; int tmp513_512 = 1;tmp513_512; int tmp520_519 = 1;tmp520_519;long[(7[tmp513_512] ^ j[(7 + tmp520_519)] & 0xFF)] = (i++);
  }
  


  private static final long[][] jdField_long;
  

  private static final long[] jdField_int;
  

  private final byte[] jdField_super;
  
  private final byte[] jdField_final;
  
  private int jdField_enum;
  
  private int jdField_else;
  
  private final long[] jdField_if;
  
  private final long[] jdField_null;
  
  private final long[] jdField_byte;
  
  private final long[] jdField_new;
  
  private final long[] jdField_void;
  
  private Whirlpool()
  {
    int tmp28_27 = 1;tmp28_27; int tmp33_32 = 1;tmp33_32;2827jdField_super = tmp33_32; int 
    



      tmp39_38 = 1;tmp39_38; int tmp44_43 = 1;tmp44_43;3938jdField_final = tmp44_43; int 
    



      tmp50_49 = 1;tmp50_49;
    














      32jdField_enum = tmp50_49; int tmp56_55 = 1;tmp56_55;jdField_else = tmp56_55; int tmp62_61 = 1;tmp62_61; int tmp67_66 = 1;tmp67_66;6261jdField_if = tmp67_66; int tmp73_72 = 1;tmp73_72; int tmp78_77 = 1;tmp78_77;7372jdField_null = tmp78_77; int tmp84_83 = 1;tmp84_83; int tmp89_88 = 1;tmp89_88;8483jdField_byte = tmp89_88; int tmp95_94 = 1;tmp95_94; int tmp100_99 = 1;tmp100_99;9594jdField_new = tmp100_99; int tmp106_105 = 1;tmp106_105; int tmp111_110 = 1;tmp111_110;106105jdField_void = tmp111_110;
  }
  







  private void jdMethod_true()
  {
    int tmp2_1 = 1;tmp2_1;int i = tmp2_1; int tmp7_6 = 1;tmp7_6; for (int j = tmp7_6;; tmpTernaryOp = i) { int tmp14_13 = 1;tmp14_13; if (8 >= tmp14_13) break;
      1;1;1;1;1;1;1;1;1;1;1; int tmp160_159 = 1;tmp160_159; int tmp172_171 = 1;tmp172_171; int tmp184_183 = 1;tmp184_183;(j[(6 + tmp160_159)] & 0xFF ^ 8 << tmp172_171)[(jdField_final ^ j[(7 + tmp184_183)] & 0xFF)] = (i++);j += 8;
    }
    throw 
      jdField_final; int 
    











      tmp208_207 = 1;tmp208_207; for (i = tmp208_207;; tmpTernaryOp = i) { int tmp215_214 = 1;tmp215_214; if (8 >= tmp215_214) break;
      int tmp230_229 = i; int tmp242_241 = i; long tmp244_243 = jdField_if[tmp242_241];jdField_null[tmp242_241] = tmp244_243;tmp230_229[(jdField_new[tmp230_229] ^ tmp244_243)] = (i++);
    }
    throw 
      jdField_void; int 
    



      tmp258_256 = 1;tmp258_256;i = tmp258_256;1; int 
    


      tmp272_271 = 1;tmp272_271;j = tmp272_271;1;
    jdField_byte[j] = 0L; int 
      tmp293_292 = 1;tmp293_292;int k = tmp293_292; int tmp299_298 = 1;tmp299_298;int m = tmp299_298;1; int 
      tmp334_333 = 1;tmp334_333; int tmp346_345 = 1;tmp346_345;long[k][(jdField_null ^ ((int)((j - k)[(0x7 & tmp334_333)] >>> m))[(0xFF & tmp346_345)])] = (k++);m -= 8;j++;
    

    1; int tmp384_383 = 1;tmp384_383; int tmp389_388 = 1;tmp389_388;System.arraycopy(jdField_null, 0, tmp384_383, 8, tmp389_388); int 
      tmp399_398 = 1;tmp399_398;0[tmp399_398] ^= int[i]; int 
    


      tmp412_411 = 1;tmp412_411;j = tmp412_411;1; int 
      tmp435_434 = j;jdField_byte[tmp435_434] = jdField_null[tmp435_434]; int 
      tmp439_438 = 1;tmp439_438;k = tmp439_438; int tmp445_444 = 1;tmp445_444;m = tmp445_444;1; int 
      tmp480_479 = 1;tmp480_479; int tmp492_491 = 1;tmp492_491;long[k][(jdField_void ^ ((int)((j - k)[(0x7 & tmp480_479)] >>> m))[(0xFF & tmp492_491)])] = (k++);m -= 8;j++;
    

    1; int tmp529_528 = 1;tmp529_528; int tmp537_534 = (i++);tmp537_534;System.arraycopy(0, tmp529_528, 8, 1, tmp537_534); int 
    



      tmp548_547 = 1;tmp548_547;i = tmp548_547;1; int 
      tmp565_564 = i;tmp565_564[(jdField_if[tmp565_564] ^ jdField_void[i] ^ jdField_new[i])] = (i++);
  }
  



  private void jdMethod_this()
  {
    int tmp9_8 = 1;tmp9_8;Arrays.fill(0, tmp9_8); int 
      tmp15_14 = 1;tmp15_14;0jdField_enum = (jdField_super.else = tmp15_14); int 
      tmp31_30 = 1;tmp31_30; int tmp35_34 = 1;tmp35_34;tmp31_30[0] = tmp35_34;
    Arrays.fill(0jdField_if, 0L);
  }
  



















  private void jdMethod_this(byte[] a, long a)
  {
    int tmp2_1 = 1;tmp2_1;int i = tmp2_1;
    1;1; int tmp23_22 = 1;tmp23_22;int j = 0x7 & tmp23_22; int 
      tmp35_34 = 1;tmp35_34;int k = 0x7 & tmp35_34;
    

    long l = a; int 
      tmp46_45 = 1;tmp46_45;int n = tmp46_45; int tmp52_51 = 1;tmp52_51; for (int i1 = tmp52_51; n >= 0;) {
      int tmp74_73 = 1;tmp74_73; int tmp84_83 = 1;tmp84_83;tmp84_83 = (0xFF & tmp74_73) + ((int)l + (0xFF & tmp84_83));
      jdField_super[tmp74_73] = ((byte)tmp84_83); int 
        tmp105_104 = 1;tmp105_104;tmp84_83 = 8 >>> tmp105_104; int 
        tmp115_114 = 1;(tmp74_73--);l = tmp115_114 >>> tmp115_114;tmpTernaryOp = tmp74_73; continue;throw 8;
    }
    
    while (a > 8L)
    {
      1;1; int tmp164_163 = 1;tmp164_163; int tmp170_169 = 1;tmp170_169;
      
      if ((m = 0xFF & tmp164_163 | 8 >>> tmp170_169 - j) >= 0) { int tmp189_188 = 1;tmp189_188; if (256 < tmp189_188) {}
      } else { throw new RuntimeException(HashTable.jdMethod_this("ktmp\004vvaka"));
      }
      
      int tmp216_213 = jdField_else; int tmp218_217 = 1; int tmp219_218 = tmp218_217;tmp219_218;216213jdField_else = (tmp218_217 + tmp219_218); int tmp225_216 = tmp216_213;tmp225_216[a] = ((byte)(tmp225_216[a] | m >>> k)); int 
        tmp244_243 = 1;tmp244_243;jdField_enum.jdField_enum = (8 + (tmp244_243 - k)); int 
        tmp260_259 = 1;tmp260_259; if (512 == tmp260_259)
      {
        a.jdMethod_true(); int 
        
          tmp273_272 = 1;tmp273_272;jdField_enum = (0.else = tmp273_272);
      }
      int tmp297_296 = 1;tmp297_296; int tmp307_306 = 1;tmp307_306;m[(8 << tmp297_296 - k)] = ((byte)(0xFF & tmp307_306));
      jdField_else.jdField_enum += k;
      
      a = i++ - 8L;
      tmpTernaryOp = a; continue;throw a;
    }
    


    int tmp354_353 = 1;tmp354_353;int m = 0xFF & tmp354_353; int 
    
      tmp366_363 = jdField_else; byte[] tmp366_359 = jdField_final;tmp366_359[tmp366_363] = ((byte)(tmp366_359[tmp366_363] | m >>> k)); int 
    
      tmp383_382 = 1;tmp383_382;m = tmp383_382;
    
    if ((a > 0L ? k : k) + a < 8L)
    {
      jdField_enum = ((int)(jdField_enum + a)); return;
    }
    
    int tmp418_417 = 1; int tmp419_418 = tmp418_417;tmp419_418;0jdField_else.jdField_else = (tmp418_417 + tmp419_418); int 
      tmp435_434 = 1;tmp435_434;jdField_enum.jdField_enum = (8 + (tmp435_434 - k)); int 
      tmp447_446 = 1;tmp447_446;a = 8 - (tmp447_446 - k); int 
    
      tmp462_461 = 1;tmp462_461; if (512 == tmp462_461)
    {
      a.jdMethod_true(); int 
      
        tmp475_474 = 1;tmp475_474;jdField_enum = (0.else = tmp475_474);
    }
    int tmp499_498 = 1;tmp499_498; int tmp509_508 = 1;tmp509_508;m[(8 << tmp499_498 - k)] = ((byte)(0xFF & tmp509_508));
    jdField_else.jdField_enum += (int)a;
  }
  






  private void jdMethod_this(byte[] a)
  {
    int tmp10_7 = jdField_else; int tmp16_15 = 1;tmp16_15; int tmp25_24 = 1;tmp25_24;jdField_final[tmp10_7][''] = ((byte)(tmp16_15 | jdField_enum >>> (0x7 & tmp25_24))); int 
      tmp37_36 = 1; int tmp38_37 = tmp37_36;tmp38_37;107jdField_else.jdField_else = (tmp37_36 + tmp38_37); int 
    
      tmp50_49 = 1;tmp50_49; if (32 > tmp50_49) {
      for (;;) { int tmp62_61 = 1;tmp62_61; if (64 >= tmp62_61) break;
        int tmp78_77 = 1; int tmp79_78 = tmp78_77;tmp79_78;jdField_else.jdField_else = (tmp78_77 + tmp79_78); int tmp87_86 = 1;tmp87_86;a[0] = tmp87_86;tmpTernaryOp = a; } throw tmp76_73;
      

      a.jdMethod_true(); int 
      
        tmp102_101 = 1;tmp102_101;0jdField_else = tmp102_101;
    }
    for (;;) { int tmp114_113 = 1;tmp114_113; if (32 >= tmp114_113) break;
      int tmp130_129 = 1; int tmp131_130 = tmp130_129;tmp131_130;jdField_else.jdField_else = (tmp130_129 + tmp131_130); int tmp139_138 = 1;tmp139_138;a[0] = tmp139_138;tmpTernaryOp = a; } throw tmp128_125; int 
    

      tmp154_153 = 1;tmp154_153; int tmp163_162 = 1;tmp163_162; int tmp168_167 = 1;tmp168_167;System.arraycopy(jdField_final, 32, tmp163_162, 32, tmp168_167);tmp154_153
    
      .jdMethod_true(); int 
    
      tmp178_177 = 1;tmp178_177;int i = tmp178_177; int tmp183_182 = 1;tmp183_182;int j = tmp183_182;1;
    long l = jdField_if[i]; int 
      tmp224_223 = 1;tmp224_223;j[l] = ((byte)(int)(56 >>> tmp224_223)); int 
      tmp231_230 = 1; int tmp232_231 = tmp231_230;tmp232_231; int tmp240_239 = 1;tmp240_239;(tmp231_230 + tmp232_231)[l] = ((byte)(int)(48 >>> tmp240_239)); int 
      tmp248_247 = 1;tmp248_247; int tmp256_255 = 1;tmp256_255;(2 + tmp248_247)[l] = ((byte)(int)(40 >>> tmp256_255)); int 
      tmp264_263 = 1;tmp264_263; int tmp272_271 = 1;tmp272_271;(3 + tmp264_263)[l] = ((byte)(int)(32 >>> tmp272_271)); int 
      tmp280_279 = 1;tmp280_279; int tmp288_287 = 1;tmp288_287;(4 + tmp280_279)[l] = ((byte)(int)(24 >>> tmp288_287)); int 
      tmp296_295 = 1;tmp296_295; int tmp304_303 = 1;tmp304_303;(5 + tmp296_295)[l] = ((byte)(int)(16 >>> tmp304_303)); int 
      tmp313_312 = 1;tmp313_312; int tmp321_320 = 1;tmp321_320;(6 + tmp313_312)[l] = ((byte)(int)(8 >>> tmp321_320)); int 
      tmp330_329 = 1;tmp330_329;(7 + tmp330_329)[((byte)(int)l)] = (i++);j += 8;
  }
  
















  public void NESSIEadd(String a)
  {
    if (a.length() > 0) {
      int tmp14_13 = 1;tmp14_13;int ? = tmp14_13; int 
        tmp19_18 = 1;
      int i; for (tmp19_18; (i = tmp19_18) < a.length();) {
        int tmp33_32 = i;tmp33_32[((byte)a.charAt(tmp33_32))] = (i++);tmpTernaryOp = i; continue;throw ?;
      }
      int tmp51_50 = 1;tmp51_50; int tmp54_53 = ?;8.jdMethod_this(tmp54_53, tmp51_50 * tmp54_53.length);
    }
  }
  
  /* Error */
  public static byte[] whirlpool(byte[] a, int a, int a)
  {
    // Byte code:
    //   0: iload_1
    //   1: ifgt +9 -> 10
    //   4: aload_0
    //   5: astore_3
    //   6: goto +22 -> 28
    //   9: athrow
    //   10: iload_2
    //   11: newarray byte
    //   13: iconst_1
    //   14: dup
    //   15: pop2
    //   16: astore_3
    //   17: aload_0
    //   18: iload_1
    //   19: aload_3
    //   20: iconst_0
    //   21: iconst_1
    //   22: dup
    //   23: pop2
    //   24: iload_2
    //   25: invokestatic 36	java/lang/System:arraycopy	(Ljava/lang/Object;ILjava/lang/Object;II)V
    //   28: new 2	org/powerbot/bot/cache/Whirlpool
    //   31: dup
    //   32: invokespecial 40	org/powerbot/bot/cache/Whirlpool:<init>	()V
    //   35: astore_1
    //   36: bipush 64
    //   38: aload_1
    //   39: dup_x1
    //   40: aload_3
    //   41: iload_2
    //   42: aload_1
    //   43: invokespecial 43	org/powerbot/bot/cache/Whirlpool:this	()V
    //   46: bipush 8
    //   48: iconst_1
    //   49: dup
    //   50: pop2
    //   51: imul
    //   52: i2l
    //   53: invokespecial 46	org/powerbot/bot/cache/Whirlpool:this	([BJ)V
    //   56: iconst_1
    //   57: dup
    //   58: pop2
    //   59: newarray byte
    //   61: iconst_1
    //   62: dup
    //   63: pop2
    //   64: dup
    //   65: astore_1
    //   66: invokespecial 49	org/powerbot/bot/cache/Whirlpool:this	([B)V
    //   69: aload_1
    //   70: areturn
    // Line number table:
    //   Java source line #155	-> byte code offset #0
    //   Java source line #156	-> byte code offset #4
    //   Java source line #158	-> byte code offset #10
    //   Java source line #159	-> byte code offset #17
    //   Java source line #161	-> byte code offset #28
    //   Java source line #162	-> byte code offset #36
    //   Java source line #163	-> byte code offset #46
    //   Java source line #164	-> byte code offset #56
    //   Java source line #165	-> byte code offset #66
    //   Java source line #166	-> byte code offset #69
    // Local variable table:
    //   start	length	slot	name	signature
    //   0	71	0	a	byte[]
    //   0	71	1	a	int
    //   0	71	2	a	int
  }
}
