package org.powerbot.util;

import java.io.BufferedReader;
import java.io.IOException;
import java.util.Map;
import z.Oa;

public class Ini implements java.io.Serializable
{
  private static final String jdField_byte = "";
  private static final long serialVersionUID = 2162875213770806139L;
  private final transient Map<String, aUX> jdField_new;
  private final transient java.util.concurrent.atomic.AtomicBoolean jdField_void;
  
  public Ini()
  {
    a;a.<init>();jdField_new = a;
    a; int tmp27_26 = 1; int tmp28_27 = tmp27_26;tmp28_27;tmp27_26.<init>(tmp28_27);jdField_void = a;
  }
  
  public boolean jdMethod_this() {
    return a.jdMethod_catch("");
  }
  
  private boolean jdMethod_catch(String a) {
    return jdField_new.containsKey(a);
  }
  
  public aUX get()
  {
    return a.jdMethod_this("");
  }
  
  /* Error */
  public aUX jdMethod_this(String a)
  {
    // Byte code:
    //   0: aload_0
    //   1: getfield 36	org/powerbot/util/Ini:new	Ljava/util/Map;
    //   4: aload_1
    //   5: invokeinterface 57 2 0
    //   10: ifeq +20 -> 30
    //   13: aload_0
    //   14: getfield 36	org/powerbot/util/Ini:new	Ljava/util/Map;
    //   17: aload_1
    //   18: invokeinterface 65 2 0
    //   23: checkcast 11	org/powerbot/util/aUX
    //   26: dup
    //   27: astore_2
    //   28: areturn
    //   29: athrow
    //   30: aload_0
    //   31: getfield 36	org/powerbot/util/Ini:new	Ljava/util/Map;
    //   34: new 11	org/powerbot/util/aUX
    //   37: aload_1
    //   38: dup_x1
    //   39: dup
    //   40: pop2
    //   41: dup
    //   42: aload_0
    //   43: aconst_null
    //   44: invokespecial 68	org/powerbot/util/aUX:<init>	(Lorg/powerbot/util/Ini;Lorg/powerbot/util/Aux;)V
    //   47: dup
    //   48: astore_2
    //   49: invokeinterface 72 3 0
    //   54: pop
    //   55: aload_2
    //   56: areturn
    // Line number table:
    //   Java source line #36	-> byte code offset #0
    //   Java source line #37	-> byte code offset #13
    //   Java source line #39	-> byte code offset #30
    //   Java source line #41	-> byte code offset #55
    // Local variable table:
    //   start	length	slot	name	signature
    //   0	57	0	a	Ini
    //   0	57	1	a	String
  }
  
  public Ini put(aUX a)
  {
    return a.jdMethod_this("", a);
  }
  
  private Ini jdMethod_this(String a, aUX a) {
    jdField_new.put(a, a);
    return a;
  }
  
  public Ini put(Map<String, String> a)
  {
    return a.jdMethod_this("", a);
  }
  
  private Ini jdMethod_this(String a, Map<String, String> a) {
    String tmp5_4 = a; String tmp6_5 = tmp5_4;tmp6_5; String tmp8_6 = tmp6_5;tmp8_6.<init>(a, a, null);return tmp5_4.jdMethod_this(new org/powerbot/util/aUX, tmp8_6);
  }
  
  public Ini jdMethod_true() {
    return a.jdMethod_this("");
  }
  
  private Ini jdMethod_this(String a) {
    jdField_new.remove(a);
    return a;
  }
  
  public Ini jdMethod_this() {
    jdField_new.clear();
    return a;
  }
  
  /* Error */
  public Ini write(java.io.File a)
  {
    // Byte code:
    //   0: new 105	java/io/FileOutputStream
    //   3: dup
    //   4: aload_1
    //   5: invokespecial 108	java/io/FileOutputStream:<init>	(Ljava/io/File;)V
    //   8: astore_1
    //   9: aconst_null
    //   10: astore_2
    //   11: aload_0
    //   12: aload_1
    //   13: invokevirtual 111	org/powerbot/util/Ini:this	(Ljava/io/OutputStream;)Lorg/powerbot/util/Ini;
    //   16: pop
    //   17: aload_1
    //   18: ifnull +78 -> 96
    //   21: aload_2
    //   22: ifnull +21 -> 43
    //   25: aload_1
    //   26: invokevirtual 116	java/io/OutputStream:close	()V
    //   29: goto +67 -> 96
    //   32: athrow
    //   33: astore_3
    //   34: aload_2
    //   35: aload_3
    //   36: invokevirtual 120	java/lang/Throwable:addSuppressed	(Ljava/lang/Throwable;)V
    //   39: goto +57 -> 96
    //   42: athrow
    //   43: aload_1
    //   44: invokevirtual 116	java/io/OutputStream:close	()V
    //   47: goto +49 -> 96
    //   50: astore_3
    //   51: aload_3
    //   52: dup
    //   53: astore_2
    //   54: athrow
    //   55: astore 4
    //   57: aload_1
    //   58: ifnull +31 -> 89
    //   61: aload_2
    //   62: ifnull +23 -> 85
    //   65: aload_1
    //   66: invokevirtual 116	java/io/OutputStream:close	()V
    //   69: aload 4
    //   71: goto +20 -> 91
    //   74: astore_3
    //   75: aload 4
    //   77: aload_2
    //   78: aload_3
    //   79: invokevirtual 120	java/lang/Throwable:addSuppressed	(Ljava/lang/Throwable;)V
    //   82: goto +9 -> 91
    //   85: aload_1
    //   86: invokevirtual 116	java/io/OutputStream:close	()V
    //   89: aload 4
    //   91: athrow
    //   92: nop
    //   93: nop
    //   94: athrow
    //   95: astore_1
    //   96: aload_0
    //   97: areturn
    // Line number table:
    //   Java source line #79	-> byte code offset #0
    //   Java source line #80	-> byte code offset #11
    //   Java source line #81	-> byte code offset #17
    //   Java source line #79	-> byte code offset #50
    //   Java source line #81	-> byte code offset #55
    //   Java source line #82	-> byte code offset #92
    //   Java source line #81	-> byte code offset #95
    //   Java source line #83	-> byte code offset #96
    // Local variable table:
    //   start	length	slot	name	signature
    //   0	98	0	a	Ini
    //   0	98	1	a	java.io.File
    // Exception table:
    //   from	to	target	type
    //   25	29	33	java/lang/Throwable
    //   11	17	50	java/lang/Throwable
    //   11	17	55	finally
    //   50	57	55	finally
    //   65	69	74	java/lang/Throwable
    //   0	32	95	java/io/IOException
    //   33	42	95	java/io/IOException
    //   43	92	95	java/io/IOException
  }
  
  /* Error */
  public Ini jdMethod_this(java.io.OutputStream a)
    throws IOException
  {
    // Byte code:
    //   0: aload_0
    //   1: invokevirtual 127	org/powerbot/util/Ini:toString	()Ljava/lang/String;
    //   4: ldc -127
    //   6: invokestatic 134	org/powerbot/util/IOUtils:this	(Ljava/lang/Object;)Ljava/lang/String;
    //   9: invokevirtual 138	java/lang/String:getBytes	(Ljava/lang/String;)[B
    //   12: astore_2
    //   13: aload_1
    //   14: goto +15 -> 29
    //   17: athrow
    //   18: astore_3
    //   19: new 140	java/lang/IllegalStateException
    //   22: dup
    //   23: aload_3
    //   24: invokespecial 142	java/lang/IllegalStateException:<init>	(Ljava/lang/Throwable;)V
    //   27: athrow
    //   28: athrow
    //   29: aload_2
    //   30: invokevirtual 145	java/io/OutputStream:write	([B)V
    //   33: aload_0
    //   34: aload_1
    //   35: invokevirtual 116	java/io/OutputStream:close	()V
    //   38: areturn
    // Line number table:
    //   Java source line #89	-> byte code offset #0
    //   Java source line #92	-> byte code offset #14
    //   Java source line #90	-> byte code offset #18
    //   Java source line #91	-> byte code offset #19
    //   Java source line #93	-> byte code offset #28
    //   Java source line #94	-> byte code offset #34
    //   Java source line #95	-> byte code offset #38
    // Local variable table:
    //   start	length	slot	name	signature
    //   0	39	0	a	Ini
    //   0	39	1	a	java.io.OutputStream
    // Exception table:
    //   from	to	target	type
    //   0	13	18	java/io/UnsupportedEncodingException
  }
  
  private void writeObject(java.io.ObjectOutputStream a)
    throws IOException
  {
    a.jdMethod_this(a);
  }
  
  /* Error */
  public Ini read(java.io.File a)
  {
    // Byte code:
    //   0: new 154	java/io/FileInputStream
    //   3: dup
    //   4: aload_1
    //   5: invokespecial 155	java/io/FileInputStream:<init>	(Ljava/io/File;)V
    //   8: astore_1
    //   9: aconst_null
    //   10: astore_2
    //   11: aload_0
    //   12: aload_1
    //   13: invokevirtual 158	org/powerbot/util/Ini:this	(Ljava/io/InputStream;)Lorg/powerbot/util/Ini;
    //   16: astore_3
    //   17: aload_1
    //   18: ifnull +29 -> 47
    //   21: aload_2
    //   22: ifnull +21 -> 43
    //   25: aload_1
    //   26: invokevirtual 161	java/io/InputStream:close	()V
    //   29: aload_3
    //   30: areturn
    //   31: athrow
    //   32: astore 4
    //   34: aload_3
    //   35: aload_2
    //   36: aload 4
    //   38: invokevirtual 120	java/lang/Throwable:addSuppressed	(Ljava/lang/Throwable;)V
    //   41: areturn
    //   42: athrow
    //   43: aload_1
    //   44: invokevirtual 161	java/io/InputStream:close	()V
    //   47: aload_3
    //   48: areturn
    //   49: astore_3
    //   50: aload_3
    //   51: dup
    //   52: astore_2
    //   53: athrow
    //   54: astore 5
    //   56: aload_1
    //   57: ifnull +31 -> 88
    //   60: aload_2
    //   61: ifnull +23 -> 84
    //   64: aload_1
    //   65: invokevirtual 161	java/io/InputStream:close	()V
    //   68: aload 5
    //   70: goto +20 -> 90
    //   73: astore_3
    //   74: aload 5
    //   76: aload_2
    //   77: aload_3
    //   78: invokevirtual 120	java/lang/Throwable:addSuppressed	(Ljava/lang/Throwable;)V
    //   81: goto +9 -> 90
    //   84: aload_1
    //   85: invokevirtual 161	java/io/InputStream:close	()V
    //   88: aload 5
    //   90: athrow
    //   91: astore_1
    //   92: aload_0
    //   93: areturn
    // Line number table:
    //   Java source line #104	-> byte code offset #0
    //   Java source line #105	-> byte code offset #11
    //   Java source line #106	-> byte code offset #17
    //   Java source line #105	-> byte code offset #47
    //   Java source line #104	-> byte code offset #49
    //   Java source line #106	-> byte code offset #54
    //   Java source line #107	-> byte code offset #92
    // Local variable table:
    //   start	length	slot	name	signature
    //   0	94	0	a	Ini
    //   0	94	1	a	java.io.File
    // Exception table:
    //   from	to	target	type
    //   25	29	32	java/lang/Throwable
    //   11	17	49	java/lang/Throwable
    //   11	17	54	finally
    //   49	56	54	finally
    //   64	68	73	java/lang/Throwable
    //   0	31	91	java/io/IOException
    //   32	42	91	java/io/IOException
    //   43	47	91	java/io/IOException
    //   49	91	91	java/io/IOException
  }
  
  /* Error */
  public Ini jdMethod_this(java.io.InputStream a)
    throws IOException
  {
    // Byte code:
    //   0: new 163	java/io/BufferedReader
    //   3: dup
    //   4: new 165	java/io/InputStreamReader
    //   7: dup
    //   8: aload_1
    //   9: invokespecial 168	java/io/InputStreamReader:<init>	(Ljava/io/InputStream;)V
    //   12: invokespecial 171	java/io/BufferedReader:<init>	(Ljava/io/Reader;)V
    //   15: astore_1
    //   16: ldc 49
    //   18: astore_2
    //   19: aload_0
    //   20: getfield 36	org/powerbot/util/Ini:new	Ljava/util/Map;
    //   23: aload_2
    //   24: invokeinterface 57 2 0
    //   29: ifeq +23 -> 52
    //   32: aload_0
    //   33: getfield 36	org/powerbot/util/Ini:new	Ljava/util/Map;
    //   36: aload_2
    //   37: invokeinterface 65 2 0
    //   42: checkcast 11	org/powerbot/util/aUX
    //   45: astore 4
    //   47: aload_1
    //   48: goto +31 -> 79
    //   51: athrow
    //   52: aload_0
    //   53: getfield 36	org/powerbot/util/Ini:new	Ljava/util/Map;
    //   56: new 11	org/powerbot/util/aUX
    //   59: aload_2
    //   60: dup_x1
    //   61: dup
    //   62: pop2
    //   63: dup
    //   64: aload_0
    //   65: aconst_null
    //   66: invokespecial 68	org/powerbot/util/aUX:<init>	(Lorg/powerbot/util/Ini;Lorg/powerbot/util/Aux;)V
    //   69: dup
    //   70: astore 4
    //   72: invokeinterface 72 3 0
    //   77: pop
    //   78: aload_1
    //   79: invokevirtual 174	java/io/BufferedReader:readLine	()Ljava/lang/String;
    //   82: dup
    //   83: astore_3
    //   84: ifnull +249 -> 333
    //   87: aload_3
    //   88: invokevirtual 177	java/lang/String:trim	()Ljava/lang/String;
    //   91: dup
    //   92: astore 5
    //   94: invokevirtual 180	java/lang/String:isEmpty	()Z
    //   97: ifeq +8 -> 105
    //   100: aload_1
    //   101: goto -22 -> 79
    //   104: athrow
    //   105: aload 5
    //   107: invokevirtual 184	java/lang/String:length	()I
    //   110: iconst_1
    //   111: dup
    //   112: dup
    //   113: pop2
    //   114: if_icmple +139 -> 253
    //   117: aload 5
    //   119: iconst_0
    //   120: iconst_1
    //   121: dup
    //   122: pop2
    //   123: invokevirtual 188	java/lang/String:charAt	(I)C
    //   126: bipush 91
    //   128: iconst_1
    //   129: dup
    //   130: pop2
    //   131: if_icmpne +122 -> 253
    //   134: aload 5
    //   136: dup
    //   137: invokevirtual 184	java/lang/String:length	()I
    //   140: iconst_1
    //   141: dup
    //   142: dup
    //   143: pop2
    //   144: isub
    //   145: invokevirtual 188	java/lang/String:charAt	(I)C
    //   148: bipush 93
    //   150: iconst_1
    //   151: dup
    //   152: pop2
    //   153: if_icmpne +100 -> 253
    //   156: aload 5
    //   158: invokevirtual 184	java/lang/String:length	()I
    //   161: iconst_2
    //   162: iconst_1
    //   163: dup
    //   164: pop2
    //   165: if_icmpne +8 -> 173
    //   168: ldc 49
    //   170: goto +22 -> 192
    //   173: aload 5
    //   175: iconst_1
    //   176: dup
    //   177: pop2
    //   178: aload 5
    //   180: invokevirtual 184	java/lang/String:length	()I
    //   183: iconst_1
    //   184: dup
    //   185: dup_x2
    //   186: dup
    //   187: pop2
    //   188: isub
    //   189: invokevirtual 192	java/lang/String:substring	(II)Ljava/lang/String;
    //   192: astore_2
    //   193: aload_0
    //   194: getfield 36	org/powerbot/util/Ini:new	Ljava/util/Map;
    //   197: aload_2
    //   198: invokeinterface 57 2 0
    //   203: aload_0
    //   204: swap
    //   205: ifeq +20 -> 225
    //   208: getfield 36	org/powerbot/util/Ini:new	Ljava/util/Map;
    //   211: aload_2
    //   212: invokeinterface 65 2 0
    //   217: checkcast 11	org/powerbot/util/aUX
    //   220: astore 4
    //   222: goto -144 -> 78
    //   225: getfield 36	org/powerbot/util/Ini:new	Ljava/util/Map;
    //   228: new 11	org/powerbot/util/aUX
    //   231: aload_2
    //   232: dup_x1
    //   233: dup
    //   234: pop2
    //   235: dup
    //   236: aload_0
    //   237: aconst_null
    //   238: invokespecial 68	org/powerbot/util/aUX:<init>	(Lorg/powerbot/util/Ini;Lorg/powerbot/util/Aux;)V
    //   241: dup
    //   242: astore 4
    //   244: invokeinterface 72 3 0
    //   249: pop
    //   250: goto -172 -> 78
    //   253: aload_3
    //   254: aload_1
    //   255: invokestatic 195	org/powerbot/util/Ini:this	(Ljava/lang/String;Ljava/io/BufferedReader;)Ljava/lang/String;
    //   258: invokevirtual 177	java/lang/String:trim	()Ljava/lang/String;
    //   261: dup
    //   262: astore 5
    //   264: bipush 61
    //   266: iconst_1
    //   267: dup
    //   268: pop2
    //   269: invokevirtual 199	java/lang/String:indexOf	(I)I
    //   272: dup
    //   273: istore_3
    //   274: iconst_m1
    //   275: iconst_1
    //   276: dup
    //   277: pop2
    //   278: if_icmpne +7 -> 285
    //   281: aload_1
    //   282: goto -203 -> 79
    //   285: aload 4
    //   287: aload 5
    //   289: iconst_0
    //   290: iconst_1
    //   291: dup
    //   292: pop2
    //   293: iload_3
    //   294: iinc 3 1
    //   297: invokevirtual 192	java/lang/String:substring	(II)Ljava/lang/String;
    //   300: invokevirtual 177	java/lang/String:trim	()Ljava/lang/String;
    //   303: iload_3
    //   304: aload 5
    //   306: invokevirtual 184	java/lang/String:length	()I
    //   309: if_icmpne +8 -> 317
    //   312: ldc 49
    //   314: goto +12 -> 326
    //   317: aload 5
    //   319: iload_3
    //   320: invokevirtual 202	java/lang/String:substring	(I)Ljava/lang/String;
    //   323: invokevirtual 177	java/lang/String:trim	()Ljava/lang/String;
    //   326: invokevirtual 205	org/powerbot/util/aUX:this	(Ljava/lang/String;Ljava/lang/String;)Lorg/powerbot/util/aUX;
    //   329: pop
    //   330: goto -252 -> 78
    //   333: aload_1
    //   334: invokevirtual 206	java/io/BufferedReader:close	()V
    //   337: aload_0
    //   338: areturn
    // Line number table:
    //   Java source line #112	-> byte code offset #0
    //   Java source line #114	-> byte code offset #16
    //   Java source line #116	-> byte code offset #19
    //   Java source line #117	-> byte code offset #32
    //   Java source line #119	-> byte code offset #52
    //   Java source line #122	-> byte code offset #78
    //   Java source line #123	-> byte code offset #87
    //   Java source line #124	-> byte code offset #94
    //   Java source line #125	-> byte code offset #101
    //   Java source line #127	-> byte code offset #105
    //   Java source line #128	-> byte code offset #156
    //   Java source line #129	-> byte code offset #193
    //   Java source line #130	-> byte code offset #208
    //   Java source line #132	-> byte code offset #225
    //   Java source line #135	-> byte code offset #253
    //   Java source line #136	-> byte code offset #264
    //   Java source line #137	-> byte code offset #274
    //   Java source line #138	-> byte code offset #282
    //   Java source line #140	-> byte code offset #285
    //   Java source line #142	-> byte code offset #330
    //   Java source line #144	-> byte code offset #333
    //   Java source line #145	-> byte code offset #337
    // Local variable table:
    //   start	length	slot	name	signature
    //   0	339	0	a	Ini
    //   0	339	1	a	java.io.InputStream
  }
  
  private static String jdMethod_this(String a, BufferedReader a)
    throws IOException
  {
    if (!a.isEmpty()) { 1; int tmp23_22 = 1;tmp23_22; if (92 == tmp23_22) {}
    } else { return a;throw a.length().charAt(tmp13_12 - tmp14_12);
    }
    
    StringBuilder localStringBuilder = new StringBuilder();
    String str1 = System.getProperty(Oa.jdMethod_this("|=~1>'u$q&q &"));
    String str2;
    for (;;)
    {
      1; int tmp75_74 = 1;tmp75_74; if (92 != tmp75_74) break;
      int tmp92_91 = ;;;;; } throw a; StringBuilder 
    
      tmp105_104 = localStringBuilder;tmp105_104.append(str2).append(str1);
    



    return ((str2 = a.readLine()) != null ? tmp105_104 : localStringBuilder).delete(localStringBuilder.length() - str1.length(), str1.length()).toString();
  }
  
  private void readObject(java.io.ObjectInputStream a) throws IOException {
    a.jdMethod_this(a);
  }
  
  private void jdMethod_this() throws java.io.ObjectStreamException
  {}
  
  public java.util.Set<java.util.Map.Entry<String, aUX>> jdMethod_this()
  {
    return jdField_new.entrySet();
  }
  
  /* Error */
  public String toString()
  {
    // Byte code:
    //   0: new 209	java/lang/StringBuilder
    //   3: dup
    //   4: invokespecial 210	java/lang/StringBuilder:<init>	()V
    //   7: astore_1
    //   8: aload_0
    //   9: dup
    //   10: getfield 43	org/powerbot/util/Ini:void	Ljava/util/concurrent/atomic/AtomicBoolean;
    //   13: invokevirtual 247	java/util/concurrent/atomic/AtomicBoolean:get	()Z
    //   16: istore_2
    //   17: getfield 36	org/powerbot/util/Ini:new	Ljava/util/Map;
    //   20: ldc 49
    //   22: invokeinterface 57 2 0
    //   27: ifeq +38 -> 65
    //   30: aload_0
    //   31: getfield 36	org/powerbot/util/Ini:new	Ljava/util/Map;
    //   34: ldc 49
    //   36: invokeinterface 65 2 0
    //   41: checkcast 11	org/powerbot/util/aUX
    //   44: invokevirtual 248	org/powerbot/util/aUX:toString	()Ljava/lang/String;
    //   47: astore_3
    //   48: iload_2
    //   49: ifeq +10 -> 59
    //   52: aload_3
    //   53: invokevirtual 180	java/lang/String:isEmpty	()Z
    //   56: ifne +9 -> 65
    //   59: aload_1
    //   60: aload_3
    //   61: invokevirtual 225	java/lang/StringBuilder:append	(Ljava/lang/String;)Ljava/lang/StringBuilder;
    //   64: pop
    //   65: aload_0
    //   66: getfield 36	org/powerbot/util/Ini:new	Ljava/util/Map;
    //   69: invokeinterface 245 1 0
    //   74: invokeinterface 254 1 0
    //   79: astore_3
    //   80: aload_3
    //   81: invokeinterface 259 1 0
    //   86: ifeq +105 -> 191
    //   89: aload_3
    //   90: invokeinterface 263 1 0
    //   95: checkcast 13	java/util/Map$Entry
    //   98: dup
    //   99: astore 4
    //   101: invokeinterface 266 1 0
    //   106: checkcast 76	java/lang/String
    //   109: ldc 49
    //   111: invokevirtual 269	java/lang/String:equals	(Ljava/lang/Object;)Z
    //   114: ifeq +8 -> 122
    //   117: aload_3
    //   118: goto -37 -> 81
    //   121: athrow
    //   122: aload 4
    //   124: invokeinterface 272 1 0
    //   129: checkcast 11	org/powerbot/util/aUX
    //   132: invokevirtual 248	org/powerbot/util/aUX:toString	()Ljava/lang/String;
    //   135: astore 5
    //   137: iload_2
    //   138: ifeq +11 -> 149
    //   141: aload 5
    //   143: invokevirtual 180	java/lang/String:isEmpty	()Z
    //   146: ifne -66 -> 80
    //   149: aload_1
    //   150: ldc_w 274
    //   153: invokestatic 134	org/powerbot/util/IOUtils:this	(Ljava/lang/Object;)Ljava/lang/String;
    //   156: invokevirtual 225	java/lang/StringBuilder:append	(Ljava/lang/String;)Ljava/lang/StringBuilder;
    //   159: aload 4
    //   161: invokeinterface 266 1 0
    //   166: checkcast 76	java/lang/String
    //   169: invokevirtual 225	java/lang/StringBuilder:append	(Ljava/lang/String;)Ljava/lang/StringBuilder;
    //   172: ldc_w 276
    //   175: invokestatic 215	z/Oa:this	(Ljava/lang/Object;)Ljava/lang/String;
    //   178: invokevirtual 225	java/lang/StringBuilder:append	(Ljava/lang/String;)Ljava/lang/StringBuilder;
    //   181: aload 5
    //   183: invokevirtual 225	java/lang/StringBuilder:append	(Ljava/lang/String;)Ljava/lang/StringBuilder;
    //   186: pop
    //   187: goto -107 -> 80
    //   190: athrow
    //   191: aload_1
    //   192: invokevirtual 235	java/lang/StringBuilder:toString	()Ljava/lang/String;
    //   195: areturn
    // Line number table:
    //   Java source line #183	-> byte code offset #0
    //   Java source line #184	-> byte code offset #8
    //   Java source line #186	-> byte code offset #17
    //   Java source line #187	-> byte code offset #30
    //   Java source line #188	-> byte code offset #48
    //   Java source line #189	-> byte code offset #59
    //   Java source line #193	-> byte code offset #65
    //   Java source line #194	-> byte code offset #101
    //   Java source line #195	-> byte code offset #109
    //   Java source line #196	-> byte code offset #118
    //   Java source line #198	-> byte code offset #122
    //   Java source line #199	-> byte code offset #137
    //   Java source line #200	-> byte code offset #149
    //   Java source line #202	-> byte code offset #187
    //   Java source line #204	-> byte code offset #191
    // Local variable table:
    //   start	length	slot	name	signature
    //   0	196	0	a	Ini
  }
  
  private static boolean jdMethod_true(String a)
  {
    if ((a != null) && (!(a = a.trim()).isEmpty()) && (!a.equals(IOUtils.jdMethod_this("g"))) && (!a.equalsIgnoreCase(Oa.jdMethod_this("2q8c1"))) && (!a.equalsIgnoreCase(IOUtils.jdMethod_this("8n1"))) && (!a.equalsIgnoreCase(Oa.jdMethod_this("~;")))) { int tmp69_68 = 1; int tmp70_69 = tmp69_68;tmp70_69;return tmp70_69;throw tmp69_68; } int tmp76_75 = 1;tmp76_75;return tmp76_75;
  }
}
