package z;

import java.util.ArrayList;
import java.util.List;






























































































































public class dA
  extends auX
{
  public int jdField_int;
  public String jdField_super;
  public String jdField_final;
  public String jdField_enum;
  public Object jdField_else;
  public List<ca> jdField_if;
  public List<ca> jdField_null;
  public List<LPT8> jdField_byte;
  public List<LPT8> jdField_new;
  public List<lpt6> jdField_void;
  
  public dA(int a, String a, String a, String a, Object a)
  {
    a.<init>(327680, a, a, a, a, a);
    if (a.getClass() != dA.class) {
      throw new IllegalStateException();
    }
  }
  
























  public dA(int a, int a, String a, String a, String a, Object a)
  {
    a.<init>(a);
    jdField_int = a;
    jdField_super = a;
    jdField_final = a;
    jdField_enum = a;
    jdField_else = a;
  }
  





  public aux jdMethod_this(String a, boolean a)
  {
    a = new ca(a);
    if (a != 0) {
      if (jdField_if == null) {
        a; int tmp29_28 = 1; int tmp30_29 = tmp29_28;tmp30_29;tmp29_28.<init>(tmp30_29);jdField_if = a;
      }
      jdField_if.add(a);return a;throw new java/util/ArrayList;
    }
    if (jdField_null == null) {
      a; int tmp68_67 = 1; int tmp69_68 = tmp68_67;tmp69_68;tmp68_67.<init>(tmp69_68);jdField_null = a;
    }
    jdField_null.add(a);
    
    return a;
  }
  

  public aux jdMethod_this(int a, Qa a, String a, boolean a)
  {
    a = new LPT8(a, a, a);
    if (a != 0) {
      if (jdField_byte == null) {
        a; int tmp32_31 = 1; int tmp33_32 = tmp32_31;tmp33_32;tmp32_31.<init>(tmp33_32);jdField_byte = a;
      }
      jdField_byte.add(a);return a;throw new java/util/ArrayList;
    }
    if (jdField_new == null) {
      a; int tmp71_70 = 1; int tmp72_71 = tmp71_70;tmp72_71;tmp71_70.<init>(tmp72_71);jdField_new = a;
    }
    jdField_new.add(a);
    
    return a;
  }
  
  public void jdMethod_this(lpt6 a)
  {
    if (jdField_void == null) {
      a; int tmp16_15 = 1; int tmp17_16 = tmp16_15;tmp17_16;tmp16_15.<init>(tmp17_16);jdField_void = a;
    }
    jdField_void.add(a);
  }
  








  public void jdMethod_this() {}
  







  public void jdMethod_this(int a)
  {
    if (a == 262144) {
      if ((jdField_byte != null) && 
        (jdField_byte.size() > 0)) {
        throw new RuntimeException();
      }
      if ((jdField_new != null) && 
        (jdField_new.size() > 0)) {
        throw new RuntimeException();
      }
    }
  }
  
  /* Error */
  public void jdMethod_this(cOn a)
  {
    // Byte code:
    //   0: aload_1
    //   1: aload_0
    //   2: dup
    //   3: getfield 48	z/dA:int	I
    //   6: swap
    //   7: getfield 50	z/dA:super	Ljava/lang/String;
    //   10: aload_0
    //   11: dup
    //   12: getfield 52	z/dA:final	Ljava/lang/String;
    //   15: swap
    //   16: getfield 54	z/dA:enum	Ljava/lang/String;
    //   19: aload_0
    //   20: getfield 56	z/dA:else	Ljava/lang/Object;
    //   23: invokevirtual 109	z/cOn:this	(ILjava/lang/String;Ljava/lang/String;Ljava/lang/String;Ljava/lang/Object;)Lz/auX;
    //   26: dup
    //   27: astore_1
    //   28: ifnonnull +5 -> 33
    //   31: return
    //   32: athrow
    //   33: aload_0
    //   34: getfield 65	z/dA:if	Ljava/util/List;
    //   37: ifnonnull +11 -> 48
    //   40: iconst_0
    //   41: iconst_1
    //   42: dup
    //   43: pop2
    //   44: goto +13 -> 57
    //   47: athrow
    //   48: aload_0
    //   49: getfield 65	z/dA:if	Ljava/util/List;
    //   52: invokeinterface 100 1 0
    //   57: istore_3
    //   58: iconst_0
    //   59: iconst_1
    //   60: dup
    //   61: pop2
    //   62: dup
    //   63: istore_2
    //   64: iload_3
    //   65: if_icmpge +42 -> 107
    //   68: aload_0
    //   69: getfield 65	z/dA:if	Ljava/util/List;
    //   72: iload_2
    //   73: invokeinterface 113 2 0
    //   78: checkcast 60	z/ca
    //   81: astore 4
    //   83: aload_1
    //   84: aload 4
    //   86: dup_x1
    //   87: getfield 115	z/ca:new	Ljava/lang/String;
    //   90: iconst_1
    //   91: dup
    //   92: dup
    //   93: iinc 2 1
    //   96: pop2
    //   97: invokevirtual 117	z/auX:this	(Ljava/lang/String;Z)Lz/aux;
    //   100: invokevirtual 120	z/ca:this	(Lz/aux;)V
    //   103: iload_2
    //   104: goto -40 -> 64
    //   107: aload_0
    //   108: getfield 76	z/dA:null	Ljava/util/List;
    //   111: ifnonnull +10 -> 121
    //   114: iconst_0
    //   115: iconst_1
    //   116: dup
    //   117: pop2
    //   118: goto +12 -> 130
    //   121: aload_0
    //   122: getfield 76	z/dA:null	Ljava/util/List;
    //   125: invokeinterface 100 1 0
    //   130: istore_3
    //   131: iconst_0
    //   132: iconst_1
    //   133: dup
    //   134: pop2
    //   135: dup
    //   136: istore_2
    //   137: iload_3
    //   138: if_icmpge +42 -> 180
    //   141: aload_0
    //   142: getfield 76	z/dA:null	Ljava/util/List;
    //   145: iload_2
    //   146: invokeinterface 113 2 0
    //   151: checkcast 60	z/ca
    //   154: astore 4
    //   156: aload_1
    //   157: aload 4
    //   159: dup_x1
    //   160: getfield 115	z/ca:new	Ljava/lang/String;
    //   163: iconst_0
    //   164: iconst_1
    //   165: dup
    //   166: iinc 2 1
    //   169: pop2
    //   170: invokevirtual 117	z/auX:this	(Ljava/lang/String;Z)Lz/aux;
    //   173: invokevirtual 120	z/ca:this	(Lz/aux;)V
    //   176: iload_2
    //   177: goto -40 -> 137
    //   180: aload_0
    //   181: getfield 86	z/dA:byte	Ljava/util/List;
    //   184: ifnonnull +10 -> 194
    //   187: iconst_0
    //   188: iconst_1
    //   189: dup
    //   190: pop2
    //   191: goto +12 -> 203
    //   194: aload_0
    //   195: getfield 86	z/dA:byte	Ljava/util/List;
    //   198: invokeinterface 100 1 0
    //   203: istore_3
    //   204: iconst_0
    //   205: iconst_1
    //   206: dup
    //   207: pop2
    //   208: dup
    //   209: istore_2
    //   210: iload_3
    //   211: if_icmpge +52 -> 263
    //   214: aload_0
    //   215: getfield 86	z/dA:byte	Ljava/util/List;
    //   218: iload_2
    //   219: invokeinterface 113 2 0
    //   224: checkcast 81	z/LPT8
    //   227: astore 4
    //   229: aload_1
    //   230: aload 4
    //   232: getfield 122	z/LPT8:byte	I
    //   235: aload 4
    //   237: dup_x2
    //   238: getfield 124	z/LPT8:void	Lz/Qa;
    //   241: aload 4
    //   243: getfield 125	z/LPT8:new	Ljava/lang/String;
    //   246: iconst_1
    //   247: dup
    //   248: dup
    //   249: iinc 2 1
    //   252: pop2
    //   253: invokevirtual 127	z/auX:this	(ILz/Qa;Ljava/lang/String;Z)Lz/aux;
    //   256: invokevirtual 128	z/LPT8:this	(Lz/aux;)V
    //   259: iload_2
    //   260: goto -50 -> 210
    //   263: aload_0
    //   264: getfield 88	z/dA:new	Ljava/util/List;
    //   267: ifnonnull +10 -> 277
    //   270: iconst_0
    //   271: iconst_1
    //   272: dup
    //   273: pop2
    //   274: goto +12 -> 286
    //   277: aload_0
    //   278: getfield 88	z/dA:new	Ljava/util/List;
    //   281: invokeinterface 100 1 0
    //   286: istore_3
    //   287: iconst_0
    //   288: iconst_1
    //   289: dup
    //   290: pop2
    //   291: dup
    //   292: istore_2
    //   293: iload_3
    //   294: if_icmpge +52 -> 346
    //   297: aload_0
    //   298: getfield 88	z/dA:new	Ljava/util/List;
    //   301: iload_2
    //   302: invokeinterface 113 2 0
    //   307: checkcast 81	z/LPT8
    //   310: astore 4
    //   312: aload_1
    //   313: aload 4
    //   315: getfield 122	z/LPT8:byte	I
    //   318: aload 4
    //   320: dup_x2
    //   321: getfield 124	z/LPT8:void	Lz/Qa;
    //   324: aload 4
    //   326: getfield 125	z/LPT8:new	Ljava/lang/String;
    //   329: iconst_0
    //   330: iconst_1
    //   331: dup
    //   332: iinc 2 1
    //   335: pop2
    //   336: invokevirtual 127	z/auX:this	(ILz/Qa;Ljava/lang/String;Z)Lz/aux;
    //   339: invokevirtual 128	z/LPT8:this	(Lz/aux;)V
    //   342: iload_2
    //   343: goto -50 -> 293
    //   346: aload_0
    //   347: getfield 94	z/dA:void	Ljava/util/List;
    //   350: ifnonnull +10 -> 360
    //   353: iconst_0
    //   354: iconst_1
    //   355: dup
    //   356: pop2
    //   357: goto +12 -> 369
    //   360: aload_0
    //   361: getfield 94	z/dA:void	Ljava/util/List;
    //   364: invokeinterface 100 1 0
    //   369: istore_3
    //   370: iconst_0
    //   371: iconst_1
    //   372: dup
    //   373: pop2
    //   374: dup
    //   375: istore_2
    //   376: iload_3
    //   377: if_icmpge +27 -> 404
    //   380: aload_1
    //   381: aload_0
    //   382: getfield 94	z/dA:void	Ljava/util/List;
    //   385: iload_2
    //   386: iinc 2 1
    //   389: invokeinterface 113 2 0
    //   394: checkcast 130	z/lpt6
    //   397: invokevirtual 132	z/auX:this	(Lz/lpt6;)V
    //   400: iload_2
    //   401: goto -25 -> 376
    //   404: aload_1
    //   405: invokevirtual 134	z/auX:this	()V
    //   408: return
    // Line number table:
    //   Java source line #273	-> byte code offset #0
    //   Java source line #274	-> byte code offset #28
    //   Java source line #275	-> byte code offset #31
    //   Java source line #278	-> byte code offset #33
    //   Java source line #279	-> byte code offset #58
    //   Java source line #280	-> byte code offset #68
    //   Java source line #281	-> byte code offset #83
    //   Java source line #279	-> byte code offset #103
    //   Java source line #283	-> byte code offset #107
    //   Java source line #284	-> byte code offset #131
    //   Java source line #285	-> byte code offset #141
    //   Java source line #286	-> byte code offset #156
    //   Java source line #284	-> byte code offset #176
    //   Java source line #288	-> byte code offset #180
    //   Java source line #289	-> byte code offset #204
    //   Java source line #290	-> byte code offset #214
    //   Java source line #291	-> byte code offset #229
    //   Java source line #289	-> byte code offset #259
    //   Java source line #294	-> byte code offset #263
    //   Java source line #295	-> byte code offset #281
    //   Java source line #296	-> byte code offset #287
    //   Java source line #297	-> byte code offset #297
    //   Java source line #298	-> byte code offset #312
    //   Java source line #296	-> byte code offset #342
    //   Java source line #301	-> byte code offset #346
    //   Java source line #302	-> byte code offset #370
    //   Java source line #303	-> byte code offset #380
    //   Java source line #302	-> byte code offset #400
    //   Java source line #305	-> byte code offset #404
    //   Java source line #306	-> byte code offset #408
    // Local variable table:
    //   start	length	slot	name	signature
    //   0	409	0	a	dA
    //   0	409	1	a	cOn
  }
}
