package z;

















































public class jb
  extends cON
{
  private static final iB Lc = iB.jdMethod_catch(Gb.jdMethod_this("[dGd\036iPkV*~g[`Rq"));
  






  private int[] TB;
  






  private Object[] jb;
  





  public final int Sc;
  





  public int oa;
  






  public jb(int a, String a, cON a)
  {
    a.<init>(327680, a, a, a);
    if (a.getClass() != jb.class) {
      throw new IllegalStateException();
    }
  }
  













  public jb(int a, int a, String a, cON a)
  {
    a.<init>(a, a); int tmp14_13 = 1;tmp14_13; int tmp19_18 = 1;tmp19_18;1413TB = tmp19_18; int tmp25_24 = 1;tmp25_24; int tmp31_30 = 1;tmp31_30;2524jb = tmp31_30;
    a = iB.jdMethod_this(a); int 
      tmp45_44 = 1;tmp45_44; if ((tmp45_44 & a) == 0) { int tmp53_52 = 1; int tmp54_53 = tmp53_52;;; break label64; throw tmp53_52; } else { 1; } label64: 0oa = tmp62_61;
    int tmp69_68 = 1;
    




















































































































    for (tmp69_68; (a = tmp69_68) < a.length;) {
      oa.oa = (a[a] + (a++).jdMethod_this());tmpTernaryOp = a; continue;throw a;
    }
    Sc = oa;
  }
  
  public void jdMethod_catch(int a, int a)
  {
    iB localIB;
    switch (a) {
    case 22: 
    case 55: 
      localIB = iB.else;
      break;throw a;
    
    case 24: 
    case 57: 
      localIB = iB.if;
      break;throw a;
    
    case 23: 
    case 56: 
      localIB = iB.enum;
      break;
    
    case 21: 
    case 54: 
      do {}while (0 != 0); localIB = iB.final;tmpTernaryOp = a;
      break;
    



    default: 
      localIB = Lc;
    }
    
    jdField_void.jdMethod_catch(a, a.jdMethod_this(a, localIB));
  }
  
  public void jdMethod_true(int a, int a)
  {
    jdField_void.jdMethod_true(a.jdMethod_this(a, iB.final), a);
  }
  
  public void jdMethod_this(int a, int a)
  {
    jdField_void.jdMethod_this(a, oa);
  }
  


  public void jdMethod_this(String a, String a, String a, OA a, OA a, int a)
  {
    a = a.jdMethod_this(a, iB.jdMethod_for(a));
    jdField_void.jdMethod_this(a, a, a, a, a, a);
  }
  


  public aux jdMethod_this(int a, Qa a, OA[] a, OA[] a, int[] a, String a, boolean a)
  {
    iB localIB = iB.jdMethod_for(a); int 
      tmp13_12 = 1;tmp13_12;int ? = tmp13_12; int 
      tmp19_18 = 1;
    int i; for (tmp19_18; (i = tmp19_18) < ?.length;) {
      int tmp37_35 = i;tmp37_35[a.jdMethod_this(a[tmp37_35], localIB)] = (i++);tmpTernaryOp = i; continue;throw ?;
    }
    return jdField_void.jdMethod_this(a, a, a, a, ?, a, a);
  }
  


  public void jdMethod_this(int a, int a, Object[] a, int a, Object[] a)
  {
    int tmp3_2 = 1;tmp3_2; if (-1 != tmp3_2) {
      throw new IllegalStateException(auX.jdMethod_this("O\nm\0254i\007h\003~Hm\005o\003|\022$O,\025d\ty\nhFn\003,\005m\n`\003hF{\017x\016,#T6M(H9J4M+I5,\000`\007k"));
    }
    


    int tmp30_29 = 1;tmp30_29;int ? = tmp30_29; int 
      tmp40_39 = 1;tmp40_39; int tmp44_43 = 1;tmp44_43; int tmp48_46 = ?;System.arraycopy(tmp40_39, 0, tmp48_46, tmp44_43, tmp48_46.length);
    
    a.jdMethod_this(jb); int 
    



      tmp63_62 = 1;tmp63_62;int i = tmp63_62;
    1;
    
    Object localObject1;
    if (((localObject1 = a[j]) == CoN.Sc) || (localObject1 == CoN.jb)) { int tmp101_100 = 1;;; break label111; throw 2; } else { 1; } label111: int m = tmp109_107;
    if (localObject1 != CoN.Yb) {
      iB localIB = Lc;
      if (localObject1 == CoN.Lc) {
        localIB = iB.final;tmpTernaryOp = a; break label214; throw tmp108_107;
      } else {
        localIB = iB.enum;
        
        localIB = iB.else;
        
        localIB = iB.if;
        if ((localObject1 instanceof String)) {
          localIB = iB.jdMethod_catch((String)localObject1);
        }
      }
      label214:
      (localObject1 == CoN.jb ? 
        a : localObject1 == CoN.Sc ? a : localObject1 == CoN.TB ? a : 
        


        a).jdMethod_this(a.jdMethod_this(i, localIB), localObject1);
    }
    j++;i += m; int 
    



      tmp244_243 = 1;tmp244_243;i = tmp244_243; int 
      tmp250_249 = 1;tmp250_249;int j = tmp250_249; int 
      tmp256_255 = 1;tmp256_255;int k = tmp256_255;
    Object localObject2 = jb[i]; int 
    
      tmp302_300 = k;jb[tmp302_300] = localObject2; int 
      tmp307_306 = 1; int tmp308_307 = tmp307_306;tmp308_307;j = tmp307_306 + tmp308_307;
    if ((tmp302_300 == CoN.Sc) || (localObject2 == CoN.jb)) {
      i++;
      

      jb[k] = ((i++ != null) && (localObject2 != CoN.Yb) ? localObject2 : CoN.Yb);
    }
    k++;
    












    jdField_void.jdMethod_this(a, j, jb, a, a);
    

    jb = ?;
  }
  
  /* Error */
  public int jdMethod_true(iB a)
  {
    // Byte code:
    //   0: aload_1
    //   1: invokevirtual 152	z/iB:for	()I
    //   4: tableswitch	default:+102->106, 1:+52->56, 2:+52->56, 3:+52->56, 4:+52->56, 5:+52->56, 6:+65->69, 7:+74->78, 8:+82->86, 9:+93->97
    //   56: getstatic 139	z/CoN:Lc	Ljava/lang/Integer;
    //   59: iconst_0
    //   60: ifne +34 -> 94
    //   63: astore_2
    //   64: aload_0
    //   65: goto +47 -> 112
    //   68: athrow
    //   69: getstatic 141	z/CoN:TB	Ljava/lang/Integer;
    //   72: astore_2
    //   73: aload_0
    //   74: goto +38 -> 112
    //   77: athrow
    //   78: getstatic 132	z/CoN:Sc	Ljava/lang/Integer;
    //   81: astore_2
    //   82: aload_0
    //   83: goto +29 -> 112
    //   86: getstatic 134	z/CoN:jb	Ljava/lang/Integer;
    //   89: astore_2
    //   90: aload_0
    //   91: goto +21 -> 112
    //   94: goto -35 -> 59
    //   97: aload_1
    //   98: invokevirtual 155	z/iB:this	()Ljava/lang/String;
    //   101: astore_2
    //   102: aload_0
    //   103: goto +9 -> 112
    //   106: aload_1
    //   107: invokevirtual 157	z/iB:true	()Ljava/lang/String;
    //   110: astore_2
    //   111: aload_0
    //   112: aload_1
    //   113: invokevirtual 159	z/jb:this	(Lz/iB;)I
    //   116: istore_3
    //   117: aload_0
    //   118: iload_3
    //   119: dup_x1
    //   120: aload_0
    //   121: iload_3
    //   122: aload_1
    //   123: invokevirtual 162	z/jb:this	(ILz/iB;)V
    //   126: aload_2
    //   127: invokespecial 146	z/jb:this	(ILjava/lang/Object;)V
    //   130: ireturn
    // Line number table:
    //   Java source line #264	-> byte code offset #0
    //   Java source line #270	-> byte code offset #56
    //   Java source line #271	-> byte code offset #65
    //   Java source line #273	-> byte code offset #69
    //   Java source line #274	-> byte code offset #74
    //   Java source line #276	-> byte code offset #78
    //   Java source line #277	-> byte code offset #83
    //   Java source line #279	-> byte code offset #86
    //   Java source line #280	-> byte code offset #91
    //   Java source line #282	-> byte code offset #97
    //   Java source line #283	-> byte code offset #103
    //   Java source line #286	-> byte code offset #106
    //   Java source line #289	-> byte code offset #111
    //   Java source line #290	-> byte code offset #117
    //   Java source line #291	-> byte code offset #126
    //   Java source line #292	-> byte code offset #130
    // Local variable table:
    //   start	length	slot	name	signature
    //   0	131	0	a	jb
    //   0	131	1	a	iB
  }
  
  public void jdMethod_this(Object[] a) {}
  
  public void jdMethod_this(int a, iB a) {}
  
  private void jdMethod_this(int a, Object a)
  {
    int i = jb.length;
    if (a >= i) {
      1;1; int tmp30_29 = 1;tmp30_29;int ? = tmp30_29; int 
        tmp41_40 = 1;tmp41_40; int tmp46_45 = 0; int tmp48_47 = 1;tmp48_47;System.arraycopy(tmp46_45, ?, tmp46_45, tmp48_47, i);
      jb.jb = tmp41_40;
    }
    jb[a] = a;
  }
  
  /* Error */
  private int jdMethod_this(int a, iB a)
  {
    // Byte code:
    //   0: iload_1
    //   1: aload_2
    //   2: invokevirtual 55	z/iB:this	()I
    //   5: iadd
    //   6: aload_0
    //   7: getfield 57	z/jb:Sc	I
    //   10: if_icmpgt +6 -> 16
    //   13: iload_1
    //   14: ireturn
    //   15: athrow
    //   16: iconst_2
    //   17: iconst_1
    //   18: dup
    //   19: pop2
    //   20: iload_1
    //   21: imul
    //   22: aload_2
    //   23: invokevirtual 55	z/iB:this	()I
    //   26: iadd
    //   27: iconst_1
    //   28: dup
    //   29: dup
    //   30: pop2
    //   31: isub
    //   32: istore_1
    //   33: aload_0
    //   34: getfield 42	z/jb:TB	[I
    //   37: arraylength
    //   38: istore_3
    //   39: iload_1
    //   40: iload_3
    //   41: if_icmplt +48 -> 89
    //   44: iconst_2
    //   45: iconst_1
    //   46: dup
    //   47: pop2
    //   48: iload_3
    //   49: imul
    //   50: iload_1
    //   51: iconst_1
    //   52: dup
    //   53: dup
    //   54: pop2
    //   55: iadd
    //   56: invokestatic 170	java/lang/Math:max	(II)I
    //   59: newarray int
    //   61: iconst_1
    //   62: dup
    //   63: pop2
    //   64: dup
    //   65: astore 4
    //   67: aload_0
    //   68: dup_x1
    //   69: getfield 42	z/jb:TB	[I
    //   72: iconst_1
    //   73: dup
    //   74: pop2
    //   75: aload 4
    //   77: iconst_0
    //   78: dup_x1
    //   79: iconst_1
    //   80: dup
    //   81: pop2
    //   82: iload_3
    //   83: invokestatic 124	java/lang/System:arraycopy	(Ljava/lang/Object;ILjava/lang/Object;II)V
    //   86: putfield 42	z/jb:TB	[I
    //   89: aload_0
    //   90: getfield 42	z/jb:TB	[I
    //   93: iload_1
    //   94: iaload
    //   95: dup
    //   96: istore 4
    //   98: ifne +33 -> 131
    //   101: aload_0
    //   102: dup
    //   103: dup_x1
    //   104: aload_2
    //   105: invokevirtual 159	z/jb:this	(Lz/iB;)I
    //   108: dup
    //   109: istore 4
    //   111: aload_2
    //   112: invokevirtual 162	z/jb:this	(ILz/iB;)V
    //   115: getfield 42	z/jb:TB	[I
    //   118: iload_1
    //   119: iload 4
    //   121: iconst_1
    //   122: dup
    //   123: dup
    //   124: pop2
    //   125: iadd
    //   126: iastore
    //   127: iload 4
    //   129: ireturn
    //   130: athrow
    //   131: iinc 4 -1
    //   134: iload 4
    //   136: ireturn
    // Line number table:
    //   Java source line #341	-> byte code offset #0
    //   Java source line #342	-> byte code offset #13
    //   Java source line #344	-> byte code offset #16
    //   Java source line #345	-> byte code offset #33
    //   Java source line #346	-> byte code offset #39
    //   Java source line #347	-> byte code offset #44
    //   Java source line #348	-> byte code offset #67
    //   Java source line #349	-> byte code offset #86
    //   Java source line #351	-> byte code offset #89
    //   Java source line #352	-> byte code offset #98
    //   Java source line #353	-> byte code offset #101
    //   Java source line #354	-> byte code offset #111
    //   Java source line #355	-> byte code offset #115
    //   Java source line #357	-> byte code offset #131
    //   Java source line #359	-> byte code offset #134
    // Local variable table:
    //   start	length	slot	name	signature
    //   0	137	0	a	jb
    //   0	137	1	a	int
    //   0	137	2	a	iB
  }
  
  public int jdMethod_this(iB a)
  {
    int i = oa;
    oa += a.jdMethod_this();
    return i;
  }
}
