package z;

import java.util.ArrayList;
import java.util.List;















































public class k
  extends P
{
  private String jdField_if;
  public String jdField_null;
  public boolean jdField_byte;
  public boolean jdField_new;
  public List<String> jdField_void;
  
  public k(cOn a, Gb a)
  {
    a.<init>(327680, a, a); int tmp14_13 = 1;tmp14_13;0jdField_byte = tmp14_13; int tmp20_19 = 1;tmp20_19;jdField_new_of_type_Boolean = tmp20_19;a;a.<init>();jdField_void_of_type_JavaUtilList = a;
  }
  
  /* Error */
  public auX jdMethod_this(int a, String a, String a)
  {
    // Byte code:
    //   0: aload_0
    //   1: iload_1
    //   2: aload_2
    //   3: aload_3
    //   4: aconst_null
    //   5: dup
    //   6: invokespecial 42	z/P:this	(ILjava/lang/String;Ljava/lang/String;Ljava/lang/String;Ljava/lang/Object;)Lz/auX;
    //   9: areturn
    // Line number table:
    //   Java source line #68	-> byte code offset #0
    // Local variable table:
    //   start	length	slot	name	signature
    //   0	10	0	a	k
    //   0	10	1	a	int
    //   0	10	2	a	String
    //   0	10	3	a	String
  }
  
  public void jdMethod_this(int a, int a, String a, String a, String a, String[] a)
  {
    int tmp7_6 = 1;tmp7_6;46.jdMethod_this(tmp7_6, a, a, null, a, a); int 
      tmp20_19 = 1;tmp20_19;
    if ((a = a.lastIndexOf(tmp20_19)) > 0) {
      int tmp35_34 = ;;;; break label55; throw a;
    } else {
      jdField_if = ""; } label55: 
    
      jdField_null = a;
    int tmp65_64 = 1;tmp65_64; if ((0x200 & tmp65_64) != 0) { int tmp72_71 = 1; int tmp73_72 = tmp72_71;;; break label83; throw tmp72_71; } else { 1; } label83: 0jdField_byte = tmp81_80;
  }
  



  public void jdMethod_this(String a, String a) {}
  



  public void jdMethod_this(String a, String a, String a) {}
  



  public aux jdMethod_this(String a, boolean a)
  {
    return null;
  }
  


  public aux jdMethod_this(int a, Qa a, String a, boolean a)
  {
    return null;
  }
  
  public void jdMethod_this(lpt6 a) {}
  
  public void jdMethod_this(String a, String a, String a, int a) {}
  
  /* Error */
  public auX jdMethod_this(int a, String a, String a, String a, Object a)
  {
    // Byte code:
    //   0: aload_0
    //   1: dup
    //   2: getfield 76	z/k:jdField_new_of_type_ZGb	Lz/Gb;
    //   5: swap
    //   6: getfield 78	z/k:jdField_void_of_type_JavaLangString	Ljava/lang/String;
    //   9: aload_2
    //   10: aload_3
    //   11: invokevirtual 83	z/Gb:this	(Ljava/lang/String;Ljava/lang/String;Ljava/lang/String;)Ljava/lang/String;
    //   14: astore 4
    //   16: ldc 85
    //   18: invokestatic 90	org/powerbot/bot/EventDispatcher:this	(Ljava/lang/Object;)Ljava/lang/String;
    //   21: aload 4
    //   23: invokevirtual 94	java/lang/String:equals	(Ljava/lang/Object;)Z
    //   26: ifeq +6 -> 32
    //   29: aconst_null
    //   30: areturn
    //   31: athrow
    //   32: iload_1
    //   33: iconst_5
    //   34: iconst_1
    //   35: dup
    //   36: pop2
    //   37: iand
    //   38: ifne +128 -> 166
    //   41: iload_1
    //   42: bipush 16
    //   44: iconst_1
    //   45: dup
    //   46: pop2
    //   47: iand
    //   48: ifeq +27 -> 75
    //   51: iload_1
    //   52: bipush 8
    //   54: iconst_1
    //   55: dup
    //   56: pop2
    //   57: iand
    //   58: ifeq +17 -> 75
    //   61: aload_3
    //   62: invokevirtual 98	java/lang/String:length	()I
    //   65: iconst_1
    //   66: dup
    //   67: dup
    //   68: pop2
    //   69: if_icmpne +6 -> 75
    //   72: aconst_null
    //   73: areturn
    //   74: athrow
    //   75: ldc 100
    //   77: invokestatic 103	z/Oa:this	(Ljava/lang/Object;)Ljava/lang/String;
    //   80: aload_0
    //   81: getfield 58	z/k:if	Ljava/lang/String;
    //   84: invokevirtual 94	java/lang/String:equals	(Ljava/lang/Object;)Z
    //   87: ifeq +65 -> 152
    //   90: aload 4
    //   92: aload_2
    //   93: invokevirtual 94	java/lang/String:equals	(Ljava/lang/Object;)Z
    //   96: ifeq +56 -> 152
    //   99: getstatic 109	java/lang/System:out	Ljava/io/PrintStream;
    //   102: new 111	java/lang/StringBuilder
    //   105: dup
    //   106: invokespecial 112	java/lang/StringBuilder:<init>	()V
    //   109: iconst_0
    //   110: ldc 114
    //   112: invokestatic 90	org/powerbot/bot/EventDispatcher:this	(Ljava/lang/Object;)Ljava/lang/String;
    //   115: invokevirtual 118	java/lang/StringBuilder:insert	(ILjava/lang/String;)Ljava/lang/StringBuilder;
    //   118: aload_0
    //   119: getfield 62	z/k:null	Ljava/lang/String;
    //   122: invokevirtual 122	java/lang/StringBuilder:append	(Ljava/lang/String;)Ljava/lang/StringBuilder;
    //   125: ldc 124
    //   127: invokestatic 103	z/Oa:this	(Ljava/lang/Object;)Ljava/lang/String;
    //   130: invokevirtual 122	java/lang/StringBuilder:append	(Ljava/lang/String;)Ljava/lang/StringBuilder;
    //   133: aload 4
    //   135: invokevirtual 122	java/lang/StringBuilder:append	(Ljava/lang/String;)Ljava/lang/StringBuilder;
    //   138: ldc 126
    //   140: invokestatic 90	org/powerbot/bot/EventDispatcher:this	(Ljava/lang/Object;)Ljava/lang/String;
    //   143: invokevirtual 122	java/lang/StringBuilder:append	(Ljava/lang/String;)Ljava/lang/StringBuilder;
    //   146: invokevirtual 130	java/lang/StringBuilder:toString	()Ljava/lang/String;
    //   149: invokevirtual 136	java/io/PrintStream:println	(Ljava/lang/String;)V
    //   152: aload_0
    //   153: iload_1
    //   154: aload_2
    //   155: aload_3
    //   156: aconst_null
    //   157: aload 5
    //   159: invokespecial 42	z/P:this	(ILjava/lang/String;Ljava/lang/String;Ljava/lang/String;Ljava/lang/Object;)Lz/auX;
    //   162: pop
    //   163: goto +77 -> 240
    //   166: aload 4
    //   168: aload_2
    //   169: invokevirtual 94	java/lang/String:equals	(Ljava/lang/Object;)Z
    //   172: ifne +57 -> 229
    //   175: new 138	java/lang/RuntimeException
    //   178: dup
    //   179: new 111	java/lang/StringBuilder
    //   182: dup
    //   183: invokespecial 112	java/lang/StringBuilder:<init>	()V
    //   186: iconst_0
    //   187: ldc -116
    //   189: invokestatic 103	z/Oa:this	(Ljava/lang/Object;)Ljava/lang/String;
    //   192: invokevirtual 118	java/lang/StringBuilder:insert	(ILjava/lang/String;)Ljava/lang/StringBuilder;
    //   195: aload_0
    //   196: getfield 78	z/k:jdField_void_of_type_JavaLangString	Ljava/lang/String;
    //   199: invokevirtual 122	java/lang/StringBuilder:append	(Ljava/lang/String;)Ljava/lang/StringBuilder;
    //   202: bipush 46
    //   204: iconst_1
    //   205: dup
    //   206: pop2
    //   207: invokevirtual 143	java/lang/StringBuilder:append	(C)Ljava/lang/StringBuilder;
    //   210: aload_2
    //   211: invokevirtual 122	java/lang/StringBuilder:append	(Ljava/lang/String;)Ljava/lang/StringBuilder;
    //   214: ldc -111
    //   216: invokestatic 90	org/powerbot/bot/EventDispatcher:this	(Ljava/lang/Object;)Ljava/lang/String;
    //   219: invokevirtual 122	java/lang/StringBuilder:append	(Ljava/lang/String;)Ljava/lang/StringBuilder;
    //   222: invokevirtual 130	java/lang/StringBuilder:toString	()Ljava/lang/String;
    //   225: invokespecial 147	java/lang/RuntimeException:<init>	(Ljava/lang/String;)V
    //   228: athrow
    //   229: aload_0
    //   230: iload_1
    //   231: aload_2
    //   232: aload_3
    //   233: aconst_null
    //   234: aload 5
    //   236: invokespecial 42	z/P:this	(ILjava/lang/String;Ljava/lang/String;Ljava/lang/String;Ljava/lang/Object;)Lz/auX;
    //   239: pop
    //   240: aconst_null
    //   241: areturn
    // Line number table:
    //   Java source line #129	-> byte code offset #0
    //   Java source line #130	-> byte code offset #16
    //   Java source line #131	-> byte code offset #29
    //   Java source line #133	-> byte code offset #32
    //   Java source line #134	-> byte code offset #41
    //   Java source line #135	-> byte code offset #62
    //   Java source line #136	-> byte code offset #72
    //   Java source line #138	-> byte code offset #75
    //   Java source line #139	-> byte code offset #99
    //   Java source line #142	-> byte code offset #152
    //   Java source line #144	-> byte code offset #166
    //   Java source line #145	-> byte code offset #175
    //   Java source line #148	-> byte code offset #229
    //   Java source line #150	-> byte code offset #240
    // Local variable table:
    //   start	length	slot	name	signature
    //   0	242	0	a	k
    //   0	242	1	a	int
    //   0	242	2	a	String
    //   0	242	3	a	String
    //   0	242	4	a	String
    //   0	242	5	a	Object
  }
  
  /* Error */
  public cON jdMethod_this(int a, String a, String a, String a, String[] a)
  {
    // Byte code:
    //   0: aload_0
    //   1: dup
    //   2: getfield 76	z/k:jdField_new_of_type_ZGb	Lz/Gb;
    //   5: swap
    //   6: getfield 78	z/k:jdField_void_of_type_JavaLangString	Ljava/lang/String;
    //   9: aload_2
    //   10: aload_3
    //   11: invokevirtual 154	z/Gb:true	(Ljava/lang/String;Ljava/lang/String;Ljava/lang/String;)Ljava/lang/String;
    //   14: astore 4
    //   16: ldc -100
    //   18: invokestatic 103	z/Oa:this	(Ljava/lang/Object;)Ljava/lang/String;
    //   21: aload 4
    //   23: invokevirtual 94	java/lang/String:equals	(Ljava/lang/Object;)Z
    //   26: ifeq +6 -> 32
    //   29: aconst_null
    //   30: areturn
    //   31: athrow
    //   32: aload_2
    //   33: ldc -98
    //   35: invokestatic 90	org/powerbot/bot/EventDispatcher:this	(Ljava/lang/Object;)Ljava/lang/String;
    //   38: invokevirtual 94	java/lang/String:equals	(Ljava/lang/Object;)Z
    //   41: ifeq +44 -> 85
    //   44: aload_0
    //   45: getfield 24	z/k:byte	Z
    //   48: ifne +37 -> 85
    //   51: iload_1
    //   52: aload_0
    //   53: dup_x1
    //   54: iconst_1
    //   55: dup
    //   56: dup
    //   57: pop2
    //   58: putfield 26	z/k:jdField_new_of_type_Boolean	Z
    //   61: aload_2
    //   62: aload_3
    //   63: aconst_null
    //   64: aload 5
    //   66: invokespecial 160	z/P:this	(ILjava/lang/String;Ljava/lang/String;Ljava/lang/String;[Ljava/lang/String;)Lz/cON;
    //   69: astore 6
    //   71: new 7	z/LPt5
    //   74: dup
    //   75: aload_0
    //   76: ldc 19
    //   78: aload 6
    //   80: invokespecial 163	z/LPt5:<init>	(Lz/k;ILz/cON;)V
    //   83: areturn
    //   84: athrow
    //   85: iload_1
    //   86: iconst_5
    //   87: iconst_1
    //   88: dup
    //   89: pop2
    //   90: iand
    //   91: ifne +103 -> 194
    //   94: ldc 100
    //   96: invokestatic 103	z/Oa:this	(Ljava/lang/Object;)Ljava/lang/String;
    //   99: aload_0
    //   100: getfield 58	z/k:if	Ljava/lang/String;
    //   103: invokevirtual 94	java/lang/String:equals	(Ljava/lang/Object;)Z
    //   106: ifeq +77 -> 183
    //   109: aload_2
    //   110: ldc -91
    //   112: invokestatic 90	org/powerbot/bot/EventDispatcher:this	(Ljava/lang/Object;)Ljava/lang/String;
    //   115: invokevirtual 169	java/lang/String:startsWith	(Ljava/lang/String;)Z
    //   118: ifne +65 -> 183
    //   121: aload 4
    //   123: aload_2
    //   124: invokevirtual 94	java/lang/String:equals	(Ljava/lang/Object;)Z
    //   127: ifeq +56 -> 183
    //   130: getstatic 109	java/lang/System:out	Ljava/io/PrintStream;
    //   133: new 111	java/lang/StringBuilder
    //   136: dup
    //   137: invokespecial 112	java/lang/StringBuilder:<init>	()V
    //   140: iconst_0
    //   141: ldc -85
    //   143: invokestatic 103	z/Oa:this	(Ljava/lang/Object;)Ljava/lang/String;
    //   146: invokevirtual 118	java/lang/StringBuilder:insert	(ILjava/lang/String;)Ljava/lang/StringBuilder;
    //   149: aload_0
    //   150: getfield 62	z/k:null	Ljava/lang/String;
    //   153: invokevirtual 122	java/lang/StringBuilder:append	(Ljava/lang/String;)Ljava/lang/StringBuilder;
    //   156: ldc -83
    //   158: invokestatic 90	org/powerbot/bot/EventDispatcher:this	(Ljava/lang/Object;)Ljava/lang/String;
    //   161: invokevirtual 122	java/lang/StringBuilder:append	(Ljava/lang/String;)Ljava/lang/StringBuilder;
    //   164: aload 4
    //   166: invokevirtual 122	java/lang/StringBuilder:append	(Ljava/lang/String;)Ljava/lang/StringBuilder;
    //   169: ldc -81
    //   171: invokestatic 103	z/Oa:this	(Ljava/lang/Object;)Ljava/lang/String;
    //   174: invokevirtual 122	java/lang/StringBuilder:append	(Ljava/lang/String;)Ljava/lang/StringBuilder;
    //   177: invokevirtual 130	java/lang/StringBuilder:toString	()Ljava/lang/String;
    //   180: invokevirtual 136	java/io/PrintStream:println	(Ljava/lang/String;)V
    //   183: aload_0
    //   184: iload_1
    //   185: aload_2
    //   186: aload_3
    //   187: aconst_null
    //   188: aload 5
    //   190: invokespecial 160	z/P:this	(ILjava/lang/String;Ljava/lang/String;Ljava/lang/String;[Ljava/lang/String;)Lz/cON;
    //   193: areturn
    //   194: aload 4
    //   196: aload_2
    //   197: invokevirtual 94	java/lang/String:equals	(Ljava/lang/Object;)Z
    //   200: ifne +61 -> 261
    //   203: new 138	java/lang/RuntimeException
    //   206: dup
    //   207: new 111	java/lang/StringBuilder
    //   210: dup
    //   211: invokespecial 112	java/lang/StringBuilder:<init>	()V
    //   214: iconst_0
    //   215: ldc -79
    //   217: invokestatic 90	org/powerbot/bot/EventDispatcher:this	(Ljava/lang/Object;)Ljava/lang/String;
    //   220: invokevirtual 118	java/lang/StringBuilder:insert	(ILjava/lang/String;)Ljava/lang/StringBuilder;
    //   223: aload_0
    //   224: getfield 78	z/k:jdField_void_of_type_JavaLangString	Ljava/lang/String;
    //   227: invokevirtual 122	java/lang/StringBuilder:append	(Ljava/lang/String;)Ljava/lang/StringBuilder;
    //   230: bipush 46
    //   232: iconst_1
    //   233: dup
    //   234: pop2
    //   235: invokevirtual 143	java/lang/StringBuilder:append	(C)Ljava/lang/StringBuilder;
    //   238: aload_2
    //   239: invokevirtual 122	java/lang/StringBuilder:append	(Ljava/lang/String;)Ljava/lang/StringBuilder;
    //   242: aload_3
    //   243: invokevirtual 122	java/lang/StringBuilder:append	(Ljava/lang/String;)Ljava/lang/StringBuilder;
    //   246: ldc -77
    //   248: invokestatic 103	z/Oa:this	(Ljava/lang/Object;)Ljava/lang/String;
    //   251: invokevirtual 122	java/lang/StringBuilder:append	(Ljava/lang/String;)Ljava/lang/StringBuilder;
    //   254: invokevirtual 130	java/lang/StringBuilder:toString	()Ljava/lang/String;
    //   257: invokespecial 147	java/lang/RuntimeException:<init>	(Ljava/lang/String;)V
    //   260: athrow
    //   261: aload_0
    //   262: iload_1
    //   263: aload_2
    //   264: aload_3
    //   265: aconst_null
    //   266: aload 5
    //   268: invokespecial 160	z/P:this	(ILjava/lang/String;Ljava/lang/String;Ljava/lang/String;[Ljava/lang/String;)Lz/cON;
    //   271: areturn
    // Line number table:
    //   Java source line #156	-> byte code offset #0
    //   Java source line #157	-> byte code offset #16
    //   Java source line #158	-> byte code offset #29
    //   Java source line #160	-> byte code offset #32
    //   Java source line #161	-> byte code offset #51
    //   Java source line #162	-> byte code offset #61
    //   Java source line #164	-> byte code offset #71
    //   Java source line #174	-> byte code offset #85
    //   Java source line #175	-> byte code offset #94
    //   Java source line #176	-> byte code offset #124
    //   Java source line #177	-> byte code offset #130
    //   Java source line #180	-> byte code offset #183
    //   Java source line #182	-> byte code offset #194
    //   Java source line #183	-> byte code offset #203
    //   Java source line #187	-> byte code offset #261
    // Local variable table:
    //   start	length	slot	name	signature
    //   0	272	0	a	k
    //   0	272	1	a	int
    //   0	272	2	a	String
    //   0	272	3	a	String
    //   0	272	4	a	String
    //   0	272	5	a	String[]
  }
  
  public cON jdMethod_this(cON a)
  {
    return new n(a, a, jdField_new_of_type_ZGb);
  }
  
  /* Error */
  public void jdMethod_this()
  {
    // Byte code:
    //   0: aload_0
    //   1: getfield 33	z/k:jdField_void_of_type_JavaUtilList	Ljava/util/List;
    //   4: invokeinterface 192 1 0
    //   9: ifeq +71 -> 80
    //   12: aload_0
    //   13: getfield 26	z/k:jdField_new_of_type_Boolean	Z
    //   16: ifeq +558 -> 574
    //   19: aload_0
    //   20: dup
    //   21: getfield 194	z/k:jdField_void_of_type_ZCOn	Lz/cOn;
    //   24: sipush 4104
    //   27: iconst_1
    //   28: dup
    //   29: pop2
    //   30: ldc -60
    //   32: invokestatic 90	org/powerbot/bot/EventDispatcher:this	(Ljava/lang/Object;)Ljava/lang/String;
    //   35: ldc -58
    //   37: invokestatic 103	z/Oa:this	(Ljava/lang/Object;)Ljava/lang/String;
    //   40: aconst_null
    //   41: dup
    //   42: invokevirtual 201	z/cOn:this	(ILjava/lang/String;Ljava/lang/String;Ljava/lang/String;[Ljava/lang/String;)Lz/cON;
    //   45: astore_1
    //   46: iconst_0
    //   47: aload_1
    //   48: dup_x1
    //   49: dup_x2
    //   50: sipush 177
    //   53: aload_1
    //   54: invokevirtual 205	z/cON:true	()V
    //   57: iconst_1
    //   58: dup
    //   59: pop2
    //   60: invokevirtual 208	z/cON:this	(I)V
    //   63: iconst_1
    //   64: dup
    //   65: pop2
    //   66: iconst_0
    //   67: iconst_1
    //   68: dup
    //   69: pop2
    //   70: invokevirtual 211	z/cON:this	(II)V
    //   73: invokevirtual 213	z/cON:this	()V
    //   76: goto +499 -> 575
    //   79: athrow
    //   80: aload_0
    //   81: dup
    //   82: getfield 194	z/k:jdField_void_of_type_ZCOn	Lz/cOn;
    //   85: sipush 4104
    //   88: iconst_1
    //   89: dup
    //   90: pop2
    //   91: ldc -41
    //   93: invokestatic 90	org/powerbot/bot/EventDispatcher:this	(Ljava/lang/Object;)Ljava/lang/String;
    //   96: ldc -39
    //   98: invokestatic 103	z/Oa:this	(Ljava/lang/Object;)Ljava/lang/String;
    //   101: aconst_null
    //   102: dup
    //   103: invokevirtual 201	z/cOn:this	(ILjava/lang/String;Ljava/lang/String;Ljava/lang/String;[Ljava/lang/String;)Lz/cON;
    //   106: dup
    //   107: astore_1
    //   108: dup
    //   109: dup_x1
    //   110: dup2
    //   111: dup2
    //   112: dup2
    //   113: dup2
    //   114: dup2
    //   115: dup2
    //   116: dup2
    //   117: invokevirtual 205	z/cON:true	()V
    //   120: new 219	z/OA
    //   123: dup
    //   124: invokespecial 220	z/OA:<init>	()V
    //   127: astore_2
    //   128: new 219	z/OA
    //   131: dup
    //   132: invokespecial 220	z/OA:<init>	()V
    //   135: astore_3
    //   136: new 219	z/OA
    //   139: dup
    //   140: invokespecial 220	z/OA:<init>	()V
    //   143: astore 4
    //   145: aload_2
    //   146: aload_3
    //   147: aload 4
    //   149: ldc -34
    //   151: invokestatic 90	org/powerbot/bot/EventDispatcher:this	(Ljava/lang/Object;)Ljava/lang/String;
    //   154: invokevirtual 225	z/cON:this	(Lz/OA;Lz/OA;Lz/OA;Ljava/lang/String;)V
    //   157: aload_2
    //   158: invokevirtual 228	z/cON:this	(Lz/OA;)V
    //   161: bipush 25
    //   163: iconst_1
    //   164: dup
    //   165: pop2
    //   166: iconst_0
    //   167: iconst_1
    //   168: dup
    //   169: pop2
    //   170: invokevirtual 231	z/cON:catch	(II)V
    //   173: sipush 184
    //   176: iconst_1
    //   177: dup
    //   178: pop2
    //   179: ldc -23
    //   181: invokestatic 103	z/Oa:this	(Ljava/lang/Object;)Ljava/lang/String;
    //   184: ldc -21
    //   186: invokestatic 90	org/powerbot/bot/EventDispatcher:this	(Ljava/lang/Object;)Ljava/lang/String;
    //   189: ldc -39
    //   191: invokestatic 103	z/Oa:this	(Ljava/lang/Object;)Ljava/lang/String;
    //   194: iconst_0
    //   195: iconst_1
    //   196: dup
    //   197: pop2
    //   198: invokevirtual 238	z/cON:this	(ILjava/lang/String;Ljava/lang/String;Ljava/lang/String;Z)V
    //   201: aload_3
    //   202: invokevirtual 228	z/cON:this	(Lz/OA;)V
    //   205: sipush 176
    //   208: iconst_1
    //   209: dup
    //   210: pop2
    //   211: invokevirtual 208	z/cON:this	(I)V
    //   214: aload 4
    //   216: invokevirtual 228	z/cON:this	(Lz/OA;)V
    //   219: sipush 182
    //   222: iconst_1
    //   223: dup
    //   224: pop2
    //   225: ldc -34
    //   227: invokestatic 90	org/powerbot/bot/EventDispatcher:this	(Ljava/lang/Object;)Ljava/lang/String;
    //   230: ldc -16
    //   232: invokestatic 103	z/Oa:this	(Ljava/lang/Object;)Ljava/lang/String;
    //   235: ldc -14
    //   237: invokestatic 90	org/powerbot/bot/EventDispatcher:this	(Ljava/lang/Object;)Ljava/lang/String;
    //   240: iconst_0
    //   241: iconst_1
    //   242: dup
    //   243: pop2
    //   244: invokevirtual 238	z/cON:this	(ILjava/lang/String;Ljava/lang/String;Ljava/lang/String;Z)V
    //   247: bipush 58
    //   249: iconst_1
    //   250: dup
    //   251: pop2
    //   252: iconst_1
    //   253: dup
    //   254: dup
    //   255: pop2
    //   256: invokevirtual 231	z/cON:catch	(II)V
    //   259: sipush 187
    //   262: iconst_1
    //   263: dup
    //   264: pop2
    //   265: ldc -12
    //   267: invokestatic 103	z/Oa:this	(Ljava/lang/Object;)Ljava/lang/String;
    //   270: invokevirtual 247	z/cON:this	(ILjava/lang/String;)V
    //   273: bipush 89
    //   275: iconst_1
    //   276: dup
    //   277: pop2
    //   278: invokevirtual 208	z/cON:this	(I)V
    //   281: bipush 25
    //   283: iconst_1
    //   284: dup
    //   285: pop2
    //   286: iconst_1
    //   287: dup
    //   288: dup
    //   289: pop2
    //   290: invokevirtual 231	z/cON:catch	(II)V
    //   293: sipush 183
    //   296: iconst_1
    //   297: dup
    //   298: pop2
    //   299: ldc -7
    //   301: invokestatic 90	org/powerbot/bot/EventDispatcher:this	(Ljava/lang/Object;)Ljava/lang/String;
    //   304: ldc -5
    //   306: invokestatic 103	z/Oa:this	(Ljava/lang/Object;)Ljava/lang/String;
    //   309: ldc -3
    //   311: invokestatic 90	org/powerbot/bot/EventDispatcher:this	(Ljava/lang/Object;)Ljava/lang/String;
    //   314: iconst_0
    //   315: iconst_1
    //   316: dup
    //   317: pop2
    //   318: invokevirtual 238	z/cON:this	(ILjava/lang/String;Ljava/lang/String;Ljava/lang/String;Z)V
    //   321: sipush 191
    //   324: iconst_1
    //   325: dup
    //   326: pop2
    //   327: invokevirtual 208	z/cON:this	(I)V
    //   330: iconst_3
    //   331: iconst_1
    //   332: dup
    //   333: pop2
    //   334: iconst_2
    //   335: iconst_1
    //   336: dup
    //   337: pop2
    //   338: invokevirtual 211	z/cON:this	(II)V
    //   341: invokevirtual 213	z/cON:this	()V
    //   344: getfield 26	z/k:jdField_new_of_type_Boolean	Z
    //   347: ifeq +34 -> 381
    //   350: aload_0
    //   351: dup
    //   352: getfield 194	z/k:jdField_void_of_type_ZCOn	Lz/cOn;
    //   355: bipush 10
    //   357: iconst_1
    //   358: dup
    //   359: pop2
    //   360: ldc -1
    //   362: invokestatic 103	z/Oa:this	(Ljava/lang/Object;)Ljava/lang/String;
    //   365: ldc_w 257
    //   368: invokestatic 90	org/powerbot/bot/EventDispatcher:this	(Ljava/lang/Object;)Ljava/lang/String;
    //   371: aconst_null
    //   372: dup
    //   373: invokevirtual 201	z/cOn:this	(ILjava/lang/String;Ljava/lang/String;Ljava/lang/String;[Ljava/lang/String;)Lz/cON;
    //   376: astore_1
    //   377: goto +32 -> 409
    //   380: athrow
    //   381: aload_0
    //   382: dup
    //   383: getfield 194	z/k:jdField_void_of_type_ZCOn	Lz/cOn;
    //   386: bipush 8
    //   388: iconst_1
    //   389: dup
    //   390: pop2
    //   391: ldc_w 259
    //   394: invokestatic 103	z/Oa:this	(Ljava/lang/Object;)Ljava/lang/String;
    //   397: ldc_w 257
    //   400: invokestatic 90	org/powerbot/bot/EventDispatcher:this	(Ljava/lang/Object;)Ljava/lang/String;
    //   403: aconst_null
    //   404: dup
    //   405: invokevirtual 201	z/cOn:this	(ILjava/lang/String;Ljava/lang/String;Ljava/lang/String;[Ljava/lang/String;)Lz/cON;
    //   408: astore_1
    //   409: getfield 33	z/k:jdField_void_of_type_JavaUtilList	Ljava/util/List;
    //   412: invokeinterface 263 1 0
    //   417: dup
    //   418: astore_2
    //   419: invokeinterface 268 1 0
    //   424: ifeq +124 -> 548
    //   427: aload_2
    //   428: invokeinterface 272 1 0
    //   433: checkcast 48	java/lang/String
    //   436: astore_3
    //   437: new 111	java/lang/StringBuilder
    //   440: dup
    //   441: invokespecial 112	java/lang/StringBuilder:<init>	()V
    //   444: iconst_0
    //   445: ldc_w 274
    //   448: invokestatic 103	z/Oa:this	(Ljava/lang/Object;)Ljava/lang/String;
    //   451: invokevirtual 118	java/lang/StringBuilder:insert	(ILjava/lang/String;)Ljava/lang/StringBuilder;
    //   454: aload_3
    //   455: bipush 47
    //   457: iconst_1
    //   458: dup
    //   459: pop2
    //   460: bipush 36
    //   462: iconst_1
    //   463: dup
    //   464: pop2
    //   465: invokevirtual 278	java/lang/String:replace	(CC)Ljava/lang/String;
    //   468: invokevirtual 122	java/lang/StringBuilder:append	(Ljava/lang/String;)Ljava/lang/StringBuilder;
    //   471: invokevirtual 130	java/lang/StringBuilder:toString	()Ljava/lang/String;
    //   474: astore 4
    //   476: aload_2
    //   477: sipush 179
    //   480: aload_1
    //   481: dup_x1
    //   482: sipush 184
    //   485: aload_1
    //   486: aload_3
    //   487: bipush 47
    //   489: iconst_1
    //   490: dup
    //   491: pop2
    //   492: bipush 46
    //   494: iconst_1
    //   495: dup
    //   496: pop2
    //   497: invokevirtual 278	java/lang/String:replace	(CC)Ljava/lang/String;
    //   500: invokevirtual 281	z/cON:this	(Ljava/lang/Object;)V
    //   503: iconst_1
    //   504: dup
    //   505: pop2
    //   506: aload_0
    //   507: getfield 62	z/k:null	Ljava/lang/String;
    //   510: ldc -41
    //   512: invokestatic 90	org/powerbot/bot/EventDispatcher:this	(Ljava/lang/Object;)Ljava/lang/String;
    //   515: ldc -39
    //   517: invokestatic 103	z/Oa:this	(Ljava/lang/Object;)Ljava/lang/String;
    //   520: iconst_0
    //   521: iconst_1
    //   522: dup
    //   523: pop2
    //   524: invokevirtual 238	z/cON:this	(ILjava/lang/String;Ljava/lang/String;Ljava/lang/String;Z)V
    //   527: iconst_1
    //   528: dup
    //   529: pop2
    //   530: aload_0
    //   531: getfield 62	z/k:null	Ljava/lang/String;
    //   534: aload 4
    //   536: ldc_w 283
    //   539: invokestatic 90	org/powerbot/bot/EventDispatcher:this	(Ljava/lang/Object;)Ljava/lang/String;
    //   542: invokevirtual 286	z/cON:true	(ILjava/lang/String;Ljava/lang/String;Ljava/lang/String;)V
    //   545: goto -126 -> 419
    //   548: aload_1
    //   549: iconst_1
    //   550: aload_1
    //   551: dup_x1
    //   552: sipush 177
    //   555: iconst_1
    //   556: dup
    //   557: pop2
    //   558: invokevirtual 208	z/cON:this	(I)V
    //   561: iconst_1
    //   562: dup
    //   563: pop2
    //   564: iconst_0
    //   565: iconst_1
    //   566: dup
    //   567: pop2
    //   568: invokevirtual 211	z/cON:this	(II)V
    //   571: invokevirtual 213	z/cON:this	()V
    //   574: aload_0
    //   575: invokespecial 287	z/P:this	()V
    //   578: return
    // Line number table:
    //   Java source line #198	-> byte code offset #0
    //   Java source line #199	-> byte code offset #12
    //   Java source line #200	-> byte code offset #19
    //   Java source line #202	-> byte code offset #46
    //   Java source line #203	-> byte code offset #57
    //   Java source line #204	-> byte code offset #63
    //   Java source line #205	-> byte code offset #73
    //   Java source line #206	-> byte code offset #76
    //   Java source line #208	-> byte code offset #80
    //   Java source line #211	-> byte code offset #108
    //   Java source line #212	-> byte code offset #120
    //   Java source line #213	-> byte code offset #128
    //   Java source line #214	-> byte code offset #136
    //   Java source line #215	-> byte code offset #145
    //   Java source line #217	-> byte code offset #157
    //   Java source line #218	-> byte code offset #161
    //   Java source line #219	-> byte code offset #173
    //   Java source line #221	-> byte code offset #201
    //   Java source line #222	-> byte code offset #205
    //   Java source line #223	-> byte code offset #214
    //   Java source line #224	-> byte code offset #219
    //   Java source line #227	-> byte code offset #247
    //   Java source line #228	-> byte code offset #259
    //   Java source line #229	-> byte code offset #273
    //   Java source line #230	-> byte code offset #281
    //   Java source line #231	-> byte code offset #293
    //   Java source line #234	-> byte code offset #321
    //   Java source line #235	-> byte code offset #330
    //   Java source line #236	-> byte code offset #341
    //   Java source line #238	-> byte code offset #344
    //   Java source line #239	-> byte code offset #350
    //   Java source line #242	-> byte code offset #381
    //   Java source line #245	-> byte code offset #409
    //   Java source line #246	-> byte code offset #437
    //   Java source line #247	-> byte code offset #477
    //   Java source line #248	-> byte code offset #503
    //   Java source line #250	-> byte code offset #527
    //   Java source line #252	-> byte code offset #545
    //   Java source line #253	-> byte code offset #548
    //   Java source line #254	-> byte code offset #561
    //   Java source line #255	-> byte code offset #571
    //   Java source line #257	-> byte code offset #574
    //   Java source line #258	-> byte code offset #578
    // Local variable table:
    //   start	length	slot	name	signature
    //   0	579	0	a	k
    //   45	506	1	localCON	cON
    //   127	350	2	localObject1	Object
    //   135	352	3	localObject2	Object
    //   143	392	4	localObject3	Object
    //   28	579	5	tmp28_27	int
  }
}
