package z;




















public class LA
  extends aux
{
  private final GA jdField_void;
  



















  public LA(aux a, GA a)
  {
    a.<init>(327680, a);
    jdField_void_of_type_ZGA = a;
  }
  
  /* Error */
  public void jdMethod_this(String a, Object a)
  {
    // Byte code:
    //   0: aload_1
    //   1: ifnull +12 -> 13
    //   4: aload_0
    //   5: getfield 15	z/LA:jdField_void_of_type_ZGA	Lz/GA;
    //   8: aload_1
    //   9: invokevirtual 26	z/GA:for	(Ljava/lang/String;)Lz/Xb;
    //   12: pop
    //   13: aload_2
    //   14: instanceof 28
    //   17: ifeq +23 -> 40
    //   20: aload_0
    //   21: getfield 15	z/LA:jdField_void_of_type_ZGA	Lz/GA;
    //   24: aload_2
    //   25: checkcast 28	java/lang/Byte
    //   28: invokevirtual 32	java/lang/Byte:byteValue	()B
    //   31: invokevirtual 35	z/GA:this	(I)Lz/Xb;
    //   34: pop
    //   35: aload_0
    //   36: goto +547 -> 583
    //   39: athrow
    //   40: aload_2
    //   41: instanceof 37
    //   44: ifeq +37 -> 81
    //   47: aload_0
    //   48: getfield 15	z/LA:jdField_void_of_type_ZGA	Lz/GA;
    //   51: aload_2
    //   52: checkcast 37	java/lang/Boolean
    //   55: invokevirtual 41	java/lang/Boolean:booleanValue	()Z
    //   58: ifeq +11 -> 69
    //   61: iconst_1
    //   62: dup
    //   63: dup
    //   64: pop2
    //   65: goto +8 -> 73
    //   68: athrow
    //   69: iconst_0
    //   70: iconst_1
    //   71: dup
    //   72: pop2
    //   73: invokevirtual 35	z/GA:this	(I)Lz/Xb;
    //   76: pop
    //   77: aload_0
    //   78: goto +505 -> 583
    //   81: aload_2
    //   82: instanceof 43
    //   85: ifeq +22 -> 107
    //   88: aload_0
    //   89: getfield 15	z/LA:jdField_void_of_type_ZGA	Lz/GA;
    //   92: aload_2
    //   93: checkcast 43	java/lang/Character
    //   96: invokevirtual 47	java/lang/Character:charValue	()C
    //   99: invokevirtual 35	z/GA:this	(I)Lz/Xb;
    //   102: pop
    //   103: aload_0
    //   104: goto +479 -> 583
    //   107: aload_2
    //   108: instanceof 49
    //   111: ifeq +22 -> 133
    //   114: aload_0
    //   115: getfield 15	z/LA:jdField_void_of_type_ZGA	Lz/GA;
    //   118: aload_2
    //   119: checkcast 49	java/lang/Short
    //   122: invokevirtual 53	java/lang/Short:shortValue	()S
    //   125: invokevirtual 35	z/GA:this	(I)Lz/Xb;
    //   128: pop
    //   129: aload_0
    //   130: goto +453 -> 583
    //   133: aload_2
    //   134: instanceof 55
    //   137: ifeq +22 -> 159
    //   140: aload_0
    //   141: getfield 15	z/LA:jdField_void_of_type_ZGA	Lz/GA;
    //   144: aload_2
    //   145: checkcast 55	z/iB
    //   148: invokevirtual 58	z/iB:this	()Ljava/lang/String;
    //   151: invokevirtual 26	z/GA:for	(Ljava/lang/String;)Lz/Xb;
    //   154: pop
    //   155: aload_0
    //   156: goto +427 -> 583
    //   159: aload_2
    //   160: instanceof 60
    //   163: ifeq +46 -> 209
    //   166: aload_2
    //   167: checkcast 60	[B
    //   170: checkcast 60	[B
    //   173: astore_3
    //   174: iconst_0
    //   175: iconst_1
    //   176: dup
    //   177: pop2
    //   178: dup
    //   179: istore 4
    //   181: aload_3
    //   182: arraylength
    //   183: if_icmpge +399 -> 582
    //   186: aload_0
    //   187: getfield 15	z/LA:jdField_void_of_type_ZGA	Lz/GA;
    //   190: aload_3
    //   191: iload 4
    //   193: iinc 4 1
    //   196: baload
    //   197: invokevirtual 35	z/GA:this	(I)Lz/Xb;
    //   200: pop
    //   201: iload 4
    //   203: goto -22 -> 181
    //   206: nop
    //   207: nop
    //   208: athrow
    //   209: aload_2
    //   210: instanceof 62
    //   213: ifeq +60 -> 273
    //   216: aload_2
    //   217: checkcast 62	[Z
    //   220: checkcast 62	[Z
    //   223: astore_3
    //   224: iconst_0
    //   225: iconst_1
    //   226: dup
    //   227: pop2
    //   228: dup
    //   229: istore 4
    //   231: aload_3
    //   232: arraylength
    //   233: if_icmpge +349 -> 582
    //   236: aload_0
    //   237: getfield 15	z/LA:jdField_void_of_type_ZGA	Lz/GA;
    //   240: aload_3
    //   241: iload 4
    //   243: baload
    //   244: ifeq +10 -> 254
    //   247: iconst_1
    //   248: dup
    //   249: dup
    //   250: pop2
    //   251: goto +7 -> 258
    //   254: iconst_0
    //   255: iconst_1
    //   256: dup
    //   257: pop2
    //   258: invokevirtual 35	z/GA:this	(I)Lz/Xb;
    //   261: pop
    //   262: iinc 4 1
    //   265: iload 4
    //   267: goto -36 -> 231
    //   270: nop
    //   271: nop
    //   272: athrow
    //   273: aload_2
    //   274: instanceof 64
    //   277: ifeq +46 -> 323
    //   280: aload_2
    //   281: checkcast 64	[S
    //   284: checkcast 64	[S
    //   287: astore_3
    //   288: iconst_0
    //   289: iconst_1
    //   290: dup
    //   291: pop2
    //   292: dup
    //   293: istore 4
    //   295: aload_3
    //   296: arraylength
    //   297: if_icmpge +285 -> 582
    //   300: aload_0
    //   301: getfield 15	z/LA:jdField_void_of_type_ZGA	Lz/GA;
    //   304: aload_3
    //   305: iload 4
    //   307: iinc 4 1
    //   310: saload
    //   311: invokevirtual 35	z/GA:this	(I)Lz/Xb;
    //   314: pop
    //   315: iload 4
    //   317: goto -22 -> 295
    //   320: nop
    //   321: nop
    //   322: athrow
    //   323: aload_2
    //   324: instanceof 66
    //   327: ifeq +46 -> 373
    //   330: aload_2
    //   331: checkcast 66	[C
    //   334: checkcast 66	[C
    //   337: astore_3
    //   338: iconst_0
    //   339: iconst_1
    //   340: dup
    //   341: pop2
    //   342: dup
    //   343: istore 4
    //   345: aload_3
    //   346: arraylength
    //   347: if_icmpge +235 -> 582
    //   350: aload_0
    //   351: getfield 15	z/LA:jdField_void_of_type_ZGA	Lz/GA;
    //   354: aload_3
    //   355: iload 4
    //   357: iinc 4 1
    //   360: caload
    //   361: invokevirtual 35	z/GA:this	(I)Lz/Xb;
    //   364: pop
    //   365: iload 4
    //   367: goto -22 -> 345
    //   370: nop
    //   371: nop
    //   372: athrow
    //   373: aload_2
    //   374: instanceof 68
    //   377: ifeq +46 -> 423
    //   380: aload_2
    //   381: checkcast 68	[I
    //   384: checkcast 68	[I
    //   387: astore_3
    //   388: iconst_0
    //   389: iconst_1
    //   390: dup
    //   391: pop2
    //   392: dup
    //   393: istore 4
    //   395: aload_3
    //   396: arraylength
    //   397: if_icmpge +185 -> 582
    //   400: aload_0
    //   401: getfield 15	z/LA:jdField_void_of_type_ZGA	Lz/GA;
    //   404: aload_3
    //   405: iload 4
    //   407: iinc 4 1
    //   410: iaload
    //   411: invokevirtual 35	z/GA:this	(I)Lz/Xb;
    //   414: pop
    //   415: iload 4
    //   417: goto -22 -> 395
    //   420: nop
    //   421: nop
    //   422: athrow
    //   423: aload_2
    //   424: instanceof 70
    //   427: ifeq +46 -> 473
    //   430: aload_2
    //   431: checkcast 70	[J
    //   434: checkcast 70	[J
    //   437: astore_3
    //   438: iconst_0
    //   439: iconst_1
    //   440: dup
    //   441: pop2
    //   442: dup
    //   443: istore 4
    //   445: aload_3
    //   446: arraylength
    //   447: if_icmpge +135 -> 582
    //   450: aload_0
    //   451: getfield 15	z/LA:jdField_void_of_type_ZGA	Lz/GA;
    //   454: aload_3
    //   455: iload 4
    //   457: iinc 4 1
    //   460: laload
    //   461: invokevirtual 73	z/GA:this	(J)Lz/Xb;
    //   464: pop
    //   465: iload 4
    //   467: goto -22 -> 445
    //   470: nop
    //   471: nop
    //   472: athrow
    //   473: aload_2
    //   474: instanceof 75
    //   477: ifeq +46 -> 523
    //   480: aload_2
    //   481: checkcast 75	[F
    //   484: checkcast 75	[F
    //   487: astore_3
    //   488: iconst_0
    //   489: iconst_1
    //   490: dup
    //   491: pop2
    //   492: dup
    //   493: istore 4
    //   495: aload_3
    //   496: arraylength
    //   497: if_icmpge +85 -> 582
    //   500: aload_0
    //   501: getfield 15	z/LA:jdField_void_of_type_ZGA	Lz/GA;
    //   504: aload_3
    //   505: iload 4
    //   507: iinc 4 1
    //   510: faload
    //   511: invokevirtual 78	z/GA:this	(F)Lz/Xb;
    //   514: pop
    //   515: iload 4
    //   517: goto -22 -> 495
    //   520: nop
    //   521: nop
    //   522: athrow
    //   523: aload_2
    //   524: instanceof 80
    //   527: ifeq +46 -> 573
    //   530: aload_2
    //   531: checkcast 80	[D
    //   534: checkcast 80	[D
    //   537: astore_3
    //   538: iconst_0
    //   539: iconst_1
    //   540: dup
    //   541: pop2
    //   542: dup
    //   543: istore 4
    //   545: aload_3
    //   546: arraylength
    //   547: if_icmpge +35 -> 582
    //   550: aload_0
    //   551: getfield 15	z/LA:jdField_void_of_type_ZGA	Lz/GA;
    //   554: aload_3
    //   555: iload 4
    //   557: iinc 4 1
    //   560: daload
    //   561: invokevirtual 83	z/GA:this	(D)Lz/Xb;
    //   564: pop
    //   565: iload 4
    //   567: goto -22 -> 545
    //   570: nop
    //   571: nop
    //   572: athrow
    //   573: aload_0
    //   574: getfield 15	z/LA:jdField_void_of_type_ZGA	Lz/GA;
    //   577: aload_2
    //   578: invokevirtual 86	z/GA:this	(Ljava/lang/Object;)Lz/Xb;
    //   581: pop
    //   582: aload_0
    //   583: getfield 88	z/LA:jdField_void_of_type_ZAux	Lz/aux;
    //   586: aload_1
    //   587: aload_2
    //   588: invokevirtual 90	z/aux:this	(Ljava/lang/String;Ljava/lang/Object;)V
    //   591: return
    // Line number table:
    //   Java source line #54	-> byte code offset #0
    //   Java source line #55	-> byte code offset #4
    //   Java source line #57	-> byte code offset #13
    //   Java source line #58	-> byte code offset #20
    //   Java source line #59	-> byte code offset #40
    //   Java source line #60	-> byte code offset #47
    //   Java source line #61	-> byte code offset #81
    //   Java source line #62	-> byte code offset #88
    //   Java source line #63	-> byte code offset #107
    //   Java source line #64	-> byte code offset #114
    //   Java source line #65	-> byte code offset #133
    //   Java source line #66	-> byte code offset #140
    //   Java source line #67	-> byte code offset #159
    //   Java source line #68	-> byte code offset #166
    //   Java source line #69	-> byte code offset #174
    //   Java source line #70	-> byte code offset #186
    //   Java source line #69	-> byte code offset #200
    //   Java source line #72	-> byte code offset #206
    //   Java source line #73	-> byte code offset #216
    //   Java source line #74	-> byte code offset #224
    //   Java source line #75	-> byte code offset #236
    //   Java source line #74	-> byte code offset #261
    //   Java source line #77	-> byte code offset #270
    //   Java source line #78	-> byte code offset #280
    //   Java source line #79	-> byte code offset #288
    //   Java source line #80	-> byte code offset #300
    //   Java source line #79	-> byte code offset #314
    //   Java source line #82	-> byte code offset #320
    //   Java source line #83	-> byte code offset #330
    //   Java source line #84	-> byte code offset #338
    //   Java source line #85	-> byte code offset #350
    //   Java source line #84	-> byte code offset #364
    //   Java source line #87	-> byte code offset #370
    //   Java source line #88	-> byte code offset #380
    //   Java source line #89	-> byte code offset #388
    //   Java source line #90	-> byte code offset #400
    //   Java source line #89	-> byte code offset #414
    //   Java source line #92	-> byte code offset #420
    //   Java source line #93	-> byte code offset #430
    //   Java source line #94	-> byte code offset #438
    //   Java source line #95	-> byte code offset #450
    //   Java source line #94	-> byte code offset #464
    //   Java source line #97	-> byte code offset #470
    //   Java source line #98	-> byte code offset #480
    //   Java source line #99	-> byte code offset #488
    //   Java source line #100	-> byte code offset #500
    //   Java source line #99	-> byte code offset #514
    //   Java source line #102	-> byte code offset #520
    //   Java source line #103	-> byte code offset #530
    //   Java source line #104	-> byte code offset #538
    //   Java source line #105	-> byte code offset #550
    //   Java source line #104	-> byte code offset #564
    //   Java source line #107	-> byte code offset #570
    //   Java source line #108	-> byte code offset #573
    //   Java source line #110	-> byte code offset #582
    //   Java source line #111	-> byte code offset #591
    // Local variable table:
    //   start	length	slot	name	signature
    //   0	592	0	a	LA
    //   0	592	1	a	String
    //   0	592	2	a	Object
  }
  
  public void jdMethod_this(String a, String a, String a)
  {
    if (a != null) {
      jdField_void_of_type_ZGA.jdMethod_for(a);
    }
    

    jdField_void_of_type_ZAux.jdMethod_this(a, a, a);jdField_void_of_type_ZGA.jdMethod_for(a);
  }
  

  public aux jdMethod_this(String a, String a)
  {
    if (a != null) {
      jdField_void_of_type_ZGA.jdMethod_for(a);
    }
    jdField_void_of_type_ZGA.jdMethod_for(a);
    return new LA(jdField_void_of_type_ZAux.jdMethod_this(a, a), jdField_void_of_type_ZGA);
  }
  

  public aux jdMethod_this(String a)
  {
    if (a != null) {
      jdField_void_of_type_ZGA.jdMethod_for(a);
    }
    return new LA(jdField_void_of_type_ZAux.jdMethod_this(a), jdField_void_of_type_ZGA);
  }
  
  public void jdMethod_this()
  {
    jdField_void_of_type_ZAux.jdMethod_this();
  }
}
