package z;





























































public class lPt3
  extends cOn
{
  public String jdField_new;
  


























































  public String jdField_void;
  



























































  public lPt3()
  {
    a.<init>(327680);
  }
  


  public void jdMethod_this(int a, int a, String a, String a, String a, String[] a)
  {
    jdField_new = a;
  }
  


  public cON jdMethod_this(int a, String a, String a, String a, String[] a)
  {
    a;a.<init>();jdField_void = (a + a);
    return new nA(a, 327680);
  }
  
  /* Error */
  public void jdMethod_true(String a, String a)
  {
    // Byte code:
    //   0: aload_1
    //   1: ldc 48
    //   3: invokestatic 53	z/Gb:this	(Ljava/lang/Object;)Ljava/lang/String;
    //   6: invokevirtual 59	java/lang/String:startsWith	(Ljava/lang/String;)Z
    //   9: ifeq +146 -> 155
    //   12: aload_1
    //   13: dup
    //   14: astore_3
    //   15: ifnull +61 -> 76
    //   18: getstatic 63	z/gb:byte	Ljava/util/Set;
    //   21: new 29	java/lang/StringBuilder
    //   24: dup
    //   25: invokespecial 31	java/lang/StringBuilder:<init>	()V
    //   28: iconst_0
    //   29: aload_3
    //   30: invokevirtual 67	java/lang/StringBuilder:insert	(ILjava/lang/String;)Ljava/lang/StringBuilder;
    //   33: bipush 32
    //   35: iconst_1
    //   36: dup
    //   37: pop2
    //   38: invokevirtual 70	java/lang/StringBuilder:append	(C)Ljava/lang/StringBuilder;
    //   41: aload_2
    //   42: invokevirtual 35	java/lang/StringBuilder:append	(Ljava/lang/String;)Ljava/lang/StringBuilder;
    //   45: invokevirtual 39	java/lang/StringBuilder:toString	()Ljava/lang/String;
    //   48: invokeinterface 76 2 0
    //   53: ifeq +5 -> 58
    //   56: return
    //   57: athrow
    //   58: getstatic 79	z/gb:new	Ljava/util/Map;
    //   61: aload_3
    //   62: invokeinterface 85 2 0
    //   67: checkcast 55	java/lang/String
    //   70: dup
    //   71: astore_3
    //   72: goto -57 -> 15
    //   75: athrow
    //   76: getstatic 91	java/lang/System:out	Ljava/io/PrintStream;
    //   79: new 29	java/lang/StringBuilder
    //   82: dup
    //   83: invokespecial 31	java/lang/StringBuilder:<init>	()V
    //   86: iconst_0
    //   87: ldc 93
    //   89: invokestatic 96	z/COm8:this	(Ljava/lang/Object;)Ljava/lang/String;
    //   92: invokevirtual 67	java/lang/StringBuilder:insert	(ILjava/lang/String;)Ljava/lang/StringBuilder;
    //   95: aload_1
    //   96: invokevirtual 35	java/lang/StringBuilder:append	(Ljava/lang/String;)Ljava/lang/StringBuilder;
    //   99: bipush 32
    //   101: iconst_1
    //   102: dup
    //   103: pop2
    //   104: invokevirtual 70	java/lang/StringBuilder:append	(C)Ljava/lang/StringBuilder;
    //   107: aload_2
    //   108: invokevirtual 35	java/lang/StringBuilder:append	(Ljava/lang/String;)Ljava/lang/StringBuilder;
    //   111: ldc 98
    //   113: invokestatic 53	z/Gb:this	(Ljava/lang/Object;)Ljava/lang/String;
    //   116: invokevirtual 35	java/lang/StringBuilder:append	(Ljava/lang/String;)Ljava/lang/StringBuilder;
    //   119: aload_0
    //   120: getfield 24	z/lPt3:new	Ljava/lang/String;
    //   123: invokevirtual 35	java/lang/StringBuilder:append	(Ljava/lang/String;)Ljava/lang/StringBuilder;
    //   126: bipush 32
    //   128: iconst_1
    //   129: dup
    //   130: pop2
    //   131: invokevirtual 70	java/lang/StringBuilder:append	(C)Ljava/lang/StringBuilder;
    //   134: aload_0
    //   135: getfield 41	z/lPt3:void	Ljava/lang/String;
    //   138: invokevirtual 35	java/lang/StringBuilder:append	(Ljava/lang/String;)Ljava/lang/StringBuilder;
    //   141: ldc 100
    //   143: invokestatic 96	z/COm8:this	(Ljava/lang/Object;)Ljava/lang/String;
    //   146: invokevirtual 35	java/lang/StringBuilder:append	(Ljava/lang/String;)Ljava/lang/StringBuilder;
    //   149: invokevirtual 39	java/lang/StringBuilder:toString	()Ljava/lang/String;
    //   152: invokevirtual 106	java/io/PrintStream:println	(Ljava/lang/String;)V
    //   155: return
    // Line number table:
    //   Java source line #221	-> byte code offset #0
    //   Java source line #222	-> byte code offset #12
    //   Java source line #223	-> byte code offset #15
    //   Java source line #224	-> byte code offset #18
    //   Java source line #225	-> byte code offset #56
    //   Java source line #227	-> byte code offset #58
    //   Java source line #229	-> byte code offset #76
    //   Java source line #233	-> byte code offset #155
    // Local variable table:
    //   start	length	slot	name	signature
    //   0	156	0	a	lPt3
    //   0	156	1	a	String
    //   0	156	2	a	String
  }
}
