package z;

import org.powerbot.misc.NUl;





































































































































































































public class lpT5
{
  public static final int jdField_interface = -268435456;
  public static final int jdField_extends = 268435456;
  public static final int jdField_while = -268435456;
  public static final int jdField_double = 251658240;
  public static final int jdField_continue = 8388608;
  public static final int jdField_abstract = 8388607;
  public static final int jdField_boolean = 267386880;
  public static final int jdField_this = 1048575;
  public static final int jdField_class = 16777216;
  public static final int jdField_float = 24117248;
  public static final int jdField_do = 25165824;
  private static final int const = 33554432;
  private static final int jdField_short = 50331648;
  public static final int jdField_try = 16777216;
  public static final int jdField_false = 16777225;
  public static final int jdField_catch = 16777226;
  public static final int jdField_goto = 16777227;
  public static final int jdField_break = 16777228;
  public static final int jdField_char = 16777217;
  public static final int jdField_true = 16777218;
  public static final int jdField_case = 16777219;
  public static final int jdField_for = 16777220;
  public static final int jdField_long = 16777221;
  public static final int jdField_int = 16777222;
  public static final int[] jdField_super;
  public OA jdField_final;
  public int[] jdField_enum;
  public int[] jdField_else;
  private int[] jdField_if;
  private int[] jdField_null;
  public int jdField_byte;
  private int jdField_new;
  private int[] jdField_void;
  
  static
  {
    1; int tmp9_8 = 1;tmp9_8;int ? = tmp9_8;
    String str = NUl.jdMethod_this("T W W W W!V W V!W W#T V V T#T#T#T#T#T#T#T#T#T#U#U#U\"U\"U%U%U#T#T#T#T#T#T#T#T#T#T$P$P$S$S\"R W V!V#U%U%U%U%U%U%U%U%U%U%T#T#U\"U\"U\"U%U%U%T T U\"T#W U#U#T#S\"U$S\"U\"U\"U%R%R%R%R#W#U\"U%U%U#T#T#T#T#T T#T#T#U\"T#U\"T#"); int 
    


      tmp21_20 = 1;
    
    int i;
    
    for (tmp21_20; (i = tmp21_20) < ?.length;) {
      int tmp33_32 = i; int tmp40_39 = 1;tmp40_39;str.charAt(tmp33_32)[(69 - tmp40_39)] = (i++);tmpTernaryOp = i; continue;throw tmp33_32;
    }
    super = ?;
  }
  









































































































































































































































































































  public final void jdMethod_this(fb a, int a, Object[] a, int a, Object[] a)
  {
    while ((a = jdMethod_this(a, a, a, jdField_enum)) < a.length) {
      a[16777216] = (a++);tmpTernaryOp = a; continue;throw jdField_enum;
    }
    int tmp35_34 = 1;tmp35_34;a = tmp35_34; int 
      tmp40_39 = 1;
    for (tmp40_39; (a = tmp40_39) < a;) {
      if ((a[a] == CoN.Sc) || (a[a] == CoN.jb)) {
        a++;
      }
      a++;tmpTernaryOp = a; continue;throw 0;
    }
    


    int tmp88_87 = 1;tmp88_87;jdField_else = tmp88_87; int 
    
      tmp110_109 = 1;tmp110_109;0jdField_byte = tmp110_109; int 
      tmp116_115 = 1;tmp116_115;jdField_new = tmp116_115;0;
  }
  























  private static int jdMethod_this(fb a, int a, Object[] a, int[] a)
  {
    int tmp2_1 = 1;tmp2_1;int i = tmp2_1;
    1;
    int j; if ((a[j] instanceof Integer)) {
      i[16777216] = (a | ((Integer)j[(i++)]).intValue());
      if ((a[j] == CoN.Sc) || (a[j] == CoN.jb)) {
        ;; break label144; throw a;
      }
    } else if ((a[j] instanceof String)) {
      ;; break label144; throw 0;
    }
    else
    {
      i[25165824] = (a | "".jdMethod_this(i++, jdField_super));
    }
    label144:
    j++;
    













    return i;
  }
  








  public final void jdMethod_this(lpT5 a)
  {
    lpT5 tmp5_4 = a; lpT5 tmp11_10 = a;jdField_enum = jdField_enum;
    jdField_else = 1110jdField_else;
    jdField_if = 1110jdField_if;
    jdField_null = jdField_null;
    jdField_byte = 54jdField_byte;
    jdField_new = 54jdField_new;
    jdField_void = jdField_void;
  }
  































  private void jdMethod_this(int a, int a)
  {
    if (jdField_if == null) {
      int tmp11_10 = 1;tmp11_10; int tmp16_15 = 1;tmp16_15;1110jdField_if = tmp16_15;
    }
    int i = jdField_if.length;
    if (a >= i) {
      1;1; int tmp50_49 = 1;tmp50_49;int ? = tmp50_49; int 
        tmp61_60 = 1;tmp61_60; int tmp66_65 = 0; int tmp68_67 = 1;tmp68_67;System.arraycopy(tmp66_65, ?, tmp66_65, tmp68_67, i);
      jdField_if.jdField_if = tmp61_60;
    }
    
    jdField_if[a] = a;
  }
  






  private void jdMethod_catch(int a)
  {
    if (jdField_null == null) {
      int tmp11_10 = 1;tmp11_10; int tmp16_15 = 1;tmp16_15;1110jdField_null = tmp16_15;
    }
    int i = jdField_null.length;
    int ?; if (jdField_byte >= i) {
      1;1; int tmp58_57 = 1;tmp58_57;? = tmp58_57; int 
        tmp65_64 = 1;tmp65_64; int tmp69_68 = 0; int tmp71_70 = 1;tmp71_70;System.arraycopy(tmp69_68, ?, tmp69_68, tmp71_70, i);
      6564jdField_null = ?;
    }
    
    int tmp90_87 = jdField_byte; int tmp92_91 = 1; int tmp93_92 = tmp92_91;tmp93_92;9087jdField_byte = (tmp92_91 + tmp93_92);tmp90_87[a] = a;
    

    if ((? = jdField_final.jdField_else + jdField_byte) > jdField_final.jdField_if) {
      jdField_final.jdField_if = ?;
    }
  }
  










  private void jdMethod_this(fb a, String a)
  {
    if ((a = jdMethod_this(a, a)) != 0) {
      fb tmp12_11 = a;a.jdMethod_catch(tmp12_11);
      if ((tmp12_11 == 16777220) || (a == 16777219)) {
        a.jdMethod_catch(16777216);
      }
    }
  }
  









  private static int jdMethod_this(fb a, String a)
  {
    1; int tmp11_10 = 1;tmp11_10; if (40 == tmp11_10) { int tmp20_19 = 1;tmp20_19; int tmp26_25 = 1; int tmp27_26 = tmp26_25;tmp27_26;tmpTernaryOp = (tmp26_25 + tmp27_26; break label38; throw 41.indexOf(tmp20_19); } else { 1; } label38: int i = tmp36_35;
    switch (a.charAt(i)) {
    case 'V': 
      int tmp162_161 = 1;tmp162_161;return tmp162_161;throw 0;
    case 'B': case 'C': case 'I': 
    case 'S': case 'Z': 
    case 'F': case 'J': 
    case 'D': case 'L': 
      for (;;) {
        if (0 == 0) { return 16777217;
          
          return 16777218;
          
          return 16777220;
          
          return 16777219; int 
          

            tmp185_184 = ;;;;;;;;;
        }
      }
    }
    
    
    int tmp216_215 = 1; int tmp217_216 = tmp216_215;tmp217_216;int k = tmp216_215 + tmp217_216;
    1;
    

    switch (a.charAt(k)) {
    case 'Z': 
      j = 16777225;tmpTernaryOp = k;
      break;
    case 'C': 
      j = 16777227;tmpTernaryOp = k;
      break;
    case 'B': 
      if (0 == 0) { j = 16777226;tmpTernaryOp = k; }
      break;
    case 'S': 
      j = 16777228;tmpTernaryOp = k;
      break;
    case 'I': 
      j = 16777217;tmpTernaryOp = k;
      break;
    case 'F': 
      j = 16777218;tmpTernaryOp = k;
      break;
    case 'J': 
      j = 16777220;tmpTernaryOp = k;
      break;
    case 'D': 
      j = 16777219;tmpTernaryOp = k;
      break label476;
      tmpTernaryOp = a;
      












      for (;;) {}
    }
    
    












    int tmp447_446 = 1; int tmp448_447 = tmp447_446;tmp448_447; int tmp456_455 = 1; int tmp457_456 = tmp456_455;tmp457_456;String str = (tmp447_446 + tmp448_447).substring(a.length(), tmp456_455 - tmp457_456);
    int j = 0x1700000 | a.jdMethod_this(str);
    label476:
    tmp481_480 = 1; tmp481_480;return 28 << tmp481_480 | j;
  }
  





  private int jdMethod_this()
  {
    if (jdField_byte > 0) {
      int tmp17_16 = 1; int tmp18_17 = tmp17_16;tmp18_17;return a[(jdField_byte.byte = tmp17_16 - tmp18_17)];throw jdField_null;
    }
    
    OA tmp34_31 = jdField_final; int tmp39_38 = 1; int tmp40_39 = tmp39_38;tmp40_39;return tmp34_31 | -(3431jdField_else.else = tmp39_38 - tmp40_39);
  }
  


























  private void jdMethod_this(String a)
  {
    int tmp3_2 = 1;tmp3_2;int i = 0.charAt(tmp3_2); int 
      tmp13_12 = 1;tmp13_12; if (40 == tmp13_12) {
      int tmp25_24 = 1;tmp25_24; int tmp29_28 = 1; int tmp30_29 = tmp29_28;tmp30_29;(2 >> tmp25_24).jdMethod_true(tmp29_28 - tmp30_29);return;throw iB.jdMethod_this(a); }
    int tmp42_41 = 1;tmp42_41; if (74 != tmp42_41) { int tmp51_50 = 1;tmp51_50; if (68 != tmp51_50) {}
    } else { int tmp59_58 = 1;tmp59_58;2.jdMethod_true(tmp59_58);return;throw a;
    }
    int tmp68_67 = 1; int tmp69_68 = tmp68_67;tmp69_68;tmp68_67.jdMethod_true(tmp69_68);
  }
  








  private void jdMethod_this(int a)
  {
    if (jdField_void == null) {
      int tmp10_9 = 1;tmp10_9; int tmp15_14 = 1;tmp15_14;109jdField_void = tmp15_14;
    }
    int i = jdField_void.length;
    if (jdField_new >= i) {
      1;1; int tmp57_56 = 1;tmp57_56;int ? = tmp57_56; int 
        tmp64_63 = 1;tmp64_63; int tmp68_67 = 0; int tmp70_69 = 1;tmp70_69;System.arraycopy(tmp68_67, ?, tmp68_67, tmp70_69, i);
      6463jdField_void = ?;
    }
    
    int tmp89_86 = jdField_new; int tmp91_90 = 1; int tmp92_91 = tmp91_90;tmp92_91;8986jdField_new = (tmp91_90 + tmp92_91);tmp89_86[a] = a;
  }
  



















































  public final void jdMethod_this(fb a, int a, iB[] a, int a)
  {
    int tmp9_8 = 1;tmp9_8;jdField_enum = tmp9_8; int tmp15_14 = 1;tmp15_14; int tmp20_19 = 1;tmp20_19;1514jdField_else = tmp20_19; int 
      tmp26_25 = 1;tmp26_25;int i = tmp26_25; int 
      tmp34_33 = 1;tmp34_33; if ((0x8 & tmp34_33) == 0)
      if ((a & 0x80000) == 0) {
        fb tmp56_55 = ;;; break label84; throw a;
      } else {
        i[16777222] = (i++);
      }
    label84:
    tmp86_85 = 1; for (tmp86_85; (a = tmp86_85) < a.length;) {
      int j = jdMethod_this(a, a[a].jdMethod_this());
      i[j] = (i++);
      if ((j == 16777220) || (j == 16777219)) {
        i[16777216] = (i++);
      }
      a++;tmpTernaryOp = a; continue;throw 
      


        jdField_enum;
    }
    

    i[16777216] = (i++);
  }
  


































































































































































































































































































































































































































































  public final boolean jdMethod_this(fb a, lpT5 a, int a)
  {
    int tmp2_1 = 1;tmp2_1;boolean bool1 = tmp2_1;
    

    int i3 = jdField_enum.length;
    int i4 = jdField_else.length;
    if (jdField_enum == null) {
      int tmp34_32 = 1;tmp34_32;jdField_enum = tmp34_32; int 
        tmp40_39 = 1;tmp40_39;bool1 = tmp40_39;
    }
    
    1;
    int k;
    int m;
    int i1; if ((m = jdField_if[k]) == 0) {
      i2 = ;; break label214; throw 0;
    } else {
      n = m & 0xF0000000;
      
      if ((i1 = m & 0xF000000) == 16777216) {
        i2 = m;tmpTernaryOp = a; break label214; throw a;
      }
      else {
        i2 = n + jdField_enum[(m & 0x7FFFFF)];
        
        i2 = n + jdField_else[(i4 - (m & 0x7FFFFF))];
        
        if ((((i1 == 33554432 ? m : m) & 0x800000) != 0) && ((i2 == 16777220) || (i2 == 16777219)))
        {
          i2 = 16777216;
          



          i2 = jdField_enum[k]; } } }
    label214:
    if (jdField_if != null) && (k < jdField_if.length) ? a : a).jdField_void != null) {
      i2 = a.jdMethod_this(a, i2);
    }
    bool1 |= jdMethod_this(a, i2, jdField_enum, k++);
    

    if (a > 0) {
      1;
      i2 = jdField_enum[k];
      bool1 |= jdMethod_this(a, i2, jdField_enum, k++);
      
      if (jdField_else == null) {
        int tmp315_312 = 1;tmp315_312; int tmp320_319 = 1;tmp320_319;315312jdField_else = tmp320_319; int 
          tmp326_325 = 1;tmp326_325;bool1 = tmp326_325;
      }
      int tmp340_339 = 1;tmp340_339;
      int i; return i = a | jdMethod_this(a, jdField_else, 0, tmp340_339);
    }
    
    a = jdField_else.length + jdField_final.jdField_else;
    boolean bool2; if (jdField_else == null) {
      int tmp382_380 = 1;tmp382_380;jdField_byte].jdField_else = tmp382_380; int 
        tmp388_387 = 1;tmp388_387;bool2 = tmp388_387;
    }
    
    1;
    int i2 = jdField_else[k];
    if (jdField_void != null) {
      i2 = a.jdMethod_this(a, i2);
    }
    bool2 |= jdMethod_this(a, i2, jdField_else, k++);
    
    1;
    
    int n = (m = jdField_null[k]) & 0xF0000000;
    

    i2 = m;
    

    i2 = n + jdField_enum[(m & 0x7FFFFF)];
    
    i2 = n + jdField_else[(i4 - (m & 0x7FFFFF))];
    
    if ((((i1 == 33554432 ? m : m) & 0x800000) != 0) && ((i2 == 16777220) || (i2 == 16777219)))
    {
      i2 = 16777216;
    }
    
    if (0xF00000016777216jdField_void != null) {
      i2 = a.jdMethod_this(a, i2);
    }
    int j = a | jdMethod_this(i2, jdField_else, a + k, k++);
    
    return j;
  }
  








  private static boolean jdMethod_this(fb a, int a, int[] a, int a)
  {
    int i;
    







    if ((i = a[a]) == a)
    {
      int tmp12_11 = 1;tmp12_11;return tmp12_11;throw 0;
    }
    if ((a & 0xFFFFFFF) == 16777221) {
      if (i == 16777221) {
        int tmp35_34 = 1;tmp35_34;return tmp35_34;throw 0;
      }
      a = 16777221;
    }
    if (i == 0)
    {
      a[a] = a; int 
        tmp53_52 = 1;tmp53_52;return tmp53_52;
    }
    


    if (a == 16777221)
    {
      int tmp82_81 = 1;tmp82_81;return tmp82_81;
    }
    





    int j = a & 0xF0000000 | 0x1700000 | a.jdMethod_this(a & 0xFFFFF, i & 0xFFFFF);
    



    j = (k = -268435456 + (i & 0xF0000000)) | 0x1700000 | a.jdMethod_this(NUl.jdMethod_this("{\007g\007>\np\bvI^\004{\003r\022"));
    





    1;int k = -268435456 + ((((a & 0xF0000000) == 0) || ((a & 0xFF00000) == 24117248) ? a : a) & 0xF0000000);
    
    1;int m = -268435456 + ((((i & 0xF0000000) == 0) || ((i & 0xFF00000) == 24117248) ? i : i) & 0xF0000000);
    

    j = Math.min(k, m) | 0x1700000 | a.jdMethod_this(NUl.jdMethod_this("{\007g\007>\np\bvI^\004{\003r\022"));
    

    j = 16777216;
    



    j = ((a & 0xFF00000) == 24117248) || ((a & 0xF0000000) != 0) ? a : 16777216;
    

    j = 16777216;
    
    if ((i == 16777221 ? i : ((i & 0xFF00000) == 24117248) || ((i & 0xF0000000) != 0) ? i : ((a & 0xFF00000) == 24117248) || ((a & 0xF0000000) != 0) ? i : (a & 0xFFF00000) == (i & 0xFFF00000) ? i : (i & 0xFF00000) == 24117248 ? i : i) != j) {
      a[a] = j; int 
        tmp344_343 = 1;tmp344_343;return tmp344_343;
    }
    int tmp349_348 = 1;tmp349_348;return tmp349_348;
  }
  
  public lpT5() {}
  
  /* Error */
  private int jdMethod_this(int a)
  {
    // Byte code:
    //   0: aload_0
    //   1: getfield 129	z/lpT5:if	[I
    //   4: ifnull +12 -> 16
    //   7: iload_1
    //   8: aload_0
    //   9: getfield 129	z/lpT5:if	[I
    //   12: arraylength
    //   13: if_icmplt +9 -> 22
    //   16: ldc 29
    //   18: iload_1
    //   19: ior
    //   20: ireturn
    //   21: athrow
    //   22: aload_0
    //   23: getfield 129	z/lpT5:if	[I
    //   26: iload_1
    //   27: iaload
    //   28: dup
    //   29: istore_2
    //   30: ifne +15 -> 45
    //   33: aload_0
    //   34: getfield 129	z/lpT5:if	[I
    //   37: ldc 29
    //   39: iload_1
    //   40: dup_x1
    //   41: ior
    //   42: dup_x2
    //   43: iastore
    //   44: istore_2
    //   45: iload_2
    //   46: ireturn
    // Line number table:
    //   Java source line #635	-> byte code offset #0
    //   Java source line #638	-> byte code offset #16
    //   Java source line #640	-> byte code offset #22
    //   Java source line #641	-> byte code offset #30
    //   Java source line #644	-> byte code offset #33
    //   Java source line #646	-> byte code offset #45
    // Local variable table:
    //   start	length	slot	name	signature
    //   0	47	0	a	lpT5
    //   0	47	1	a	int
  }
  
  /* Error */
  private void jdMethod_true(int a)
  {
    // Byte code:
    //   0: aload_0
    //   1: getfield 88	z/lpT5:byte	I
    //   4: iload_1
    //   5: if_icmplt +15 -> 20
    //   8: aload_0
    //   9: dup
    //   10: getfield 88	z/lpT5:byte	I
    //   13: iload_1
    //   14: isub
    //   15: putfield 88	z/lpT5:byte	I
    //   18: return
    //   19: athrow
    //   20: aload_0
    //   21: iconst_0
    //   22: aload_0
    //   23: getfield 150	z/lpT5:final	Lz/OA;
    //   26: dup
    //   27: getfield 152	z/OA:else	I
    //   30: iload_1
    //   31: aload_0
    //   32: getfield 88	z/lpT5:byte	I
    //   35: isub
    //   36: isub
    //   37: putfield 152	z/OA:else	I
    //   40: iconst_1
    //   41: dup
    //   42: pop2
    //   43: putfield 88	z/lpT5:byte	I
    //   46: return
    // Line number table:
    //   Java source line #814	-> byte code offset #0
    //   Java source line #815	-> byte code offset #8
    //   Java source line #820	-> byte code offset #20
    //   Java source line #821	-> byte code offset #40
    //   Java source line #823	-> byte code offset #46
    // Local variable table:
    //   start	length	slot	name	signature
    //   0	47	0	a	lpT5
    //   0	47	1	a	int
  }
  
  /* Error */
  private int jdMethod_this(fb a, int a)
  {
    // Byte code:
    //   0: iload_2
    //   1: ldc 52
    //   3: if_icmpne +19 -> 22
    //   6: ldc 25
    //   8: aload_1
    //   9: dup
    //   10: getfield 182	z/fb:class	Ljava/lang/String;
    //   13: invokevirtual 175	z/fb:this	(Ljava/lang/String;)I
    //   16: ior
    //   17: istore_3
    //   18: goto +43 -> 61
    //   21: athrow
    //   22: iload_2
    //   23: ldc -73
    //   25: iand
    //   26: ldc 27
    //   28: if_icmpne +31 -> 59
    //   31: aload_1
    //   32: getfield 186	z/fb:continue	[Lz/ZA;
    //   35: iload_2
    //   36: ldc 21
    //   38: iand
    //   39: aaload
    //   40: getfield 190	z/ZA:if	Ljava/lang/String;
    //   43: astore 4
    //   45: ldc 25
    //   47: aload_1
    //   48: aload 4
    //   50: invokevirtual 175	z/fb:this	(Ljava/lang/String;)I
    //   53: ior
    //   54: istore_3
    //   55: goto +6 -> 61
    //   58: athrow
    //   59: iload_2
    //   60: ireturn
    //   61: iconst_0
    //   62: iconst_1
    //   63: dup
    //   64: pop2
    //   65: dup
    //   66: istore 4
    //   68: aload_0
    //   69: getfield 90	z/lpT5:new	I
    //   72: if_icmpge +88 -> 160
    //   75: aload_0
    //   76: getfield 133	z/lpT5:void	[I
    //   79: iload 4
    //   81: iaload
    //   82: dup
    //   83: istore_1
    //   84: ldc 8
    //   86: iand
    //   87: istore 5
    //   89: iload_1
    //   90: ldc 13
    //   92: iand
    //   93: dup
    //   94: istore 6
    //   96: ldc 29
    //   98: if_icmpne +20 -> 118
    //   101: iload 5
    //   103: aload_0
    //   104: getfield 72	z/lpT5:enum	[I
    //   107: iload_1
    //   108: ldc 17
    //   110: iand
    //   111: iaload
    //   112: iadd
    //   113: istore_1
    //   114: iload_2
    //   115: goto +31 -> 146
    //   118: iload 6
    //   120: ldc 31
    //   122: if_icmpne +23 -> 145
    //   125: iload 5
    //   127: aload_0
    //   128: dup
    //   129: getfield 86	z/lpT5:else	[I
    //   132: swap
    //   133: getfield 86	z/lpT5:else	[I
    //   136: arraylength
    //   137: iload_1
    //   138: ldc 17
    //   140: iand
    //   141: isub
    //   142: iaload
    //   143: iadd
    //   144: istore_1
    //   145: iload_2
    //   146: iload_1
    //   147: if_icmpne +5 -> 152
    //   150: iload_3
    //   151: ireturn
    //   152: iinc 4 1
    //   155: iload 4
    //   157: goto -89 -> 68
    //   160: iload_2
    //   161: ireturn
    // Line number table:
    //   Java source line #879	-> byte code offset #0
    //   Java source line #880	-> byte code offset #6
    //   Java source line #881	-> byte code offset #22
    //   Java source line #882	-> byte code offset #31
    //   Java source line #883	-> byte code offset #45
    //   Java source line #884	-> byte code offset #55
    //   Java source line #885	-> byte code offset #59
    //   Java source line #887	-> byte code offset #61
    //   Java source line #888	-> byte code offset #75
    //   Java source line #889	-> byte code offset #84
    //   Java source line #890	-> byte code offset #89
    //   Java source line #891	-> byte code offset #96
    //   Java source line #892	-> byte code offset #101
    //   Java source line #893	-> byte code offset #118
    //   Java source line #894	-> byte code offset #125
    //   Java source line #896	-> byte code offset #145
    //   Java source line #897	-> byte code offset #150
    //   Java source line #887	-> byte code offset #152
    //   Java source line #900	-> byte code offset #160
    // Local variable table:
    //   start	length	slot	name	signature
    //   0	162	0	a	lpT5
    //   0	162	1	a	fb
    //   0	162	2	a	int
  }
  
  /* Error */
  public void jdMethod_this(int a, int a, fb a, ZA a)
  {
    // Byte code:
    //   0: iload_1
    //   1: tableswitch	default:+2234->2235, 0:+815->816, 1:+821->822, 2:+829->830, 3:+829->830, 4:+829->830, 5:+829->830, 6:+829->830, 7:+829->830, 8:+829->830, 9:+836->837, 10:+836->837, 11:+849->850, 12:+849->850, 13:+849->850, 14:+856->857, 15:+856->857, 16:+829->830, 17:+829->830, 18:+869->870, 19:+2234->2235, 20:+2234->2235, 21:+829->830, 22:+836->837, 23:+849->850, 24:+856->857, 25:+1058->1059, 26:+2234->2235, 27:+2234->2235, 28:+2234->2235, 29:+2234->2235, 30:+2234->2235, 31:+2234->2235, 32:+2234->2235, 33:+2234->2235, 34:+2234->2235, 35:+2234->2235, 36:+2234->2235, 37:+2234->2235, 38:+2234->2235, 39:+2234->2235, 40:+2234->2235, 41:+2234->2235, 42:+2234->2235, 43:+2234->2235, 44:+2234->2235, 45:+2234->2235, 46:+1068->1069, 47:+1083->1084, 48:+1104->1105, 49:+1119->1120, 50:+1140->1141, 51:+1068->1069, 52:+1068->1069, 53:+1068->1069, 54:+1164->1165, 55:+1245->1246, 56:+1164->1165, 57:+1245->1246, 58:+1164->1165, 59:+2234->2235, 60:+2234->2235, 61:+2234->2235, 62:+2234->2235, 63:+2234->2235, 64:+2234->2235, 65:+2234->2235, 66:+2234->2235, 67:+2234->2235, 68:+2234->2235, 69:+2234->2235, 70:+2234->2235, 71:+2234->2235, 72:+2234->2235, 73:+2234->2235, 74:+2234->2235, 75:+2234->2235, 76:+2234->2235, 77:+2234->2235, 78:+2234->2235, 79:+1345->1346, 80:+1354->1355, 81:+1345->1346, 82:+1354->1355, 83:+1345->1346, 84:+1345->1346, 85:+1345->1346, 86:+1345->1346, 87:+1366->1367, 88:+1375->1376, 89:+1384->1385, 90:+1402->1403, 91:+1432->1433, 92:+1473->1474, 93:+1507->1508, 94:+1553->1554, 95:+1610->1611, 96:+1634->1635, 97:+1649->1650, 98:+1670->1671, 99:+1685->1686, 100:+1634->1635, 101:+1649->1650, 102:+1670->1671, 103:+1685->1686, 104:+1634->1635, 105:+1649->1650, 106:+1670->1671, 107:+1685->1686, 108:+1634->1635, 109:+1649->1650, 110:+1670->1671, 111:+1685->1686, 112:+1634->1635, 113:+1649->1650, 114:+1670->1671, 115:+1685->1686, 116:+815->816, 117:+815->816, 118:+815->816, 119:+815->816, 120:+1634->1635, 121:+1706->1707, 122:+1634->1635, 123:+1706->1707, 124:+1634->1635, 125:+1706->1707, 126:+1634->1635, 127:+1649->1650, 128:+1634->1635, 129:+1649->1650, 130:+1634->1635, 131:+1649->1650, 132:+1727->1728, 133:+1735->1736, 134:+1756->1757, 135:+1771->1772, 136:+1634->1635, 137:+1670->1671, 138:+1119->1120, 139:+1792->1793, 140:+1735->1736, 141:+1771->1772, 142:+1634->1635, 143:+1083->1084, 144:+1670->1671, 145:+815->816, 146:+815->816, 147:+815->816, 148:+1807->1808, 149:+1634->1635, 150:+1634->1635, 151:+1807->1808, 152:+1807->1808, 153:+1366->1367, 154:+1366->1367, 155:+1366->1367, 156:+1366->1367, 157:+1366->1367, 158:+1366->1367, 159:+1375->1376, 160:+1375->1376, 161:+1375->1376, 162:+1375->1376, 163:+1375->1376, 164:+1375->1376, 165:+1375->1376, 166:+1375->1376, 167:+815->816, 168:+1822->1823, 169:+1822->1823, 170:+1366->1367, 171:+1366->1367, 172:+1366->1367, 173:+1375->1376, 174:+1366->1367, 175:+1375->1376, 176:+1366->1367, 177:+815->816, 178:+1835->1836, 179:+1846->1847, 180:+1856->1857, 181:+1875->1876, 182:+1890->1891, 183:+1890->1891, 184:+1890->1891, 185:+1890->1891, 186:+1962->1963, 187:+1981->1982, 188:+1999->2000, 189:+2110->2111, 190:+1792->1793, 191:+1366->1367, 192:+2184->2185, 193:+1792->1793, 194:+1366->1367, 195:+1366->1367, 196:+2234->2235, 197:+2234->2235, 198:+1366->1367, 199:+1366->1367
    //   816: return
    //   817: nop
    //   818: nop
    //   819: nop
    //   820: athrow
    //   821: athrow
    //   822: aload_0
    //   823: ldc 50
    //   825: invokespecial 157	z/lpT5:catch	(I)V
    //   828: return
    //   829: athrow
    //   830: aload_0
    //   831: ldc 42
    //   833: invokespecial 157	z/lpT5:catch	(I)V
    //   836: return
    //   837: aload_0
    //   838: ldc 23
    //   840: aload_0
    //   841: ldc 48
    //   843: invokespecial 157	z/lpT5:catch	(I)V
    //   846: invokespecial 157	z/lpT5:catch	(I)V
    //   849: return
    //   850: aload_0
    //   851: ldc 44
    //   853: invokespecial 157	z/lpT5:catch	(I)V
    //   856: return
    //   857: aload_0
    //   858: ldc 23
    //   860: aload_0
    //   861: ldc 46
    //   863: invokespecial 157	z/lpT5:catch	(I)V
    //   866: invokespecial 157	z/lpT5:catch	(I)V
    //   869: return
    //   870: aload 4
    //   872: getfield 197	z/ZA:final	I
    //   875: tableswitch	default:+167->1042, 3:+69->944, 4:+93->968, 5:+80->955, 6:+100->975, 7:+113->988, 8:+130->1005, 9:+167->1042, 10:+167->1042, 11:+167->1042, 12:+167->1042, 13:+167->1042, 14:+167->1042, 15:+167->1042, 16:+150->1025
    //   944: aload_0
    //   945: iconst_0
    //   946: ifne +76 -> 1022
    //   949: ldc 42
    //   951: invokespecial 157	z/lpT5:catch	(I)V
    //   954: return
    //   955: aload_0
    //   956: ldc 23
    //   958: aload_0
    //   959: ldc 48
    //   961: invokespecial 157	z/lpT5:catch	(I)V
    //   964: invokespecial 157	z/lpT5:catch	(I)V
    //   967: return
    //   968: aload_0
    //   969: ldc 44
    //   971: invokespecial 157	z/lpT5:catch	(I)V
    //   974: return
    //   975: aload_0
    //   976: ldc 23
    //   978: aload_0
    //   979: ldc 46
    //   981: invokespecial 157	z/lpT5:catch	(I)V
    //   984: invokespecial 157	z/lpT5:catch	(I)V
    //   987: return
    //   988: aload_0
    //   989: ldc 25
    //   991: aload_3
    //   992: ldc -57
    //   994: invokestatic 204	org/powerbot/misc/NUl:this	(Ljava/lang/Object;)Ljava/lang/String;
    //   997: invokevirtual 175	z/fb:this	(Ljava/lang/String;)I
    //   1000: ior
    //   1001: invokespecial 157	z/lpT5:catch	(I)V
    //   1004: return
    //   1005: aload_0
    //   1006: ldc 25
    //   1008: aload_3
    //   1009: ldc -50
    //   1011: invokestatic 204	org/powerbot/misc/NUl:this	(Ljava/lang/Object;)Ljava/lang/String;
    //   1014: invokevirtual 175	z/fb:this	(Ljava/lang/String;)I
    //   1017: ior
    //   1018: invokespecial 157	z/lpT5:catch	(I)V
    //   1021: return
    //   1022: goto -77 -> 945
    //   1025: aload_0
    //   1026: ldc 25
    //   1028: aload_3
    //   1029: ldc -48
    //   1031: invokestatic 204	org/powerbot/misc/NUl:this	(Ljava/lang/Object;)Ljava/lang/String;
    //   1034: invokevirtual 175	z/fb:this	(Ljava/lang/String;)I
    //   1037: ior
    //   1038: invokespecial 157	z/lpT5:catch	(I)V
    //   1041: return
    //   1042: aload_0
    //   1043: ldc 25
    //   1045: aload_3
    //   1046: ldc -46
    //   1048: invokestatic 204	org/powerbot/misc/NUl:this	(Ljava/lang/Object;)Ljava/lang/String;
    //   1051: invokevirtual 175	z/fb:this	(Ljava/lang/String;)I
    //   1054: ior
    //   1055: invokespecial 157	z/lpT5:catch	(I)V
    //   1058: return
    //   1059: aload_0
    //   1060: dup
    //   1061: iload_2
    //   1062: invokespecial 212	z/lpT5:this	(I)I
    //   1065: invokespecial 157	z/lpT5:catch	(I)V
    //   1068: return
    //   1069: aload_0
    //   1070: ldc 42
    //   1072: aload_0
    //   1073: iconst_2
    //   1074: iconst_1
    //   1075: dup
    //   1076: pop2
    //   1077: invokespecial 179	z/lpT5:true	(I)V
    //   1080: invokespecial 157	z/lpT5:catch	(I)V
    //   1083: return
    //   1084: aload_0
    //   1085: ldc 23
    //   1087: ldc 48
    //   1089: aload_0
    //   1090: dup_x1
    //   1091: iconst_2
    //   1092: iconst_1
    //   1093: dup
    //   1094: pop2
    //   1095: invokespecial 179	z/lpT5:true	(I)V
    //   1098: invokespecial 157	z/lpT5:catch	(I)V
    //   1101: invokespecial 157	z/lpT5:catch	(I)V
    //   1104: return
    //   1105: aload_0
    //   1106: ldc 44
    //   1108: aload_0
    //   1109: iconst_2
    //   1110: iconst_1
    //   1111: dup
    //   1112: pop2
    //   1113: invokespecial 179	z/lpT5:true	(I)V
    //   1116: invokespecial 157	z/lpT5:catch	(I)V
    //   1119: return
    //   1120: aload_0
    //   1121: ldc 23
    //   1123: ldc 46
    //   1125: aload_0
    //   1126: dup_x1
    //   1127: iconst_2
    //   1128: iconst_1
    //   1129: dup
    //   1130: pop2
    //   1131: invokespecial 179	z/lpT5:true	(I)V
    //   1134: invokespecial 157	z/lpT5:catch	(I)V
    //   1137: invokespecial 157	z/lpT5:catch	(I)V
    //   1140: return
    //   1141: aload_0
    //   1142: dup
    //   1143: dup_x1
    //   1144: iconst_1
    //   1145: dup
    //   1146: dup
    //   1147: pop2
    //   1148: invokespecial 179	z/lpT5:true	(I)V
    //   1151: invokespecial 214	z/lpT5:this	()I
    //   1154: istore 5
    //   1156: ldc 8
    //   1158: iload 5
    //   1160: iadd
    //   1161: invokespecial 157	z/lpT5:catch	(I)V
    //   1164: return
    //   1165: aload_0
    //   1166: dup
    //   1167: invokespecial 214	z/lpT5:this	()I
    //   1170: istore 5
    //   1172: iload_2
    //   1173: iload 5
    //   1175: invokespecial 216	z/lpT5:this	(II)V
    //   1178: iload_2
    //   1179: ifle +1071 -> 2250
    //   1182: aload_0
    //   1183: iload_2
    //   1184: iconst_1
    //   1185: dup
    //   1186: dup
    //   1187: pop2
    //   1188: isub
    //   1189: invokespecial 212	z/lpT5:this	(I)I
    //   1192: dup
    //   1193: istore 6
    //   1195: ldc 48
    //   1197: if_icmpeq +10 -> 1207
    //   1200: iload 6
    //   1202: ldc 46
    //   1204: if_icmpne +16 -> 1220
    //   1207: aload_0
    //   1208: iload_2
    //   1209: iconst_1
    //   1210: dup
    //   1211: dup
    //   1212: pop2
    //   1213: isub
    //   1214: ldc 23
    //   1216: invokespecial 216	z/lpT5:this	(II)V
    //   1219: return
    //   1220: iload 6
    //   1222: ldc 13
    //   1224: iand
    //   1225: ldc 23
    //   1227: if_icmpeq +1023 -> 2250
    //   1230: aload_0
    //   1231: iload_2
    //   1232: iconst_1
    //   1233: dup
    //   1234: dup
    //   1235: pop2
    //   1236: isub
    //   1237: iload 6
    //   1239: ldc 15
    //   1241: ior
    //   1242: invokespecial 216	z/lpT5:this	(II)V
    //   1245: return
    //   1246: aload_0
    //   1247: dup
    //   1248: dup2
    //   1249: iconst_1
    //   1250: dup
    //   1251: dup
    //   1252: pop2
    //   1253: invokespecial 179	z/lpT5:true	(I)V
    //   1256: invokespecial 214	z/lpT5:this	()I
    //   1259: istore 5
    //   1261: iload_2
    //   1262: iload 5
    //   1264: invokespecial 216	z/lpT5:this	(II)V
    //   1267: iload_2
    //   1268: iconst_1
    //   1269: dup
    //   1270: dup
    //   1271: pop2
    //   1272: iadd
    //   1273: ldc 23
    //   1275: invokespecial 216	z/lpT5:this	(II)V
    //   1278: iload_2
    //   1279: ifle +971 -> 2250
    //   1282: aload_0
    //   1283: iload_2
    //   1284: iconst_1
    //   1285: dup
    //   1286: dup
    //   1287: pop2
    //   1288: isub
    //   1289: invokespecial 212	z/lpT5:this	(I)I
    //   1292: dup
    //   1293: istore 6
    //   1295: ldc 48
    //   1297: if_icmpeq +10 -> 1307
    //   1300: iload 6
    //   1302: ldc 46
    //   1304: if_icmpne +16 -> 1320
    //   1307: aload_0
    //   1308: iload_2
    //   1309: iconst_1
    //   1310: dup
    //   1311: dup
    //   1312: pop2
    //   1313: isub
    //   1314: ldc 23
    //   1316: invokespecial 216	z/lpT5:this	(II)V
    //   1319: return
    //   1320: iload 6
    //   1322: ldc 13
    //   1324: iand
    //   1325: ldc 23
    //   1327: if_icmpeq +923 -> 2250
    //   1330: aload_0
    //   1331: iload_2
    //   1332: iconst_1
    //   1333: dup
    //   1334: dup
    //   1335: pop2
    //   1336: isub
    //   1337: iload 6
    //   1339: ldc 15
    //   1341: ior
    //   1342: invokespecial 216	z/lpT5:this	(II)V
    //   1345: return
    //   1346: aload_0
    //   1347: iconst_3
    //   1348: iconst_1
    //   1349: dup
    //   1350: pop2
    //   1351: invokespecial 179	z/lpT5:true	(I)V
    //   1354: return
    //   1355: aload_0
    //   1356: iconst_4
    //   1357: iconst_1
    //   1358: dup
    //   1359: pop2
    //   1360: invokespecial 179	z/lpT5:true	(I)V
    //   1363: return
    //   1364: nop
    //   1365: nop
    //   1366: athrow
    //   1367: aload_0
    //   1368: iconst_1
    //   1369: dup
    //   1370: dup
    //   1371: pop2
    //   1372: invokespecial 179	z/lpT5:true	(I)V
    //   1375: return
    //   1376: aload_0
    //   1377: iconst_2
    //   1378: iconst_1
    //   1379: dup
    //   1380: pop2
    //   1381: invokespecial 179	z/lpT5:true	(I)V
    //   1384: return
    //   1385: aload_0
    //   1386: dup
    //   1387: dup_x1
    //   1388: invokespecial 214	z/lpT5:this	()I
    //   1391: dup
    //   1392: istore 5
    //   1394: invokespecial 157	z/lpT5:catch	(I)V
    //   1397: iload 5
    //   1399: invokespecial 157	z/lpT5:catch	(I)V
    //   1402: return
    //   1403: aload_0
    //   1404: dup
    //   1405: dup_x1
    //   1406: dup2
    //   1407: invokespecial 214	z/lpT5:this	()I
    //   1410: istore 5
    //   1412: invokespecial 214	z/lpT5:this	()I
    //   1415: istore 6
    //   1417: iload 5
    //   1419: invokespecial 157	z/lpT5:catch	(I)V
    //   1422: iload 6
    //   1424: invokespecial 157	z/lpT5:catch	(I)V
    //   1427: iload 5
    //   1429: invokespecial 157	z/lpT5:catch	(I)V
    //   1432: return
    //   1433: aload_0
    //   1434: dup
    //   1435: dup_x1
    //   1436: dup2
    //   1437: dup2
    //   1438: invokespecial 214	z/lpT5:this	()I
    //   1441: istore 5
    //   1443: invokespecial 214	z/lpT5:this	()I
    //   1446: istore 6
    //   1448: invokespecial 214	z/lpT5:this	()I
    //   1451: istore 7
    //   1453: iload 5
    //   1455: invokespecial 157	z/lpT5:catch	(I)V
    //   1458: iload 7
    //   1460: invokespecial 157	z/lpT5:catch	(I)V
    //   1463: iload 6
    //   1465: invokespecial 157	z/lpT5:catch	(I)V
    //   1468: iload 5
    //   1470: invokespecial 157	z/lpT5:catch	(I)V
    //   1473: return
    //   1474: aload_0
    //   1475: dup
    //   1476: dup2
    //   1477: dup2
    //   1478: invokespecial 214	z/lpT5:this	()I
    //   1481: istore 5
    //   1483: invokespecial 214	z/lpT5:this	()I
    //   1486: dup
    //   1487: istore 6
    //   1489: invokespecial 157	z/lpT5:catch	(I)V
    //   1492: iload 5
    //   1494: invokespecial 157	z/lpT5:catch	(I)V
    //   1497: iload 6
    //   1499: invokespecial 157	z/lpT5:catch	(I)V
    //   1502: iload 5
    //   1504: invokespecial 157	z/lpT5:catch	(I)V
    //   1507: return
    //   1508: aload_0
    //   1509: dup
    //   1510: dup2
    //   1511: dup2
    //   1512: dup2
    //   1513: invokespecial 214	z/lpT5:this	()I
    //   1516: istore 5
    //   1518: invokespecial 214	z/lpT5:this	()I
    //   1521: istore 6
    //   1523: invokespecial 214	z/lpT5:this	()I
    //   1526: istore 7
    //   1528: iload 6
    //   1530: invokespecial 157	z/lpT5:catch	(I)V
    //   1533: iload 5
    //   1535: invokespecial 157	z/lpT5:catch	(I)V
    //   1538: iload 7
    //   1540: invokespecial 157	z/lpT5:catch	(I)V
    //   1543: iload 6
    //   1545: invokespecial 157	z/lpT5:catch	(I)V
    //   1548: iload 5
    //   1550: invokespecial 157	z/lpT5:catch	(I)V
    //   1553: return
    //   1554: aload_0
    //   1555: dup
    //   1556: dup2
    //   1557: dup2
    //   1558: dup2
    //   1559: dup2
    //   1560: invokespecial 214	z/lpT5:this	()I
    //   1563: istore 5
    //   1565: invokespecial 214	z/lpT5:this	()I
    //   1568: istore 6
    //   1570: invokespecial 214	z/lpT5:this	()I
    //   1573: istore 7
    //   1575: invokespecial 214	z/lpT5:this	()I
    //   1578: istore 8
    //   1580: iload 6
    //   1582: invokespecial 157	z/lpT5:catch	(I)V
    //   1585: iload 5
    //   1587: invokespecial 157	z/lpT5:catch	(I)V
    //   1590: iload 8
    //   1592: invokespecial 157	z/lpT5:catch	(I)V
    //   1595: iload 7
    //   1597: invokespecial 157	z/lpT5:catch	(I)V
    //   1600: iload 6
    //   1602: invokespecial 157	z/lpT5:catch	(I)V
    //   1605: iload 5
    //   1607: invokespecial 157	z/lpT5:catch	(I)V
    //   1610: return
    //   1611: aload_0
    //   1612: dup
    //   1613: dup2
    //   1614: invokespecial 214	z/lpT5:this	()I
    //   1617: istore 5
    //   1619: invokespecial 214	z/lpT5:this	()I
    //   1622: istore 6
    //   1624: iload 5
    //   1626: invokespecial 157	z/lpT5:catch	(I)V
    //   1629: iload 6
    //   1631: invokespecial 157	z/lpT5:catch	(I)V
    //   1634: return
    //   1635: aload_0
    //   1636: ldc 42
    //   1638: aload_0
    //   1639: iconst_2
    //   1640: iconst_1
    //   1641: dup
    //   1642: pop2
    //   1643: invokespecial 179	z/lpT5:true	(I)V
    //   1646: invokespecial 157	z/lpT5:catch	(I)V
    //   1649: return
    //   1650: aload_0
    //   1651: ldc 23
    //   1653: ldc 48
    //   1655: aload_0
    //   1656: dup_x1
    //   1657: iconst_4
    //   1658: iconst_1
    //   1659: dup
    //   1660: pop2
    //   1661: invokespecial 179	z/lpT5:true	(I)V
    //   1664: invokespecial 157	z/lpT5:catch	(I)V
    //   1667: invokespecial 157	z/lpT5:catch	(I)V
    //   1670: return
    //   1671: aload_0
    //   1672: ldc 44
    //   1674: aload_0
    //   1675: iconst_2
    //   1676: iconst_1
    //   1677: dup
    //   1678: pop2
    //   1679: invokespecial 179	z/lpT5:true	(I)V
    //   1682: invokespecial 157	z/lpT5:catch	(I)V
    //   1685: return
    //   1686: aload_0
    //   1687: ldc 23
    //   1689: ldc 46
    //   1691: aload_0
    //   1692: dup_x1
    //   1693: iconst_4
    //   1694: iconst_1
    //   1695: dup
    //   1696: pop2
    //   1697: invokespecial 179	z/lpT5:true	(I)V
    //   1700: invokespecial 157	z/lpT5:catch	(I)V
    //   1703: invokespecial 157	z/lpT5:catch	(I)V
    //   1706: return
    //   1707: aload_0
    //   1708: ldc 23
    //   1710: ldc 48
    //   1712: aload_0
    //   1713: dup_x1
    //   1714: iconst_3
    //   1715: iconst_1
    //   1716: dup
    //   1717: pop2
    //   1718: invokespecial 179	z/lpT5:true	(I)V
    //   1721: invokespecial 157	z/lpT5:catch	(I)V
    //   1724: invokespecial 157	z/lpT5:catch	(I)V
    //   1727: return
    //   1728: aload_0
    //   1729: iload_2
    //   1730: ldc 42
    //   1732: invokespecial 216	z/lpT5:this	(II)V
    //   1735: return
    //   1736: aload_0
    //   1737: ldc 23
    //   1739: ldc 48
    //   1741: aload_0
    //   1742: dup_x1
    //   1743: iconst_1
    //   1744: dup
    //   1745: dup
    //   1746: pop2
    //   1747: invokespecial 179	z/lpT5:true	(I)V
    //   1750: invokespecial 157	z/lpT5:catch	(I)V
    //   1753: invokespecial 157	z/lpT5:catch	(I)V
    //   1756: return
    //   1757: aload_0
    //   1758: ldc 44
    //   1760: aload_0
    //   1761: iconst_1
    //   1762: dup
    //   1763: dup
    //   1764: pop2
    //   1765: invokespecial 179	z/lpT5:true	(I)V
    //   1768: invokespecial 157	z/lpT5:catch	(I)V
    //   1771: return
    //   1772: aload_0
    //   1773: ldc 23
    //   1775: ldc 46
    //   1777: aload_0
    //   1778: dup_x1
    //   1779: iconst_1
    //   1780: dup
    //   1781: dup
    //   1782: pop2
    //   1783: invokespecial 179	z/lpT5:true	(I)V
    //   1786: invokespecial 157	z/lpT5:catch	(I)V
    //   1789: invokespecial 157	z/lpT5:catch	(I)V
    //   1792: return
    //   1793: aload_0
    //   1794: ldc 42
    //   1796: aload_0
    //   1797: iconst_1
    //   1798: dup
    //   1799: dup
    //   1800: pop2
    //   1801: invokespecial 179	z/lpT5:true	(I)V
    //   1804: invokespecial 157	z/lpT5:catch	(I)V
    //   1807: return
    //   1808: aload_0
    //   1809: ldc 42
    //   1811: aload_0
    //   1812: iconst_4
    //   1813: iconst_1
    //   1814: dup
    //   1815: pop2
    //   1816: invokespecial 179	z/lpT5:true	(I)V
    //   1819: invokespecial 157	z/lpT5:catch	(I)V
    //   1822: return
    //   1823: new 218	java/lang/RuntimeException
    //   1826: dup
    //   1827: ldc -36
    //   1829: invokestatic 204	org/powerbot/misc/NUl:this	(Ljava/lang/Object;)Ljava/lang/String;
    //   1832: invokespecial 222	java/lang/RuntimeException:<init>	(Ljava/lang/String;)V
    //   1835: athrow
    //   1836: aload_0
    //   1837: aload_3
    //   1838: aload 4
    //   1840: getfield 224	z/ZA:byte	Ljava/lang/String;
    //   1843: invokespecial 226	z/lpT5:this	(Lz/fb;Ljava/lang/String;)V
    //   1846: return
    //   1847: aload_0
    //   1848: aload 4
    //   1850: getfield 224	z/ZA:byte	Ljava/lang/String;
    //   1853: invokespecial 228	z/lpT5:this	(Ljava/lang/String;)V
    //   1856: return
    //   1857: aload_0
    //   1858: aload_3
    //   1859: aload 4
    //   1861: aload_0
    //   1862: iconst_1
    //   1863: dup
    //   1864: dup
    //   1865: pop2
    //   1866: invokespecial 179	z/lpT5:true	(I)V
    //   1869: getfield 224	z/ZA:byte	Ljava/lang/String;
    //   1872: invokespecial 226	z/lpT5:this	(Lz/fb;Ljava/lang/String;)V
    //   1875: return
    //   1876: aload_0
    //   1877: dup
    //   1878: aload 4
    //   1880: getfield 224	z/ZA:byte	Ljava/lang/String;
    //   1883: invokespecial 228	z/lpT5:this	(Ljava/lang/String;)V
    //   1886: invokespecial 214	z/lpT5:this	()I
    //   1889: pop
    //   1890: return
    //   1891: aload_0
    //   1892: aload 4
    //   1894: getfield 224	z/ZA:byte	Ljava/lang/String;
    //   1897: invokespecial 228	z/lpT5:this	(Ljava/lang/String;)V
    //   1900: iload_1
    //   1901: sipush 184
    //   1904: iconst_1
    //   1905: dup
    //   1906: pop2
    //   1907: if_icmpeq +45 -> 1952
    //   1910: aload_0
    //   1911: invokespecial 214	z/lpT5:this	()I
    //   1914: istore 5
    //   1916: iload_1
    //   1917: sipush 183
    //   1920: iconst_1
    //   1921: dup
    //   1922: pop2
    //   1923: if_icmpne +29 -> 1952
    //   1926: aload 4
    //   1928: getfield 230	z/ZA:null	Ljava/lang/String;
    //   1931: iconst_0
    //   1932: iconst_1
    //   1933: dup
    //   1934: pop2
    //   1935: invokevirtual 162	java/lang/String:charAt	(I)C
    //   1938: bipush 60
    //   1940: iconst_1
    //   1941: dup
    //   1942: pop2
    //   1943: if_icmpne +9 -> 1952
    //   1946: aload_0
    //   1947: iload 5
    //   1949: invokespecial 232	z/lpT5:this	(I)V
    //   1952: aload_0
    //   1953: aload_3
    //   1954: aload 4
    //   1956: getfield 224	z/ZA:byte	Ljava/lang/String;
    //   1959: invokespecial 226	z/lpT5:this	(Lz/fb;Ljava/lang/String;)V
    //   1962: return
    //   1963: aload_0
    //   1964: aload_3
    //   1965: aload_0
    //   1966: aload 4
    //   1968: dup_x1
    //   1969: getfield 230	z/ZA:null	Ljava/lang/String;
    //   1972: invokespecial 228	z/lpT5:this	(Ljava/lang/String;)V
    //   1975: getfield 230	z/ZA:null	Ljava/lang/String;
    //   1978: invokespecial 226	z/lpT5:this	(Lz/fb;Ljava/lang/String;)V
    //   1981: return
    //   1982: aload_0
    //   1983: ldc 27
    //   1985: aload_3
    //   1986: aload 4
    //   1988: getfield 190	z/ZA:if	Ljava/lang/String;
    //   1991: iload_2
    //   1992: invokevirtual 125	z/fb:this	(Ljava/lang/String;I)I
    //   1995: ior
    //   1996: invokespecial 157	z/lpT5:catch	(I)V
    //   1999: return
    //   2000: aload_0
    //   2001: invokespecial 214	z/lpT5:this	()I
    //   2004: pop
    //   2005: iload_2
    //   2006: tableswitch	default:+98->2104, 4:+42->2048, 5:+53->2059, 6:+84->2090, 7:+91->2097, 8:+60->2066, 9:+67->2073, 10:+77->2083
    //   2048: aload_0
    //   2049: iconst_0
    //   2050: ifne +30 -> 2080
    //   2053: ldc -23
    //   2055: invokespecial 157	z/lpT5:catch	(I)V
    //   2058: return
    //   2059: aload_0
    //   2060: ldc -22
    //   2062: invokespecial 157	z/lpT5:catch	(I)V
    //   2065: return
    //   2066: aload_0
    //   2067: ldc -21
    //   2069: invokespecial 157	z/lpT5:catch	(I)V
    //   2072: return
    //   2073: aload_0
    //   2074: ldc -20
    //   2076: invokespecial 157	z/lpT5:catch	(I)V
    //   2079: return
    //   2080: goto -31 -> 2049
    //   2083: aload_0
    //   2084: ldc -19
    //   2086: invokespecial 157	z/lpT5:catch	(I)V
    //   2089: return
    //   2090: aload_0
    //   2091: ldc -18
    //   2093: invokespecial 157	z/lpT5:catch	(I)V
    //   2096: return
    //   2097: aload_0
    //   2098: ldc -17
    //   2100: invokespecial 157	z/lpT5:catch	(I)V
    //   2103: return
    //   2104: aload_0
    //   2105: ldc -16
    //   2107: invokespecial 157	z/lpT5:catch	(I)V
    //   2110: return
    //   2111: aload 4
    //   2113: getfield 190	z/ZA:if	Ljava/lang/String;
    //   2116: dup
    //   2117: astore 9
    //   2119: iconst_0
    //   2120: aload_0
    //   2121: invokespecial 214	z/lpT5:this	()I
    //   2124: pop
    //   2125: iconst_1
    //   2126: dup
    //   2127: pop2
    //   2128: invokevirtual 162	java/lang/String:charAt	(I)C
    //   2131: bipush 91
    //   2133: iconst_1
    //   2134: dup
    //   2135: pop2
    //   2136: if_icmpne +35 -> 2171
    //   2139: aload_0
    //   2140: new 242	java/lang/StringBuilder
    //   2143: aload_3
    //   2144: dup_x1
    //   2145: dup
    //   2146: pop2
    //   2147: dup
    //   2148: invokespecial 243	java/lang/StringBuilder:<init>	()V
    //   2151: bipush 91
    //   2153: iconst_1
    //   2154: dup
    //   2155: pop2
    //   2156: invokevirtual 247	java/lang/StringBuilder:append	(C)Ljava/lang/StringBuilder;
    //   2159: aload 9
    //   2161: invokevirtual 250	java/lang/StringBuilder:append	(Ljava/lang/String;)Ljava/lang/StringBuilder;
    //   2164: invokevirtual 253	java/lang/StringBuilder:toString	()Ljava/lang/String;
    //   2167: invokespecial 226	z/lpT5:this	(Lz/fb;Ljava/lang/String;)V
    //   2170: return
    //   2171: aload_0
    //   2172: ldc -2
    //   2174: aload_3
    //   2175: aload 9
    //   2177: invokevirtual 175	z/fb:this	(Ljava/lang/String;)I
    //   2180: ior
    //   2181: invokespecial 157	z/lpT5:catch	(I)V
    //   2184: return
    //   2185: aload 4
    //   2187: getfield 190	z/ZA:if	Ljava/lang/String;
    //   2190: dup
    //   2191: astore 9
    //   2193: iconst_0
    //   2194: aload_0
    //   2195: invokespecial 214	z/lpT5:this	()I
    //   2198: pop
    //   2199: iconst_1
    //   2200: dup
    //   2201: pop2
    //   2202: invokevirtual 162	java/lang/String:charAt	(I)C
    //   2205: bipush 91
    //   2207: iconst_1
    //   2208: dup
    //   2209: pop2
    //   2210: if_icmpne +11 -> 2221
    //   2213: aload_0
    //   2214: aload_3
    //   2215: aload 9
    //   2217: invokespecial 226	z/lpT5:this	(Lz/fb;Ljava/lang/String;)V
    //   2220: return
    //   2221: aload_0
    //   2222: ldc 25
    //   2224: aload_3
    //   2225: aload 9
    //   2227: invokevirtual 175	z/fb:this	(Ljava/lang/String;)I
    //   2230: ior
    //   2231: invokespecial 157	z/lpT5:catch	(I)V
    //   2234: return
    //   2235: aload_0
    //   2236: aload_3
    //   2237: aload 4
    //   2239: aload_0
    //   2240: iload_2
    //   2241: invokespecial 179	z/lpT5:true	(I)V
    //   2244: getfield 190	z/ZA:if	Ljava/lang/String;
    //   2247: invokespecial 226	z/lpT5:this	(Lz/fb;Ljava/lang/String;)V
    //   2250: return
    // Line number table:
    //   Java source line #955	-> byte code offset #0
    //   Java source line #966	-> byte code offset #816
    //   Java source line #968	-> byte code offset #822
    //   Java source line #969	-> byte code offset #828
    //   Java source line #980	-> byte code offset #830
    //   Java source line #981	-> byte code offset #836
    //   Java source line #985	-> byte code offset #837
    //   Java source line #986	-> byte code offset #846
    //   Java source line #987	-> byte code offset #849
    //   Java source line #992	-> byte code offset #850
    //   Java source line #993	-> byte code offset #856
    //   Java source line #997	-> byte code offset #857
    //   Java source line #998	-> byte code offset #866
    //   Java source line #999	-> byte code offset #869
    //   Java source line #1001	-> byte code offset #870
    //   Java source line #1003	-> byte code offset #944
    //   Java source line #1004	-> byte code offset #954
    //   Java source line #1006	-> byte code offset #955
    //   Java source line #1007	-> byte code offset #964
    //   Java source line #1008	-> byte code offset #967
    //   Java source line #1010	-> byte code offset #968
    //   Java source line #1011	-> byte code offset #974
    //   Java source line #1013	-> byte code offset #975
    //   Java source line #1014	-> byte code offset #984
    //   Java source line #1015	-> byte code offset #987
    //   Java source line #1017	-> byte code offset #988
    //   Java source line #1018	-> byte code offset #1004
    //   Java source line #1020	-> byte code offset #1005
    //   Java source line #1021	-> byte code offset #1021
    //   Java source line #1023	-> byte code offset #1025
    //   Java source line #1024	-> byte code offset #1041
    //   Java source line #1027	-> byte code offset #1042
    //   Java source line #1029	-> byte code offset #1058
    //   Java source line #1031	-> byte code offset #1059
    //   Java source line #1032	-> byte code offset #1068
    //   Java source line #1037	-> byte code offset #1069
    //   Java source line #1038	-> byte code offset #1080
    //   Java source line #1039	-> byte code offset #1083
    //   Java source line #1042	-> byte code offset #1084
    //   Java source line #1043	-> byte code offset #1098
    //   Java source line #1044	-> byte code offset #1101
    //   Java source line #1045	-> byte code offset #1104
    //   Java source line #1047	-> byte code offset #1105
    //   Java source line #1048	-> byte code offset #1116
    //   Java source line #1049	-> byte code offset #1119
    //   Java source line #1052	-> byte code offset #1120
    //   Java source line #1053	-> byte code offset #1134
    //   Java source line #1054	-> byte code offset #1137
    //   Java source line #1055	-> byte code offset #1140
    //   Java source line #1057	-> byte code offset #1141
    //   Java source line #1058	-> byte code offset #1151
    //   Java source line #1059	-> byte code offset #1156
    //   Java source line #1060	-> byte code offset #1164
    //   Java source line #1064	-> byte code offset #1165
    //   Java source line #1065	-> byte code offset #1172
    //   Java source line #1066	-> byte code offset #1178
    //   Java source line #1067	-> byte code offset #1182
    //   Java source line #1069	-> byte code offset #1195
    //   Java source line #1070	-> byte code offset #1207
    //   Java source line #1071	-> byte code offset #1220
    //   Java source line #1072	-> byte code offset #1230
    //   Java source line #1078	-> byte code offset #1246
    //   Java source line #1079	-> byte code offset #1256
    //   Java source line #1080	-> byte code offset #1261
    //   Java source line #1081	-> byte code offset #1267
    //   Java source line #1082	-> byte code offset #1278
    //   Java source line #1083	-> byte code offset #1282
    //   Java source line #1085	-> byte code offset #1295
    //   Java source line #1086	-> byte code offset #1307
    //   Java source line #1087	-> byte code offset #1320
    //   Java source line #1088	-> byte code offset #1330
    //   Java source line #1098	-> byte code offset #1346
    //   Java source line #1099	-> byte code offset #1354
    //   Java source line #1102	-> byte code offset #1355
    //   Java source line #1103	-> byte code offset #1363
    //   Java source line #1121	-> byte code offset #1367
    //   Java source line #1122	-> byte code offset #1375
    //   Java source line #1134	-> byte code offset #1376
    //   Java source line #1135	-> byte code offset #1384
    //   Java source line #1137	-> byte code offset #1385
    //   Java source line #1138	-> byte code offset #1394
    //   Java source line #1139	-> byte code offset #1397
    //   Java source line #1140	-> byte code offset #1402
    //   Java source line #1142	-> byte code offset #1403
    //   Java source line #1143	-> byte code offset #1412
    //   Java source line #1144	-> byte code offset #1417
    //   Java source line #1145	-> byte code offset #1422
    //   Java source line #1146	-> byte code offset #1427
    //   Java source line #1147	-> byte code offset #1432
    //   Java source line #1149	-> byte code offset #1433
    //   Java source line #1150	-> byte code offset #1443
    //   Java source line #1151	-> byte code offset #1448
    //   Java source line #1152	-> byte code offset #1453
    //   Java source line #1153	-> byte code offset #1458
    //   Java source line #1154	-> byte code offset #1463
    //   Java source line #1155	-> byte code offset #1468
    //   Java source line #1156	-> byte code offset #1473
    //   Java source line #1158	-> byte code offset #1474
    //   Java source line #1159	-> byte code offset #1483
    //   Java source line #1160	-> byte code offset #1489
    //   Java source line #1161	-> byte code offset #1492
    //   Java source line #1162	-> byte code offset #1497
    //   Java source line #1163	-> byte code offset #1502
    //   Java source line #1164	-> byte code offset #1507
    //   Java source line #1166	-> byte code offset #1508
    //   Java source line #1167	-> byte code offset #1518
    //   Java source line #1168	-> byte code offset #1523
    //   Java source line #1169	-> byte code offset #1528
    //   Java source line #1170	-> byte code offset #1533
    //   Java source line #1171	-> byte code offset #1538
    //   Java source line #1172	-> byte code offset #1543
    //   Java source line #1173	-> byte code offset #1548
    //   Java source line #1174	-> byte code offset #1553
    //   Java source line #1176	-> byte code offset #1554
    //   Java source line #1177	-> byte code offset #1565
    //   Java source line #1178	-> byte code offset #1570
    //   Java source line #1179	-> byte code offset #1575
    //   Java source line #1180	-> byte code offset #1580
    //   Java source line #1181	-> byte code offset #1585
    //   Java source line #1182	-> byte code offset #1590
    //   Java source line #1183	-> byte code offset #1595
    //   Java source line #1184	-> byte code offset #1600
    //   Java source line #1185	-> byte code offset #1605
    //   Java source line #1186	-> byte code offset #1610
    //   Java source line #1188	-> byte code offset #1611
    //   Java source line #1189	-> byte code offset #1619
    //   Java source line #1190	-> byte code offset #1624
    //   Java source line #1191	-> byte code offset #1629
    //   Java source line #1192	-> byte code offset #1634
    //   Java source line #1208	-> byte code offset #1635
    //   Java source line #1209	-> byte code offset #1646
    //   Java source line #1210	-> byte code offset #1649
    //   Java source line #1219	-> byte code offset #1650
    //   Java source line #1220	-> byte code offset #1664
    //   Java source line #1221	-> byte code offset #1667
    //   Java source line #1222	-> byte code offset #1670
    //   Java source line #1230	-> byte code offset #1671
    //   Java source line #1231	-> byte code offset #1682
    //   Java source line #1232	-> byte code offset #1685
    //   Java source line #1238	-> byte code offset #1686
    //   Java source line #1239	-> byte code offset #1700
    //   Java source line #1240	-> byte code offset #1703
    //   Java source line #1241	-> byte code offset #1706
    //   Java source line #1245	-> byte code offset #1707
    //   Java source line #1246	-> byte code offset #1721
    //   Java source line #1247	-> byte code offset #1724
    //   Java source line #1248	-> byte code offset #1727
    //   Java source line #1250	-> byte code offset #1728
    //   Java source line #1251	-> byte code offset #1735
    //   Java source line #1254	-> byte code offset #1736
    //   Java source line #1255	-> byte code offset #1750
    //   Java source line #1256	-> byte code offset #1753
    //   Java source line #1257	-> byte code offset #1756
    //   Java source line #1259	-> byte code offset #1757
    //   Java source line #1260	-> byte code offset #1768
    //   Java source line #1261	-> byte code offset #1771
    //   Java source line #1264	-> byte code offset #1772
    //   Java source line #1265	-> byte code offset #1786
    //   Java source line #1266	-> byte code offset #1789
    //   Java source line #1267	-> byte code offset #1792
    //   Java source line #1271	-> byte code offset #1793
    //   Java source line #1272	-> byte code offset #1804
    //   Java source line #1273	-> byte code offset #1807
    //   Java source line #1277	-> byte code offset #1808
    //   Java source line #1278	-> byte code offset #1819
    //   Java source line #1279	-> byte code offset #1822
    //   Java source line #1282	-> byte code offset #1823
    //   Java source line #1285	-> byte code offset #1836
    //   Java source line #1286	-> byte code offset #1846
    //   Java source line #1288	-> byte code offset #1847
    //   Java source line #1289	-> byte code offset #1856
    //   Java source line #1291	-> byte code offset #1857
    //   Java source line #1292	-> byte code offset #1869
    //   Java source line #1293	-> byte code offset #1875
    //   Java source line #1295	-> byte code offset #1876
    //   Java source line #1296	-> byte code offset #1886
    //   Java source line #1297	-> byte code offset #1890
    //   Java source line #1302	-> byte code offset #1891
    //   Java source line #1303	-> byte code offset #1900
    //   Java source line #1304	-> byte code offset #1910
    //   Java source line #1305	-> byte code offset #1916
    //   Java source line #1306	-> byte code offset #1935
    //   Java source line #1307	-> byte code offset #1946
    //   Java source line #1310	-> byte code offset #1952
    //   Java source line #1311	-> byte code offset #1962
    //   Java source line #1313	-> byte code offset #1963
    //   Java source line #1314	-> byte code offset #1975
    //   Java source line #1315	-> byte code offset #1981
    //   Java source line #1317	-> byte code offset #1982
    //   Java source line #1318	-> byte code offset #1999
    //   Java source line #1320	-> byte code offset #2000
    //   Java source line #1321	-> byte code offset #2005
    //   Java source line #1323	-> byte code offset #2048
    //   Java source line #1324	-> byte code offset #2058
    //   Java source line #1326	-> byte code offset #2059
    //   Java source line #1327	-> byte code offset #2065
    //   Java source line #1329	-> byte code offset #2066
    //   Java source line #1330	-> byte code offset #2072
    //   Java source line #1332	-> byte code offset #2073
    //   Java source line #1333	-> byte code offset #2079
    //   Java source line #1335	-> byte code offset #2083
    //   Java source line #1336	-> byte code offset #2089
    //   Java source line #1338	-> byte code offset #2090
    //   Java source line #1339	-> byte code offset #2096
    //   Java source line #1341	-> byte code offset #2097
    //   Java source line #1342	-> byte code offset #2103
    //   Java source line #1345	-> byte code offset #2104
    //   Java source line #1346	-> byte code offset #2110
    //   Java source line #1350	-> byte code offset #2111
    //   Java source line #1351	-> byte code offset #2120
    //   Java source line #1352	-> byte code offset #2125
    //   Java source line #1353	-> byte code offset #2139
    //   Java source line #1355	-> byte code offset #2171
    //   Java source line #1357	-> byte code offset #2184
    //   Java source line #1359	-> byte code offset #2185
    //   Java source line #1360	-> byte code offset #2194
    //   Java source line #1361	-> byte code offset #2199
    //   Java source line #1362	-> byte code offset #2213
    //   Java source line #1364	-> byte code offset #2221
    //   Java source line #1366	-> byte code offset #2234
    //   Java source line #1369	-> byte code offset #2235
    //   Java source line #1370	-> byte code offset #2244
    //   Java source line #1373	-> byte code offset #2250
    // Local variable table:
    //   start	length	slot	name	signature
    //   0	2251	0	a	lpT5
    //   0	2251	1	a	int
    //   0	2251	2	a	int
    //   0	2251	3	a	fb
    //   0	2251	4	a	ZA
  }
}
