package z;






















public class LPt9
  extends cOn
{
  private final GA jdField_void;
  




















  public LPt9(cOn a, GA a)
  {
    a.<init>(327680, a);
    jdField_void_of_type_ZGA = a;
  }
  


  public void jdMethod_this(int a, int a, String a, String a, String a, String[] a)
  {
    if ((a & 0x20000) != 0) {
      jdField_void_of_type_ZGA.jdMethod_for(Gb.jdMethod_this("u`AwTfPqTa"));
    }
    int tmp25_24 = 1;tmp25_24; if ((0x1000 & tmp25_24) != 0) {
      jdField_void_of_type_ZGA.jdMethod_for(com9.jdMethod_this("^Mc@eQy]n"));
    }
    jdField_void_of_type_ZGA.jdMethod_true(a);
    if (a != null)
    {
      jdField_void_of_type_ZGA.jdMethod_for(a);
    }
    if (a != null)
      jdField_void_of_type_ZGA.jdMethod_true(a);
    int i;
    if (a != null) {
      int tmp102_101 = 1;
      








































































      for (tmp102_101; (i = tmp102_101) < a.length;) { 
          jdField_void_of_type_ZGA.jdMethod_true(a[(i++)]);tmpTernaryOp = i; continue;throw 0;
      }
    }
    jdField_void_of_type_ZCOn.jdMethod_this(a, a, a, a, a, a);
  }
  
  public void jdMethod_this(String a, String a)
  {
    if (a != null)
    {
      jdField_void_of_type_ZGA.jdMethod_for(a);
    }
    if (a != null) {
      jdField_void_of_type_ZGA.jdMethod_for(Gb.jdMethod_this("bjDwR`u`SpV@IqTkBl^k"));
    }
    jdField_void_of_type_ZCOn.jdMethod_this(a, a);
  }
  


  public void jdMethod_this(String a, String a, String a)
  {
    jdField_void_of_type_ZGA.jdMethod_true(a);
    if ((jdField_void_of_type_ZGA.jdMethod_for(com9.jdMethod_this("HZnXbGdZjyh@e[i")) != null) && (a != null)) {
      jdField_void_of_type_ZGA.jdMethod_this(a, a);
    }
    jdField_void_of_type_ZCOn.jdMethod_this(a, a, a);
  }
  
  /* Error */
  public aux jdMethod_this(String a, boolean a)
  {
    // Byte code:
    //   0: iload_2
    //   1: aload_0
    //   2: getfield 15	z/LPt9:jdField_void_of_type_ZGA	Lz/GA;
    //   5: aload_1
    //   6: invokevirtual 34	z/GA:for	(Ljava/lang/String;)Lz/Xb;
    //   9: pop
    //   10: ifeq +20 -> 30
    //   13: aload_0
    //   14: getfield 15	z/LPt9:jdField_void_of_type_ZGA	Lz/GA;
    //   17: ldc 74
    //   19: invokestatic 28	z/Gb:this	(Ljava/lang/Object;)Ljava/lang/String;
    //   22: invokevirtual 34	z/GA:for	(Ljava/lang/String;)Lz/Xb;
    //   25: pop
    //   26: goto +17 -> 43
    //   29: athrow
    //   30: aload_0
    //   31: getfield 15	z/LPt9:jdField_void_of_type_ZGA	Lz/GA;
    //   34: ldc 76
    //   36: invokestatic 39	z/com9:this	(Ljava/lang/Object;)Ljava/lang/String;
    //   39: invokevirtual 34	z/GA:for	(Ljava/lang/String;)Lz/Xb;
    //   42: pop
    //   43: new 78	z/LA
    //   46: dup
    //   47: aload_0
    //   48: getfield 46	z/LPt9:jdField_void_of_type_ZCOn	Lz/cOn;
    //   51: aload_1
    //   52: iload_2
    //   53: invokevirtual 80	z/cOn:this	(Ljava/lang/String;Z)Lz/aux;
    //   56: aload_0
    //   57: getfield 15	z/LPt9:jdField_void_of_type_ZGA	Lz/GA;
    //   60: invokespecial 83	z/LA:<init>	(Lz/aux;Lz/GA;)V
    //   63: areturn
    // Line number table:
    //   Java source line #107	-> byte code offset #1
    //   Java source line #108	-> byte code offset #10
    //   Java source line #109	-> byte code offset #13
    //   Java source line #111	-> byte code offset #30
    //   Java source line #113	-> byte code offset #43
    // Local variable table:
    //   start	length	slot	name	signature
    //   0	64	0	a	LPt9
    //   0	64	1	a	String
    //   0	64	2	a	int
  }
  
  /* Error */
  public aux jdMethod_this(int a, Qa a, String a, boolean a)
  {
    // Byte code:
    //   0: iload 4
    //   2: aload_0
    //   3: getfield 15	z/LPt9:jdField_void_of_type_ZGA	Lz/GA;
    //   6: aload_3
    //   7: invokevirtual 34	z/GA:for	(Ljava/lang/String;)Lz/Xb;
    //   10: pop
    //   11: ifeq +20 -> 31
    //   14: aload_0
    //   15: getfield 15	z/LPt9:jdField_void_of_type_ZGA	Lz/GA;
    //   18: ldc 86
    //   20: invokestatic 28	z/Gb:this	(Ljava/lang/Object;)Ljava/lang/String;
    //   23: invokevirtual 34	z/GA:for	(Ljava/lang/String;)Lz/Xb;
    //   26: pop
    //   27: goto +17 -> 44
    //   30: athrow
    //   31: aload_0
    //   32: getfield 15	z/LPt9:jdField_void_of_type_ZGA	Lz/GA;
    //   35: ldc 88
    //   37: invokestatic 39	z/com9:this	(Ljava/lang/Object;)Ljava/lang/String;
    //   40: invokevirtual 34	z/GA:for	(Ljava/lang/String;)Lz/Xb;
    //   43: pop
    //   44: new 78	z/LA
    //   47: dup
    //   48: aload_0
    //   49: getfield 46	z/LPt9:jdField_void_of_type_ZCOn	Lz/cOn;
    //   52: aload_3
    //   53: iload 4
    //   55: invokevirtual 80	z/cOn:this	(Ljava/lang/String;Z)Lz/aux;
    //   58: aload_0
    //   59: getfield 15	z/LPt9:jdField_void_of_type_ZGA	Lz/GA;
    //   62: invokespecial 83	z/LA:<init>	(Lz/aux;Lz/GA;)V
    //   65: areturn
    // Line number table:
    //   Java source line #120	-> byte code offset #2
    //   Java source line #121	-> byte code offset #11
    //   Java source line #122	-> byte code offset #14
    //   Java source line #124	-> byte code offset #31
    //   Java source line #126	-> byte code offset #44
    // Local variable table:
    //   start	length	slot	name	signature
    //   0	66	0	a	LPt9
    //   0	66	1	a	int
    //   0	66	2	a	Qa
    //   0	66	3	a	String
    //   0	66	4	a	int
  }
  
  public void jdMethod_this(lpt6 a)
  {
    jdField_void_of_type_ZCOn.jdMethod_this(a);
  }
  

  public void jdMethod_this(String a, String a, String a, int a)
  {
    jdField_void_of_type_ZGA.jdMethod_for(Gb.jdMethod_this("xk_`CF]dBvTv"));
    if (a != null) {
      jdField_void_of_type_ZGA.jdMethod_true(a);
    }
    if (a != null) {
      jdField_void_of_type_ZGA.jdMethod_true(a);
    }
    if (a != null) {
      jdField_void_of_type_ZGA.jdMethod_for(a);
    }
    jdField_void_of_type_ZCOn.jdMethod_this(a, a, a, a);
  }
  

  public auX jdMethod_this(int a, String a, String a, String a, Object a)
  {
    int tmp5_4 = 1;tmp5_4; if ((0x1000 & tmp5_4) != 0) {
      jdField_void_of_type_ZGA.jdMethod_for(com9.jdMethod_this("^Mc@eQy]n"));
    }
    if ((a & 0x20000) != 0) {
      jdField_void_of_type_ZGA.jdMethod_for(Gb.jdMethod_this("u`AwTfPqTa"));
    }
    
    jdField_void_of_type_ZGA.jdMethod_for(a);
    if (a != null)
    {
      jdField_void_of_type_ZGA.jdMethod_for(a);
    }
    if (a != null) {
      jdField_void_of_type_ZGA.jdMethod_this(a);
    }
    return new wA(jdField_void_of_type_ZCOn.jdMethod_this(a, a, a, a, a), jdField_void_of_type_ZGA);
  }
  


  public cON jdMethod_this(int a, String a, String a, String a, String[] a)
  {
    int tmp5_4 = 1;tmp5_4; if ((0x1000 & tmp5_4) != 0) {
      jdField_void_of_type_ZGA.jdMethod_for(Gb.jdMethod_this("VHkEmTqXf"));
    }
    if ((a & 0x20000) != 0) {
      jdField_void_of_type_ZGA.jdMethod_for(com9.jdMethod_this("phDQnUyQi"));
    }
    
    jdField_void_of_type_ZGA.jdMethod_for(a);
    if (a != null)
    {
      jdField_void_of_type_ZGA.jdMethod_for(a); }
    int i;
    if (a != null)
    {
      int tmp107_106 = 1;tmp107_106;i = tmp107_106; for (0; i < a.length;) { 
          jdField_void_of_type_ZGA.jdMethod_true(a[(i++)]);tmpTernaryOp = i; continue;throw jdField_void_of_type_ZGA.jdMethod_for(com9.jdMethod_this("quWhDy]bZ~"));
      }
    }
    return new LPT9(jdField_void_of_type_ZCOn.jdMethod_this(a, a, a, a, a), jdField_void_of_type_ZGA);
  }
}
