package z;















public class P
  extends cOn
{
  public final Gb jdField_new;
  













  public String jdField_void;
  













  public P(cOn a, Gb a)
  {
    a.<init>(327680, a, a);
  }
  
  public P(int a, cOn a, Gb a)
  {
    a.<init>(a, a);
    jdField_new = a;
  }
  

  public void jdMethod_this(int a, int a, String a, String a, String a, String[] a)
  {
    jdField_void = a; int 
      tmp24_23 = 1;tmp24_23;
    if (a == null) { tmpTernaryOp = null; break label57; throw jdField_new.jdMethod_catch(a);
    }
    label57:
    a.jdMethod_this(a, a, jdField_new.jdMethod_catch(a), jdField_new, a
      .jdMethod_this(0, tmp24_23), jdField_new
      .jdMethod_this(a));
  }
  
  /* Error */
  public aux jdMethod_this(String a, boolean a)
  {
    // Byte code:
    //   0: aload_0
    //   1: dup
    //   2: getfield 23	z/P:new	Lz/Gb;
    //   5: aload_1
    //   6: invokevirtual 52	z/Gb:for	(Ljava/lang/String;)Ljava/lang/String;
    //   9: iload_2
    //   10: invokespecial 54	z/cOn:this	(Ljava/lang/String;Z)Lz/aux;
    //   13: dup
    //   14: astore_1
    //   15: ifnonnull +6 -> 21
    //   18: aconst_null
    //   19: areturn
    //   20: athrow
    //   21: aload_0
    //   22: aload_1
    //   23: invokevirtual 57	z/P:this	(Lz/aux;)Lz/aux;
    //   26: areturn
    // Line number table:
    //   Java source line #72	-> byte code offset #0
    //   Java source line #74	-> byte code offset #15
    // Local variable table:
    //   start	length	slot	name	signature
    //   0	27	0	a	P
    //   0	27	1	a	String
    //   0	27	2	a	int
  }
  
  /* Error */
  public aux jdMethod_this(int a, Qa a, String a, boolean a)
  {
    // Byte code:
    //   0: iload_1
    //   1: aload_2
    //   2: aload_0
    //   3: dup_x2
    //   4: getfield 23	z/P:new	Lz/Gb;
    //   7: aload_3
    //   8: invokevirtual 52	z/Gb:for	(Ljava/lang/String;)Ljava/lang/String;
    //   11: iload 4
    //   13: invokespecial 62	z/cOn:this	(ILz/Qa;Ljava/lang/String;Z)Lz/aux;
    //   16: dup
    //   17: astore_1
    //   18: ifnonnull +6 -> 24
    //   21: aconst_null
    //   22: areturn
    //   23: athrow
    //   24: aload_0
    //   25: aload_1
    //   26: invokevirtual 57	z/P:this	(Lz/aux;)Lz/aux;
    //   29: areturn
    // Line number table:
    //   Java source line #80	-> byte code offset #0
    //   Java source line #81	-> byte code offset #8
    //   Java source line #80	-> byte code offset #13
    //   Java source line #82	-> byte code offset #18
    // Local variable table:
    //   start	length	slot	name	signature
    //   0	30	0	a	P
    //   0	30	1	a	int
    //   0	30	2	a	Qa
    //   0	30	3	a	String
    //   0	30	4	a	int
  }
  
  public auX jdMethod_this(int a, String a, String a, String a, Object a)
  {
    int tmp30_29 = 1; int tmp31_30 = tmp30_29;tmp31_30;
    
    if ((a = a.jdMethod_this(jdField_new.jdMethod_this(jdField_void, a, a), jdField_new.jdMethod_for(a), jdField_new, a.jdMethod_this(tmp30_29, tmp31_30), jdField_new.jdMethod_this(a))) == null) { return null;throw a; } return a.jdMethod_this(a);
  }
  
  /* Error */
  public cON jdMethod_this(int a, String a, String a, String a, String[] a)
  {
    // Byte code:
    //   0: aload_0
    //   1: getfield 23	z/P:new	Lz/Gb;
    //   4: aload_3
    //   5: invokevirtual 86	z/Gb:true	(Ljava/lang/String;)Ljava/lang/String;
    //   8: astore 6
    //   10: iload_1
    //   11: aload_0
    //   12: getfield 23	z/P:new	Lz/Gb;
    //   15: aload_0
    //   16: dup_x2
    //   17: getfield 28	z/P:void	Ljava/lang/String;
    //   20: aload_2
    //   21: aload_3
    //   22: invokevirtual 88	z/Gb:true	(Ljava/lang/String;Ljava/lang/String;Ljava/lang/String;)Ljava/lang/String;
    //   25: aload 6
    //   27: aload_0
    //   28: getfield 23	z/P:new	Lz/Gb;
    //   31: aload 4
    //   33: iconst_0
    //   34: iconst_1
    //   35: dup
    //   36: pop2
    //   37: invokevirtual 37	z/Gb:this	(Ljava/lang/String;Z)Ljava/lang/String;
    //   40: aload 5
    //   42: ifnonnull +8 -> 50
    //   45: aconst_null
    //   46: goto +13 -> 59
    //   49: athrow
    //   50: aload_0
    //   51: getfield 23	z/P:new	Lz/Gb;
    //   54: aload 5
    //   56: invokevirtual 40	z/Gb:this	([Ljava/lang/String;)[Ljava/lang/String;
    //   59: invokespecial 90	z/cOn:this	(ILjava/lang/String;Ljava/lang/String;Ljava/lang/String;[Ljava/lang/String;)Lz/cON;
    //   62: dup
    //   63: astore_1
    //   64: ifnonnull +6 -> 70
    //   67: aconst_null
    //   68: areturn
    //   69: athrow
    //   70: aload_0
    //   71: aload_1
    //   72: invokevirtual 93	z/P:this	(Lz/cON;)Lz/cON;
    //   75: areturn
    // Line number table:
    //   Java source line #98	-> byte code offset #0
    //   Java source line #99	-> byte code offset #10
    //   Java source line #100	-> byte code offset #37
    //   Java source line #102	-> byte code offset #56
    //   Java source line #99	-> byte code offset #59
    //   Java source line #103	-> byte code offset #64
    // Local variable table:
    //   start	length	slot	name	signature
    //   0	76	0	a	P
    //   0	76	1	a	int
    //   0	76	2	a	String
    //   0	76	3	a	String
    //   0	76	4	a	String
    //   0	76	5	a	String[]
  }
  
  public void jdMethod_this(String a, String a, String a, int a)
  {
    if (a == null) { tmpTernaryOp = a; break label28; throw null; } label28: a.jdMethod_this(jdField_new.jdMethod_catch(a), jdField_new
      .jdMethod_catch(a), a, a);
  }
  
  /* Error */
  public void jdMethod_this(String a, String a, String a)
  {
    // Byte code:
    //   0: aload_0
    //   1: dup
    //   2: getfield 23	z/P:new	Lz/Gb;
    //   5: aload_1
    //   6: invokevirtual 34	z/Gb:catch	(Ljava/lang/String;)Ljava/lang/String;
    //   9: aload_2
    //   10: ifnonnull +9 -> 19
    //   13: aconst_null
    //   14: aload_3
    //   15: goto +15 -> 30
    //   18: athrow
    //   19: aload_0
    //   20: getfield 23	z/P:new	Lz/Gb;
    //   23: aload_1
    //   24: aload_2
    //   25: aload_3
    //   26: invokevirtual 88	z/Gb:true	(Ljava/lang/String;Ljava/lang/String;Ljava/lang/String;)Ljava/lang/String;
    //   29: aload_3
    //   30: ifnonnull +8 -> 38
    //   33: aconst_null
    //   34: goto +12 -> 46
    //   37: athrow
    //   38: aload_0
    //   39: getfield 23	z/P:new	Lz/Gb;
    //   42: aload_3
    //   43: invokevirtual 86	z/Gb:true	(Ljava/lang/String;)Ljava/lang/String;
    //   46: invokespecial 101	z/cOn:this	(Ljava/lang/String;Ljava/lang/String;Ljava/lang/String;)V
    //   49: return
    // Line number table:
    //   Java source line #116	-> byte code offset #0
    //   Java source line #117	-> byte code offset #26
    //   Java source line #118	-> byte code offset #43
    //   Java source line #116	-> byte code offset #46
    //   Java source line #119	-> byte code offset #49
    // Local variable table:
    //   start	length	slot	name	signature
    //   0	50	0	a	P
    //   0	50	1	a	String
    //   0	50	2	a	String
    //   0	50	3	a	String
  }
  
  public auX jdMethod_this(auX a)
  {
    return new lPT4(a, jdField_new);
  }
  
  public cON jdMethod_this(cON a) {
    return new lPT8(a, jdField_new);
  }
  
  public aux jdMethod_this(aux a) {
    return new aA(a, jdField_new);
  }
}
