package z;






















@Deprecated
public class tb
  extends jb
{
  public final Gb jdField_void;
  





















  public tb(int a, String a, cON a, Gb a)
  {
    a.<init>(327680, a, a, a, a);
  }
  
  public tb(int a, int a, String a, cON a, Gb a)
  {
    a.<init>(a, a, a, a);
    jdField_void_of_type_ZGb = a;
  }
  
  /* Error */
  public aux jdMethod_this()
  {
    // Byte code:
    //   0: aload_0
    //   1: invokespecial 28	z/jb:this	()Lz/aux;
    //   4: dup
    //   5: astore_1
    //   6: ifnonnull +6 -> 12
    //   9: aload_1
    //   10: areturn
    //   11: athrow
    //   12: new 30	z/ia
    //   15: dup
    //   16: aload_1
    //   17: aload_0
    //   18: getfield 24	z/tb:jdField_void_of_type_ZGb	Lz/Gb;
    //   21: invokespecial 33	z/ia:<init>	(Lz/aux;Lz/Gb;)V
    //   24: areturn
    // Line number table:
    //   Java source line #64	-> byte code offset #0
    //   Java source line #65	-> byte code offset #6
    // Local variable table:
    //   start	length	slot	name	signature
    //   0	25	0	a	tb
  }
  
  /* Error */
  public aux jdMethod_this(String a, boolean a)
  {
    // Byte code:
    //   0: aload_0
    //   1: dup
    //   2: getfield 24	z/tb:jdField_void_of_type_ZGb	Lz/Gb;
    //   5: aload_1
    //   6: invokevirtual 44	z/Gb:for	(Ljava/lang/String;)Ljava/lang/String;
    //   9: iload_2
    //   10: invokespecial 46	z/jb:this	(Ljava/lang/String;Z)Lz/aux;
    //   13: dup
    //   14: astore_1
    //   15: ifnonnull +6 -> 21
    //   18: aload_1
    //   19: areturn
    //   20: athrow
    //   21: new 30	z/ia
    //   24: dup
    //   25: aload_1
    //   26: aload_0
    //   27: getfield 24	z/tb:jdField_void_of_type_ZGb	Lz/Gb;
    //   30: invokespecial 33	z/ia:<init>	(Lz/aux;Lz/Gb;)V
    //   33: areturn
    // Line number table:
    //   Java source line #70	-> byte code offset #0
    //   Java source line #72	-> byte code offset #15
    // Local variable table:
    //   start	length	slot	name	signature
    //   0	34	0	a	tb
    //   0	34	1	a	String
    //   0	34	2	a	int
  }
  
  /* Error */
  public aux jdMethod_catch(int a, Qa a, String a, boolean a)
  {
    // Byte code:
    //   0: iload_1
    //   1: aload_2
    //   2: aload_0
    //   3: dup_x2
    //   4: getfield 24	z/tb:jdField_void_of_type_ZGb	Lz/Gb;
    //   7: aload_3
    //   8: invokevirtual 44	z/Gb:for	(Ljava/lang/String;)Ljava/lang/String;
    //   11: iload 4
    //   13: invokespecial 50	z/jb:catch	(ILz/Qa;Ljava/lang/String;Z)Lz/aux;
    //   16: dup
    //   17: astore_1
    //   18: ifnonnull +6 -> 24
    //   21: aload_1
    //   22: areturn
    //   23: athrow
    //   24: new 30	z/ia
    //   27: dup
    //   28: aload_1
    //   29: aload_0
    //   30: getfield 24	z/tb:jdField_void_of_type_ZGb	Lz/Gb;
    //   33: invokespecial 33	z/ia:<init>	(Lz/aux;Lz/Gb;)V
    //   36: areturn
    // Line number table:
    //   Java source line #78	-> byte code offset #0
    //   Java source line #79	-> byte code offset #8
    //   Java source line #78	-> byte code offset #13
    //   Java source line #80	-> byte code offset #18
    // Local variable table:
    //   start	length	slot	name	signature
    //   0	37	0	a	tb
    //   0	37	1	a	int
    //   0	37	2	a	Qa
    //   0	37	3	a	String
    //   0	37	4	a	int
  }
  
  /* Error */
  public aux jdMethod_this(int a, String a, boolean a)
  {
    // Byte code:
    //   0: iload_1
    //   1: aload_0
    //   2: dup_x1
    //   3: getfield 24	z/tb:jdField_void_of_type_ZGb	Lz/Gb;
    //   6: aload_2
    //   7: invokevirtual 44	z/Gb:for	(Ljava/lang/String;)Ljava/lang/String;
    //   10: iload_3
    //   11: invokespecial 58	z/jb:this	(ILjava/lang/String;Z)Lz/aux;
    //   14: dup
    //   15: astore_1
    //   16: ifnonnull +6 -> 22
    //   19: aload_1
    //   20: areturn
    //   21: athrow
    //   22: new 30	z/ia
    //   25: dup
    //   26: aload_1
    //   27: aload_0
    //   28: getfield 24	z/tb:jdField_void_of_type_ZGb	Lz/Gb;
    //   31: invokespecial 33	z/ia:<init>	(Lz/aux;Lz/Gb;)V
    //   34: areturn
    // Line number table:
    //   Java source line #86	-> byte code offset #0
    //   Java source line #87	-> byte code offset #7
    //   Java source line #86	-> byte code offset #11
    //   Java source line #88	-> byte code offset #16
    // Local variable table:
    //   start	length	slot	name	signature
    //   0	35	0	a	tb
    //   0	35	1	a	int
    //   0	35	2	a	String
    //   0	35	3	a	int
  }
  
  public void jdMethod_this(int a, int a, Object[] a, int a, Object[] a)
  {
    int tmp12_10 = a;a.jdMethod_this(a, a, a.jdMethod_this(a, a), tmp12_10, a
      .jdMethod_this(tmp12_10, a));
  }
  
  private Object[] jdMethod_this(int a, Object[] a) {
    1;
    int i; if ((a[i] instanceof String)) {
      int tmp24_23 = 1;tmp24_23;int ? = tmp24_23;
      if (i > 0) {
        1; int tmp39_38 = 0; int tmp41_40 = 1;tmp41_40;System.arraycopy(tmp39_38, ?, tmp39_38, tmp41_40, i);
      }
      label84:
      do { Object localObject = a[i];
        if (i++ != 0) {
          tmpTernaryOp = jdField_void_of_type_ZGb.jdMethod_catch((String)localObject); break label84; throw (localObject instanceof String); } ?[i] = localObject;
      } while (i < a);
      return ?;throw tmp34_33;
    }
    i++;
    












    return a;
  }
  

  public void jdMethod_true(int a, String a, String a, String a)
  {
    a.jdMethod_true(a, jdField_void_of_type_ZGb.jdMethod_catch(a), jdField_void_of_type_ZGb
      .jdMethod_this(a, a, a), jdField_void_of_type_ZGb
      .jdMethod_for(a));
  }
  
  /* Error */
  @Deprecated
  public void jdMethod_this(int a, String a, String a, String a)
  {
    // Byte code:
    //   0: aload_0
    //   1: getfield 86	z/tb:pB	I
    //   4: ldc 11
    //   6: if_icmplt +14 -> 20
    //   9: aload_0
    //   10: iload_1
    //   11: aload_2
    //   12: aload_3
    //   13: aload 4
    //   15: invokespecial 88	z/jb:this	(ILjava/lang/String;Ljava/lang/String;Ljava/lang/String;)V
    //   18: return
    //   19: athrow
    //   20: aload_0
    //   21: iload_1
    //   22: aload_2
    //   23: aload_3
    //   24: aload 4
    //   26: iload_1
    //   27: sipush 185
    //   30: iconst_1
    //   31: dup
    //   32: pop2
    //   33: if_icmpne +11 -> 44
    //   36: iconst_1
    //   37: dup
    //   38: dup
    //   39: pop2
    //   40: goto +8 -> 48
    //   43: athrow
    //   44: iconst_0
    //   45: iconst_1
    //   46: dup
    //   47: pop2
    //   48: invokespecial 91	z/tb:true	(ILjava/lang/String;Ljava/lang/String;Ljava/lang/String;Z)V
    //   51: return
    // Line number table:
    //   Java source line #128	-> byte code offset #0
    //   Java source line #129	-> byte code offset #9
    //   Java source line #130	-> byte code offset #18
    //   Java source line #132	-> byte code offset #20
    //   Java source line #134	-> byte code offset #51
    // Local variable table:
    //   start	length	slot	name	signature
    //   0	52	0	a	tb
    //   0	52	1	a	int
    //   0	52	2	a	String
    //   0	52	3	a	String
    //   0	52	4	a	String
  }
  
  /* Error */
  public void jdMethod_this(int a, String a, String a, String a, boolean a)
  {
    // Byte code:
    //   0: aload_0
    //   1: getfield 86	z/tb:pB	I
    //   4: ldc 11
    //   6: if_icmpge +16 -> 22
    //   9: aload_0
    //   10: iload_1
    //   11: aload_2
    //   12: aload_3
    //   13: aload 4
    //   15: iload 5
    //   17: invokespecial 93	z/jb:this	(ILjava/lang/String;Ljava/lang/String;Ljava/lang/String;Z)V
    //   20: return
    //   21: athrow
    //   22: aload_0
    //   23: iload_1
    //   24: aload_2
    //   25: aload_3
    //   26: aload 4
    //   28: iload 5
    //   30: invokespecial 91	z/tb:true	(ILjava/lang/String;Ljava/lang/String;Ljava/lang/String;Z)V
    //   33: return
    // Line number table:
    //   Java source line #139	-> byte code offset #0
    //   Java source line #140	-> byte code offset #9
    //   Java source line #141	-> byte code offset #20
    //   Java source line #143	-> byte code offset #22
    //   Java source line #144	-> byte code offset #33
    // Local variable table:
    //   start	length	slot	name	signature
    //   0	34	0	a	tb
    //   0	34	1	a	int
    //   0	34	2	a	String
    //   0	34	3	a	String
    //   0	34	4	a	String
    //   0	34	5	a	int
  }
  
  private void jdMethod_true(int a, String a, String a, String a, boolean a)
  {
    if (jdField_void_of_type_ZCON != null) {
      jdField_void_of_type_ZCON.jdMethod_this(a, jdField_void_of_type_ZGb.jdMethod_catch(a), jdField_void_of_type_ZGb
        .jdMethod_true(a, a, a), jdField_void_of_type_ZGb
        .jdMethod_true(a), a);
    }
  }
  

  public void jdMethod_this(String a, String a, RA a, Object... a)
  {
    int tmp2_1 = 1;
    
















































































    int i;
    
















































































    for (tmp2_1; (i = tmp2_1) < a.length;) {
      Object[] tmp21_19 = a;i[jdField_void_of_type_ZGb.jdMethod_this(tmp21_19[i])] = (i++);tmpTernaryOp = i; continue;throw tmp21_19;
    }
    a.jdMethod_this(jdField_void_of_type_ZGb
      .jdMethod_this(a, a), jdField_void_of_type_ZGb
      .jdMethod_true(a), (RA)jdField_void_of_type_ZGb.jdMethod_this(a), a);
  }
  

  public void jdMethod_this(int a, String a)
  {
    a.jdMethod_this(a, jdField_void_of_type_ZGb.jdMethod_catch(a));
  }
  
  public void jdMethod_this(Object a)
  {
    a.jdMethod_this(jdField_void_of_type_ZGb.jdMethod_this(a));
  }
  
  public void jdMethod_this(String a, int a)
  {
    a.jdMethod_this(jdField_void_of_type_ZGb.jdMethod_for(a), a);
  }
  
  /* Error */
  public aux jdMethod_true(int a, Qa a, String a, boolean a)
  {
    // Byte code:
    //   0: iload_1
    //   1: aload_2
    //   2: aload_0
    //   3: dup_x2
    //   4: getfield 24	z/tb:jdField_void_of_type_ZGb	Lz/Gb;
    //   7: aload_3
    //   8: invokevirtual 44	z/Gb:for	(Ljava/lang/String;)Ljava/lang/String;
    //   11: iload 4
    //   13: invokespecial 126	z/jb:true	(ILz/Qa;Ljava/lang/String;Z)Lz/aux;
    //   16: dup
    //   17: astore_1
    //   18: ifnonnull +6 -> 24
    //   21: aload_1
    //   22: areturn
    //   23: athrow
    //   24: new 30	z/ia
    //   27: dup
    //   28: aload_1
    //   29: aload_0
    //   30: getfield 24	z/tb:jdField_void_of_type_ZGb	Lz/Gb;
    //   33: invokespecial 33	z/ia:<init>	(Lz/aux;Lz/Gb;)V
    //   36: areturn
    // Line number table:
    //   Java source line #191	-> byte code offset #0
    //   Java source line #192	-> byte code offset #8
    //   Java source line #191	-> byte code offset #13
    //   Java source line #193	-> byte code offset #18
    // Local variable table:
    //   start	length	slot	name	signature
    //   0	37	0	a	tb
    //   0	37	1	a	int
    //   0	37	2	a	Qa
    //   0	37	3	a	String
    //   0	37	4	a	int
  }
  
  /* Error */
  public void jdMethod_this(OA a, OA a, OA a, String a)
  {
    // Byte code:
    //   0: aload_0
    //   1: aload_1
    //   2: aload_2
    //   3: aload_3
    //   4: aload 4
    //   6: ifnonnull +8 -> 14
    //   9: aconst_null
    //   10: goto +13 -> 23
    //   13: athrow
    //   14: aload_0
    //   15: getfield 24	z/tb:jdField_void_of_type_ZGb	Lz/Gb;
    //   18: aload 4
    //   20: invokevirtual 75	z/Gb:catch	(Ljava/lang/String;)Ljava/lang/String;
    //   23: invokespecial 129	z/jb:this	(Lz/OA;Lz/OA;Lz/OA;Ljava/lang/String;)V
    //   26: return
    // Line number table:
    //   Java source line #199	-> byte code offset #0
    //   Java source line #200	-> byte code offset #20
    //   Java source line #199	-> byte code offset #23
    //   Java source line #201	-> byte code offset #26
    // Local variable table:
    //   start	length	slot	name	signature
    //   0	27	0	a	tb
    //   0	27	1	a	OA
    //   0	27	2	a	OA
    //   0	27	3	a	OA
    //   0	27	4	a	String
  }
  
  /* Error */
  public aux jdMethod_this(int a, Qa a, String a, boolean a)
  {
    // Byte code:
    //   0: iload_1
    //   1: aload_2
    //   2: aload_0
    //   3: dup_x2
    //   4: getfield 24	z/tb:jdField_void_of_type_ZGb	Lz/Gb;
    //   7: aload_3
    //   8: invokevirtual 44	z/Gb:for	(Ljava/lang/String;)Ljava/lang/String;
    //   11: iload 4
    //   13: invokespecial 134	z/jb:this	(ILz/Qa;Ljava/lang/String;Z)Lz/aux;
    //   16: dup
    //   17: astore_1
    //   18: ifnonnull +6 -> 24
    //   21: aload_1
    //   22: areturn
    //   23: athrow
    //   24: new 30	z/ia
    //   27: dup
    //   28: aload_1
    //   29: aload_0
    //   30: getfield 24	z/tb:jdField_void_of_type_ZGb	Lz/Gb;
    //   33: invokespecial 33	z/ia:<init>	(Lz/aux;Lz/Gb;)V
    //   36: areturn
    // Line number table:
    //   Java source line #206	-> byte code offset #0
    //   Java source line #207	-> byte code offset #8
    //   Java source line #206	-> byte code offset #13
    //   Java source line #208	-> byte code offset #18
    // Local variable table:
    //   start	length	slot	name	signature
    //   0	37	0	a	tb
    //   0	37	1	a	int
    //   0	37	2	a	Qa
    //   0	37	3	a	String
    //   0	37	4	a	int
  }
  
  public void jdMethod_this(String a, String a, String a, OA a, OA a, int a)
  {
    int tmp16_15 = 1; int tmp17_16 = tmp16_15;tmp17_16;a.jdMethod_this(jdField_void_of_type_ZGb.jdMethod_for(a), jdField_void_of_type_ZGb, a
      .jdMethod_this(tmp16_15, tmp17_16), a, a, a);
  }
  
  /* Error */
  public aux jdMethod_this(int a, Qa a, OA[] a, OA[] a, int[] a, String a, boolean a)
  {
    // Byte code:
    //   0: aload_0
    //   1: iload_1
    //   2: aload_2
    //   3: aload_3
    //   4: aload 4
    //   6: aload 5
    //   8: aload_0
    //   9: getfield 24	z/tb:jdField_void_of_type_ZGb	Lz/Gb;
    //   12: aload 6
    //   14: invokevirtual 44	z/Gb:for	(Ljava/lang/String;)Ljava/lang/String;
    //   17: iload 7
    //   19: invokespecial 143	z/jb:this	(ILz/Qa;[Lz/OA;[Lz/OA;[ILjava/lang/String;Z)Lz/aux;
    //   22: dup
    //   23: astore_1
    //   24: ifnonnull +6 -> 30
    //   27: aload_1
    //   28: areturn
    //   29: athrow
    //   30: new 30	z/ia
    //   33: dup
    //   34: aload_1
    //   35: aload_0
    //   36: getfield 24	z/tb:jdField_void_of_type_ZGb	Lz/Gb;
    //   39: invokespecial 33	z/ia:<init>	(Lz/aux;Lz/Gb;)V
    //   42: areturn
    // Line number table:
    //   Java source line #222	-> byte code offset #0
    //   Java source line #223	-> byte code offset #14
    //   Java source line #222	-> byte code offset #19
    //   Java source line #224	-> byte code offset #24
    // Local variable table:
    //   start	length	slot	name	signature
    //   0	43	0	a	tb
    //   0	43	1	a	int
    //   0	43	2	a	Qa
    //   0	43	3	a	OA[]
    //   0	43	4	a	OA[]
    //   0	43	5	a	int[]
    //   0	43	6	a	String
    //   0	43	7	a	int
  }
}
