package z;

import java.util.ArrayList;
import java.util.HashMap;
import java.util.List;
import java.util.Map;






















































public abstract class v
  extends Vb
  implements CoN
{
  private static final Object Fb = new Object();
  
  private static final Object EB = new Object();
  


  public int lA;
  


  public String jdField_if;
  


  private boolean jdField_null;
  


  private boolean jdField_byte;
  


  private List<Object> jdField_new;
  


  private Map<OA, List<Object>> jdField_void;
  



  public v(int a, cON a, int a, String a, String a)
  {
    a.<init>(a, a, a, a, a);
    lA = a;
    jdField_if = a;
    jdField_null = Oa.jdMethod_this(",=~=dj").equals(a);
  }
  
  public void jdMethod_true()
  {
    jdField_void_of_type_ZCON.jdMethod_true();
    if (jdField_null) {
      a;a.<init>();jdField_new = a;
      a;a.<init>();jdField_void_of_type_JavaUtilMap = a;return;throw a;
    }
    int tmp47_46 = 1; int tmp48_47 = tmp47_46;tmp48_47;4746jdField_byte = tmp48_47;a
      .jdMethod_try();
  }
  

  public void jdMethod_this(OA a)
  {
    jdField_void_of_type_ZCON.jdMethod_this(a);
    if ((jdField_null) && (jdField_void_of_type_JavaUtilMap != null)) {
      List localList;
      if ((localList = (List)jdField_void_of_type_JavaUtilMap.get(a)) != null) {
        jdField_new = localList;
        jdField_void_of_type_JavaUtilMap.remove(a);
      }
    }
  }
  
  /* Error */
  public void jdMethod_this(int a)
  {
    // Byte code:
    //   0: aload_0
    //   1: getfield 47	z/v:null	Z
    //   4: ifeq +1309 -> 1313
    //   7: iload_1
    //   8: tableswitch	default:+1302->1310, 0:+840->848, 1:+843->851, 2:+843->851, 3:+843->851, 4:+843->851, 5:+843->851, 6:+843->851, 7:+843->851, 8:+843->851, 9:+857->865, 10:+857->865, 11:+843->851, 12:+843->851, 13:+843->851, 14:+857->865, 15:+857->865, 16:+1302->1310, 17:+1302->1310, 18:+1302->1310, 19:+1302->1310, 20:+1302->1310, 21:+1302->1310, 22:+1302->1310, 23:+1302->1310, 24:+1302->1310, 25:+1302->1310, 26:+1302->1310, 27:+1302->1310, 28:+1302->1310, 29:+1302->1310, 30:+1302->1310, 31:+1302->1310, 32:+1302->1310, 33:+1302->1310, 34:+1302->1310, 35:+1302->1310, 36:+1302->1310, 37:+1302->1310, 38:+1302->1310, 39:+1302->1310, 40:+1302->1310, 41:+1302->1310, 42:+1302->1310, 43:+1302->1310, 44:+1302->1310, 45:+1302->1310, 46:+877->885, 47:+840->848, 48:+877->885, 49:+840->848, 50:+877->885, 51:+877->885, 52:+877->885, 53:+877->885, 54:+1302->1310, 55:+1302->1310, 56:+1302->1310, 57:+1302->1310, 58:+1302->1310, 59:+1302->1310, 60:+1302->1310, 61:+1302->1310, 62:+1302->1310, 63:+1302->1310, 64:+1302->1310, 65:+1302->1310, 66:+1302->1310, 67:+1302->1310, 68:+1302->1310, 69:+1302->1310, 70:+1302->1310, 71:+1302->1310, 72:+1302->1310, 73:+1302->1310, 74:+1302->1310, 75:+1302->1310, 76:+1302->1310, 77:+1302->1310, 78:+1302->1310, 79:+897->905, 80:+914->922, 81:+897->905, 82:+914->922, 83:+897->905, 84:+897->905, 85:+897->905, 86:+897->905, 87:+877->885, 88:+885->893, 89:+935->943, 90:+946->954, 91:+989->997, 92:+1032->1040, 93:+1105->1113, 94:+1178->1186, 95:+1251->1259, 96:+877->885, 97:+885->893, 98:+877->885, 99:+885->893, 100:+877->885, 101:+885->893, 102:+877->885, 103:+885->893, 104:+877->885, 105:+885->893, 106:+877->885, 107:+885->893, 108:+877->885, 109:+885->893, 110:+877->885, 111:+885->893, 112:+877->885, 113:+885->893, 114:+877->885, 115:+885->893, 116:+840->848, 117:+840->848, 118:+840->848, 119:+840->848, 120:+877->885, 121:+877->885, 122:+877->885, 123:+877->885, 124:+877->885, 125:+877->885, 126:+877->885, 127:+885->893, 128:+877->885, 129:+885->893, 130:+877->885, 131:+885->893, 132:+1302->1310, 133:+843->851, 134:+840->848, 135:+843->851, 136:+877->885, 137:+877->885, 138:+840->848, 139:+840->848, 140:+843->851, 141:+843->851, 142:+877->885, 143:+840->848, 144:+877->885, 145:+840->848, 146:+840->848, 147:+840->848, 148:+897->905, 149:+877->885, 150:+877->885, 151:+897->905, 152:+897->905, 153:+1302->1310, 154:+1302->1310, 155:+1302->1310, 156:+1302->1310, 157:+1302->1310, 158:+1302->1310, 159:+1302->1310, 160:+1302->1310, 161:+1302->1310, 162:+1302->1310, 163:+1302->1310, 164:+1302->1310, 165:+1302->1310, 166:+1302->1310, 167:+1302->1310, 168:+1302->1310, 169:+1302->1310, 170:+1302->1310, 171:+1302->1310, 172:+809->817, 173:+823->831, 174:+809->817, 175:+823->831, 176:+809->817, 177:+800->808, 178:+1302->1310, 179:+1302->1310, 180:+1302->1310, 181:+1302->1310, 182:+1302->1310, 183:+1302->1310, 184:+1302->1310, 185:+1302->1310, 186:+1302->1310, 187:+1302->1310, 188:+1302->1310, 189:+1302->1310, 190:+840->848, 191:+809->817, 192:+1302->1310, 193:+1302->1310, 194:+877->885, 195:+877->885
    //   808: aload_0
    //   809: iload_1
    //   810: invokevirtual 95	z/v:false	(I)V
    //   813: goto +604 -> 1417
    //   816: athrow
    //   817: aload_0
    //   818: invokespecial 98	z/v:true	()Ljava/lang/Object;
    //   821: aload_0
    //   822: iload_1
    //   823: invokevirtual 95	z/v:false	(I)V
    //   826: pop
    //   827: goto +590 -> 1417
    //   830: athrow
    //   831: aload_0
    //   832: invokespecial 98	z/v:true	()Ljava/lang/Object;
    //   835: aload_0
    //   836: invokespecial 98	z/v:true	()Ljava/lang/Object;
    //   839: aload_0
    //   840: iload_1
    //   841: invokevirtual 95	z/v:false	(I)V
    //   844: pop2
    //   845: goto +572 -> 1417
    //   848: goto +569 -> 1417
    //   851: aload_0
    //   852: iconst_0
    //   853: ifne +29 -> 882
    //   856: getstatic 100	z/v:EB	Ljava/lang/Object;
    //   859: invokespecial 103	z/v:true	(Ljava/lang/Object;)V
    //   862: goto +555 -> 1417
    //   865: aload_0
    //   866: dup
    //   867: getstatic 100	z/v:EB	Ljava/lang/Object;
    //   870: invokespecial 103	z/v:true	(Ljava/lang/Object;)V
    //   873: getstatic 100	z/v:EB	Ljava/lang/Object;
    //   876: invokespecial 103	z/v:true	(Ljava/lang/Object;)V
    //   879: goto +538 -> 1417
    //   882: goto -30 -> 852
    //   885: aload_0
    //   886: invokespecial 98	z/v:true	()Ljava/lang/Object;
    //   889: pop
    //   890: goto +527 -> 1417
    //   893: aload_0
    //   894: invokespecial 98	z/v:true	()Ljava/lang/Object;
    //   897: aload_0
    //   898: invokespecial 98	z/v:true	()Ljava/lang/Object;
    //   901: pop2
    //   902: goto +515 -> 1417
    //   905: aload_0
    //   906: invokespecial 98	z/v:true	()Ljava/lang/Object;
    //   909: aload_0
    //   910: invokespecial 98	z/v:true	()Ljava/lang/Object;
    //   913: aload_0
    //   914: invokespecial 98	z/v:true	()Ljava/lang/Object;
    //   917: pop
    //   918: pop2
    //   919: goto +498 -> 1417
    //   922: aload_0
    //   923: invokespecial 98	z/v:true	()Ljava/lang/Object;
    //   926: aload_0
    //   927: invokespecial 98	z/v:true	()Ljava/lang/Object;
    //   930: aload_0
    //   931: invokespecial 98	z/v:true	()Ljava/lang/Object;
    //   934: aload_0
    //   935: invokespecial 98	z/v:true	()Ljava/lang/Object;
    //   938: pop2
    //   939: pop2
    //   940: goto +477 -> 1417
    //   943: aload_0
    //   944: dup
    //   945: invokespecial 105	z/v:this	()Ljava/lang/Object;
    //   948: invokespecial 103	z/v:true	(Ljava/lang/Object;)V
    //   951: goto +466 -> 1417
    //   954: aload_0
    //   955: dup
    //   956: getfield 64	z/v:new	Ljava/util/List;
    //   959: invokeinterface 109 1 0
    //   964: istore_2
    //   965: getfield 64	z/v:new	Ljava/util/List;
    //   968: iload_2
    //   969: iconst_2
    //   970: iconst_1
    //   971: dup
    //   972: pop2
    //   973: isub
    //   974: aload_0
    //   975: getfield 64	z/v:new	Ljava/util/List;
    //   978: iload_2
    //   979: iconst_1
    //   980: dup
    //   981: dup
    //   982: pop2
    //   983: isub
    //   984: invokeinterface 112 2 0
    //   989: invokeinterface 116 3 0
    //   994: goto +423 -> 1417
    //   997: aload_0
    //   998: dup
    //   999: getfield 64	z/v:new	Ljava/util/List;
    //   1002: invokeinterface 109 1 0
    //   1007: istore_2
    //   1008: getfield 64	z/v:new	Ljava/util/List;
    //   1011: iload_2
    //   1012: iconst_3
    //   1013: iconst_1
    //   1014: dup
    //   1015: pop2
    //   1016: isub
    //   1017: aload_0
    //   1018: getfield 64	z/v:new	Ljava/util/List;
    //   1021: iload_2
    //   1022: iconst_1
    //   1023: dup
    //   1024: dup
    //   1025: pop2
    //   1026: isub
    //   1027: invokeinterface 112 2 0
    //   1032: invokeinterface 116 3 0
    //   1037: goto +380 -> 1417
    //   1040: aload_0
    //   1041: dup
    //   1042: dup_x1
    //   1043: getfield 64	z/v:new	Ljava/util/List;
    //   1046: invokeinterface 109 1 0
    //   1051: istore_2
    //   1052: getfield 64	z/v:new	Ljava/util/List;
    //   1055: iload_2
    //   1056: iconst_2
    //   1057: iconst_1
    //   1058: dup
    //   1059: pop2
    //   1060: isub
    //   1061: aload_0
    //   1062: getfield 64	z/v:new	Ljava/util/List;
    //   1065: iload_2
    //   1066: iconst_1
    //   1067: dup
    //   1068: dup
    //   1069: pop2
    //   1070: isub
    //   1071: invokeinterface 112 2 0
    //   1076: invokeinterface 116 3 0
    //   1081: getfield 64	z/v:new	Ljava/util/List;
    //   1084: iload_2
    //   1085: iconst_2
    //   1086: iconst_1
    //   1087: dup
    //   1088: pop2
    //   1089: isub
    //   1090: aload_0
    //   1091: getfield 64	z/v:new	Ljava/util/List;
    //   1094: iload_2
    //   1095: iconst_1
    //   1096: dup
    //   1097: dup
    //   1098: pop2
    //   1099: isub
    //   1100: invokeinterface 112 2 0
    //   1105: invokeinterface 116 3 0
    //   1110: goto +307 -> 1417
    //   1113: aload_0
    //   1114: dup
    //   1115: dup_x1
    //   1116: getfield 64	z/v:new	Ljava/util/List;
    //   1119: invokeinterface 109 1 0
    //   1124: istore_2
    //   1125: getfield 64	z/v:new	Ljava/util/List;
    //   1128: iload_2
    //   1129: iconst_3
    //   1130: iconst_1
    //   1131: dup
    //   1132: pop2
    //   1133: isub
    //   1134: aload_0
    //   1135: getfield 64	z/v:new	Ljava/util/List;
    //   1138: iload_2
    //   1139: iconst_1
    //   1140: dup
    //   1141: dup
    //   1142: pop2
    //   1143: isub
    //   1144: invokeinterface 112 2 0
    //   1149: invokeinterface 116 3 0
    //   1154: getfield 64	z/v:new	Ljava/util/List;
    //   1157: iload_2
    //   1158: iconst_3
    //   1159: iconst_1
    //   1160: dup
    //   1161: pop2
    //   1162: isub
    //   1163: aload_0
    //   1164: getfield 64	z/v:new	Ljava/util/List;
    //   1167: iload_2
    //   1168: iconst_1
    //   1169: dup
    //   1170: dup
    //   1171: pop2
    //   1172: isub
    //   1173: invokeinterface 112 2 0
    //   1178: invokeinterface 116 3 0
    //   1183: goto +234 -> 1417
    //   1186: aload_0
    //   1187: dup
    //   1188: dup_x1
    //   1189: getfield 64	z/v:new	Ljava/util/List;
    //   1192: invokeinterface 109 1 0
    //   1197: istore_2
    //   1198: getfield 64	z/v:new	Ljava/util/List;
    //   1201: iload_2
    //   1202: iconst_4
    //   1203: iconst_1
    //   1204: dup
    //   1205: pop2
    //   1206: isub
    //   1207: aload_0
    //   1208: getfield 64	z/v:new	Ljava/util/List;
    //   1211: iload_2
    //   1212: iconst_1
    //   1213: dup
    //   1214: dup
    //   1215: pop2
    //   1216: isub
    //   1217: invokeinterface 112 2 0
    //   1222: invokeinterface 116 3 0
    //   1227: getfield 64	z/v:new	Ljava/util/List;
    //   1230: iload_2
    //   1231: iconst_4
    //   1232: iconst_1
    //   1233: dup
    //   1234: pop2
    //   1235: isub
    //   1236: aload_0
    //   1237: getfield 64	z/v:new	Ljava/util/List;
    //   1240: iload_2
    //   1241: iconst_1
    //   1242: dup
    //   1243: dup
    //   1244: pop2
    //   1245: isub
    //   1246: invokeinterface 112 2 0
    //   1251: invokeinterface 116 3 0
    //   1256: goto +161 -> 1417
    //   1259: aload_0
    //   1260: dup
    //   1261: dup_x1
    //   1262: getfield 64	z/v:new	Ljava/util/List;
    //   1265: invokeinterface 109 1 0
    //   1270: istore_2
    //   1271: getfield 64	z/v:new	Ljava/util/List;
    //   1274: iload_2
    //   1275: iconst_2
    //   1276: iconst_1
    //   1277: dup
    //   1278: pop2
    //   1279: isub
    //   1280: aload_0
    //   1281: getfield 64	z/v:new	Ljava/util/List;
    //   1284: iload_2
    //   1285: iconst_1
    //   1286: dup
    //   1287: dup
    //   1288: pop2
    //   1289: isub
    //   1290: invokeinterface 112 2 0
    //   1295: invokeinterface 116 3 0
    //   1300: getfield 64	z/v:new	Ljava/util/List;
    //   1303: iload_2
    //   1304: invokeinterface 118 2 0
    //   1309: pop
    //   1310: goto +107 -> 1417
    //   1313: iload_1
    //   1314: tableswitch	default:+103->1417, 172:+94->1408, 173:+94->1408, 174:+94->1408, 175:+94->1408, 176:+94->1408, 177:+94->1408, 178:+103->1417, 179:+103->1417, 180:+103->1417, 181:+103->1417, 182:+103->1417, 183:+103->1417, 184:+103->1417, 185:+103->1417, 186:+103->1417, 187:+103->1417, 188:+103->1417, 189:+103->1417, 190:+103->1417, 191:+94->1408
    //   1408: aload_0
    //   1409: iconst_0
    //   1410: ifne -1 -> 1409
    //   1413: iload_1
    //   1414: invokevirtual 95	z/v:false	(I)V
    //   1417: aload_0
    //   1418: getfield 54	z/v:jdField_void_of_type_ZCON	Lz/cON;
    //   1421: iload_1
    //   1422: invokevirtual 120	z/cON:this	(I)V
    //   1425: return
    // Line number table:
    //   Java source line #130	-> byte code offset #0
    //   Java source line #132	-> byte code offset #7
    //   Java source line #134	-> byte code offset #808
    //   Java source line #135	-> byte code offset #813
    //   Java source line #140	-> byte code offset #817
    //   Java source line #141	-> byte code offset #821
    //   Java source line #142	-> byte code offset #827
    //   Java source line #145	-> byte code offset #831
    //   Java source line #146	-> byte code offset #835
    //   Java source line #147	-> byte code offset #839
    //   Java source line #148	-> byte code offset #845
    //   Java source line #164	-> byte code offset #848
    //   Java source line #180	-> byte code offset #851
    //   Java source line #181	-> byte code offset #862
    //   Java source line #186	-> byte code offset #865
    //   Java source line #187	-> byte code offset #873
    //   Java source line #188	-> byte code offset #879
    //   Java source line #223	-> byte code offset #885
    //   Java source line #224	-> byte code offset #890
    //   Java source line #239	-> byte code offset #893
    //   Java source line #240	-> byte code offset #897
    //   Java source line #241	-> byte code offset #902
    //   Java source line #251	-> byte code offset #905
    //   Java source line #252	-> byte code offset #909
    //   Java source line #253	-> byte code offset #913
    //   Java source line #254	-> byte code offset #919
    //   Java source line #257	-> byte code offset #922
    //   Java source line #258	-> byte code offset #926
    //   Java source line #259	-> byte code offset #930
    //   Java source line #260	-> byte code offset #934
    //   Java source line #261	-> byte code offset #940
    //   Java source line #263	-> byte code offset #943
    //   Java source line #264	-> byte code offset #951
    //   Java source line #266	-> byte code offset #954
    //   Java source line #267	-> byte code offset #965
    //   Java source line #268	-> byte code offset #994
    //   Java source line #270	-> byte code offset #997
    //   Java source line #271	-> byte code offset #1008
    //   Java source line #272	-> byte code offset #1037
    //   Java source line #274	-> byte code offset #1040
    //   Java source line #275	-> byte code offset #1052
    //   Java source line #276	-> byte code offset #1081
    //   Java source line #277	-> byte code offset #1110
    //   Java source line #279	-> byte code offset #1113
    //   Java source line #280	-> byte code offset #1125
    //   Java source line #281	-> byte code offset #1154
    //   Java source line #282	-> byte code offset #1183
    //   Java source line #284	-> byte code offset #1186
    //   Java source line #285	-> byte code offset #1198
    //   Java source line #286	-> byte code offset #1227
    //   Java source line #287	-> byte code offset #1256
    //   Java source line #289	-> byte code offset #1259
    //   Java source line #290	-> byte code offset #1271
    //   Java source line #291	-> byte code offset #1300
    //   Java source line #292	-> byte code offset #1310
    //   Java source line #295	-> byte code offset #1313
    //   Java source line #303	-> byte code offset #1408
    //   Java source line #307	-> byte code offset #1417
    //   Java source line #308	-> byte code offset #1425
    // Local variable table:
    //   start	length	slot	name	signature
    //   0	1426	0	a	v
    //   0	1426	1	a	int
  }
  
  /* Error */
  public void jdMethod_catch(int a, int a)
  {
    // Byte code:
    //   0: aload_0
    //   1: dup
    //   2: iload_1
    //   3: iload_2
    //   4: invokespecial 124	z/Vb:catch	(II)V
    //   7: getfield 47	z/v:null	Z
    //   10: ifeq +235 -> 245
    //   13: iload_1
    //   14: tableswitch	default:+231->245, 21:+166->180, 22:+179->193, 23:+166->180, 24:+179->193, 25:+195->209, 26:+231->245, 27:+231->245, 28:+231->245, 29:+231->245, 30:+231->245, 31:+231->245, 32:+231->245, 33:+231->245, 34:+231->245, 35:+231->245, 36:+231->245, 37:+231->245, 38:+231->245, 39:+231->245, 40:+231->245, 41:+231->245, 42:+231->245, 43:+231->245, 44:+231->245, 45:+231->245, 46:+231->245, 47:+231->245, 48:+231->245, 49:+231->245, 50:+231->245, 51:+231->245, 52:+231->245, 53:+231->245, 54:+216->230, 55:+222->236, 56:+216->230, 57:+222->236, 58:+216->230
    //   180: aload_0
    //   181: iconst_0
    //   182: ifne +45 -> 227
    //   185: getstatic 100	z/v:EB	Ljava/lang/Object;
    //   188: invokespecial 103	z/v:true	(Ljava/lang/Object;)V
    //   191: return
    //   192: athrow
    //   193: aload_0
    //   194: dup
    //   195: getstatic 100	z/v:EB	Ljava/lang/Object;
    //   198: invokespecial 103	z/v:true	(Ljava/lang/Object;)V
    //   201: getstatic 100	z/v:EB	Ljava/lang/Object;
    //   204: invokespecial 103	z/v:true	(Ljava/lang/Object;)V
    //   207: return
    //   208: athrow
    //   209: aload_0
    //   210: iload_2
    //   211: ifne +9 -> 220
    //   214: getstatic 126	z/v:Fb	Ljava/lang/Object;
    //   217: goto +6 -> 223
    //   220: getstatic 100	z/v:EB	Ljava/lang/Object;
    //   223: invokespecial 103	z/v:true	(Ljava/lang/Object;)V
    //   226: return
    //   227: goto -46 -> 181
    //   230: aload_0
    //   231: invokespecial 98	z/v:true	()Ljava/lang/Object;
    //   234: pop
    //   235: return
    //   236: aload_0
    //   237: invokespecial 98	z/v:true	()Ljava/lang/Object;
    //   240: aload_0
    //   241: invokespecial 98	z/v:true	()Ljava/lang/Object;
    //   244: pop2
    //   245: return
    // Line number table:
    //   Java source line #312	-> byte code offset #0
    //   Java source line #313	-> byte code offset #7
    //   Java source line #314	-> byte code offset #13
    //   Java source line #317	-> byte code offset #180
    //   Java source line #318	-> byte code offset #191
    //   Java source line #321	-> byte code offset #193
    //   Java source line #322	-> byte code offset #201
    //   Java source line #323	-> byte code offset #207
    //   Java source line #325	-> byte code offset #209
    //   Java source line #326	-> byte code offset #226
    //   Java source line #330	-> byte code offset #230
    //   Java source line #331	-> byte code offset #235
    //   Java source line #334	-> byte code offset #236
    //   Java source line #335	-> byte code offset #240
    //   Java source line #339	-> byte code offset #245
    // Local variable table:
    //   start	length	slot	name	signature
    //   0	246	0	a	v
    //   0	246	1	a	int
    //   0	246	2	a	int
  }
  
  public void jdMethod_true(int a, String a, String a, String a)
  {
    jdField_void_of_type_ZCON.jdMethod_true(a, a, a, a);
    if (jdField_null) {
      int tmp23_22 = 1;tmp23_22;a = 0.charAt(tmp23_22); int 
        tmp33_32 = 1;tmp33_32; if (74 != tmp33_32) { int tmp42_41 = 1;tmp42_41; if (68 != tmp42_41) {} } else { int tmp48_47 = 1; int tmp49_48 = tmp48_47;;; break label59; throw tmp48_47; } int tmp57_56 = 1;tmp57_56; label59: a = tmp57_56;
      switch (a) {
      case 178: 
        if (0 == 0) { a.jdMethod_true(EB);
          if (a == 0) return;
          a.jdMethod_true(EB);return;throw 0;
        }
      
      case 179: 
        a.jdMethod_true();
        if (a == 0) return;
        ;;;
        

        for (;;) {}
      case 181: 
        a.jdMethod_true();
        if (a == 0) return;
        a.jdMethod_true();return;
      }
      
      

      if (a != 0) {
        a.jdMethod_true(EB);
      }
    }
  }
  

  public void jdMethod_for(int a, int a)
  {
    jdField_void_of_type_ZCON.jdMethod_for(a, a);
    if (jdField_null) { int tmp21_20 = 1;tmp21_20; if (188 != tmp21_20) {
        a.jdMethod_true(EB);
      }
    }
  }
  
  public void jdMethod_this(Object a) {
    jdField_void_of_type_ZCON.jdMethod_this(a);
    if (jdField_null) {
      a.jdMethod_true(EB);
      if (((a instanceof Double)) || ((a instanceof Long))) {
        a.jdMethod_true(EB);
      }
    }
  }
  
  public void jdMethod_this(String a, int a)
  {
    jdField_void_of_type_ZCON.jdMethod_this(a, a);
    if (jdField_null) {
      int tmp18_17 = 1;
      














































































































































































































































































































































































































      for (tmp18_17; (a = tmp18_17) < a;) { 
          a.jdMethod_true();tmpTernaryOp = (++a); continue;throw 0;
      }
      a.jdMethod_true(EB);
    }
  }
  
  public void jdMethod_this(int a, String a)
  {
    jdField_void_of_type_ZCON.jdMethod_this(a, a);
    
    if (jdField_null) { int tmp21_20 = 1;tmp21_20; if (187 == tmp21_20) {
        a.jdMethod_true(EB);
      }
    }
  }
  
  /* Error */
  @Deprecated
  public void jdMethod_this(int a, String a, String a, String a)
  {
    // Byte code:
    //   0: aload_0
    //   1: getfield 154	z/v:pB	I
    //   4: ldc -101
    //   6: if_icmplt +14 -> 20
    //   9: aload_0
    //   10: iload_1
    //   11: aload_2
    //   12: aload_3
    //   13: aload 4
    //   15: invokespecial 157	z/Vb:this	(ILjava/lang/String;Ljava/lang/String;Ljava/lang/String;)V
    //   18: return
    //   19: athrow
    //   20: aload_0
    //   21: iload_1
    //   22: aload_2
    //   23: aload_3
    //   24: aload 4
    //   26: iload_1
    //   27: sipush 185
    //   30: iconst_1
    //   31: dup
    //   32: pop2
    //   33: if_icmpne +11 -> 44
    //   36: iconst_1
    //   37: dup
    //   38: dup
    //   39: pop2
    //   40: goto +8 -> 48
    //   43: athrow
    //   44: iconst_0
    //   45: iconst_1
    //   46: dup
    //   47: pop2
    //   48: invokespecial 160	z/v:true	(ILjava/lang/String;Ljava/lang/String;Ljava/lang/String;Z)V
    //   51: return
    // Line number table:
    //   Java source line #420	-> byte code offset #0
    //   Java source line #421	-> byte code offset #9
    //   Java source line #422	-> byte code offset #18
    //   Java source line #424	-> byte code offset #20
    //   Java source line #426	-> byte code offset #51
    // Local variable table:
    //   start	length	slot	name	signature
    //   0	52	0	a	v
    //   0	52	1	a	int
    //   0	52	2	a	String
    //   0	52	3	a	String
    //   0	52	4	a	String
  }
  
  /* Error */
  public void jdMethod_this(int a, String a, String a, String a, boolean a)
  {
    // Byte code:
    //   0: aload_0
    //   1: getfield 154	z/v:pB	I
    //   4: ldc -101
    //   6: if_icmpge +16 -> 22
    //   9: aload_0
    //   10: iload_1
    //   11: aload_2
    //   12: aload_3
    //   13: aload 4
    //   15: iload 5
    //   17: invokespecial 162	z/Vb:this	(ILjava/lang/String;Ljava/lang/String;Ljava/lang/String;Z)V
    //   20: return
    //   21: athrow
    //   22: aload_0
    //   23: iload_1
    //   24: aload_2
    //   25: aload_3
    //   26: aload 4
    //   28: iload 5
    //   30: invokespecial 160	z/v:true	(ILjava/lang/String;Ljava/lang/String;Ljava/lang/String;Z)V
    //   33: return
    // Line number table:
    //   Java source line #431	-> byte code offset #0
    //   Java source line #432	-> byte code offset #9
    //   Java source line #433	-> byte code offset #20
    //   Java source line #435	-> byte code offset #22
    //   Java source line #436	-> byte code offset #33
    // Local variable table:
    //   start	length	slot	name	signature
    //   0	34	0	a	v
    //   0	34	1	a	int
    //   0	34	2	a	String
    //   0	34	3	a	String
    //   0	34	4	a	String
    //   0	34	5	a	int
  }
  
  private void jdMethod_true(int a, String a, String a, String a, boolean a)
  {
    jdField_void_of_type_ZCON.jdMethod_this(a, a, a, a, a);
    if (jdField_null) {
      a = iB.jdMethod_this(a); int 
        tmp29_28 = 1;
      for (tmp29_28; (a = tmp29_28) < a.length;) {
        a.jdMethod_true(); int 
          tmp51_50 = 1;tmp51_50; if (2 == tmp51_50) {
          a.jdMethod_true();
        }
        a++;tmpTernaryOp = a; continue;throw a[a]
        
          .jdMethod_this();
      }
      

      switch (a)
      {

      case 182: 
      case 185: 
        while (0 != 0) {} a.jdMethod_true();tmpTernaryOp = a;
        break label156; throw 0;
      
      case 183: 
        if (((a = a.jdMethod_true()) == Fb) && (!jdField_byte)) {
          a.jdMethod_try(); int 
            tmp143_142 = 1;tmp143_142;1jdField_byte = tmp143_142; int 
          

            tmp149_148 = 1;tmp149_148;jdField_null = tmp149_148;
        }
        break;
      }
      
      label156:
      if ((a = iB.jdMethod_this(a)) != iB.case) {
        a.jdMethod_true(EB);
        tmp180_179 = 1;tmp180_179; if (2 == tmp180_179) {
          a.jdMethod_true(EB);
        }
      }
    }
  }
  

  public void jdMethod_this(String a, String a, RA a, Object... a)
  {
    jdField_void_of_type_ZCON.jdMethod_this(a, a, a, a);
    if (jdField_null) {
      a = iB.jdMethod_this(a); int 
        tmp26_25 = 1;
      for (tmp26_25; (a = tmp26_25) < a.length;) {
        a.jdMethod_true(); int 
          tmp48_47 = 1;tmp48_47; if (2 == tmp48_47) {
          a.jdMethod_true();
        }
        a++;tmpTernaryOp = a; continue;throw a[a]
        
          .jdMethod_this();
      }
      



      if ((a = iB.jdMethod_this(a)) != iB.case) {
        a.jdMethod_true(EB); int 
          tmp91_90 = 1;tmp91_90; if (2 == tmp91_90) {
          a.jdMethod_true(EB);
        }
      }
    }
  }
  
  /* Error */
  public void jdMethod_true(int a, OA a)
  {
    // Byte code:
    //   0: aload_0
    //   1: dup
    //   2: getfield 54	z/v:jdField_void_of_type_ZCON	Lz/cON;
    //   5: iload_1
    //   6: aload_2
    //   7: invokevirtual 188	z/cON:true	(ILz/OA;)V
    //   10: getfield 47	z/v:null	Z
    //   13: ifeq +247 -> 260
    //   16: iload_1
    //   17: tableswitch	default:+238->255, 153:+203->220, 154:+203->220, 155:+203->220, 156:+203->220, 157:+203->220, 158:+203->220, 159:+217->234, 160:+217->234, 161:+217->234, 162:+217->234, 163:+217->234, 164:+217->234, 165:+217->234, 166:+217->234, 167:+238->255, 168:+231->248, 169:+238->255, 170:+238->255, 171:+238->255, 172:+238->255, 173:+238->255, 174:+238->255, 175:+238->255, 176:+238->255, 177:+238->255, 178:+238->255, 179:+238->255, 180:+238->255, 181:+238->255, 182:+238->255, 183:+238->255, 184:+238->255, 185:+238->255, 186:+238->255, 187:+238->255, 188:+238->255, 189:+238->255, 190:+238->255, 191:+238->255, 192:+238->255, 193:+238->255, 194:+238->255, 195:+238->255, 196:+238->255, 197:+238->255, 198:+203->220, 199:+203->220
    //   220: aload_0
    //   221: iconst_0
    //   222: ifne -1 -> 221
    //   225: dup
    //   226: invokespecial 98	z/v:true	()Ljava/lang/Object;
    //   229: pop
    //   230: goto +26 -> 256
    //   233: athrow
    //   234: aload_0
    //   235: dup
    //   236: invokespecial 98	z/v:true	()Ljava/lang/Object;
    //   239: aload_0
    //   240: invokespecial 98	z/v:true	()Ljava/lang/Object;
    //   243: pop2
    //   244: goto +12 -> 256
    //   247: athrow
    //   248: aload_0
    //   249: getstatic 100	z/v:EB	Ljava/lang/Object;
    //   252: invokespecial 103	z/v:true	(Ljava/lang/Object;)V
    //   255: aload_0
    //   256: aload_2
    //   257: invokespecial 191	z/v:enum	(Lz/OA;)V
    //   260: return
    // Line number table:
    //   Java source line #503	-> byte code offset #0
    //   Java source line #504	-> byte code offset #10
    //   Java source line #505	-> byte code offset #16
    //   Java source line #514	-> byte code offset #220
    //   Java source line #515	-> byte code offset #230
    //   Java source line #524	-> byte code offset #234
    //   Java source line #525	-> byte code offset #239
    //   Java source line #526	-> byte code offset #244
    //   Java source line #528	-> byte code offset #248
    //   Java source line #531	-> byte code offset #255
    //   Java source line #533	-> byte code offset #260
    // Local variable table:
    //   start	length	slot	name	signature
    //   0	261	0	a	v
    //   0	261	1	a	int
    //   0	261	2	a	OA
  }
  
  public void jdMethod_this(OA a, int[] a, OA[] a)
  {
    jdField_void_of_type_ZCON.jdMethod_this(a, a, a);
    if (jdField_null)
    {
      a.jdMethod_this(a, a);a.jdMethod_true();
    }
  }
  

  public void jdMethod_this(int a, int a, OA a, OA... a)
  {
    jdField_void_of_type_ZCON.jdMethod_this(a, a, a, a);
    if (jdField_null)
    {
      a.jdMethod_this(a, a);a.jdMethod_true();
    }
  }
  

  public void jdMethod_this(OA a, OA a, OA a, String a)
  {
    a.jdMethod_this(a, a, a, a);
    if ((jdField_null) && (!jdField_void_of_type_JavaUtilMap.containsKey(a))) {
      a = new ArrayList();
      
      jdField_void_of_type_JavaUtilMap.put(a, a);
    }
  }
  
  private void jdMethod_this(OA a, OA[] a) {
    a.jdMethod_enum(a); int 
      tmp7_6 = 1;
    for (tmp7_6; (a = tmp7_6) < a.length;) {
      a.jdMethod_enum(a[(a++)]);tmpTernaryOp = a; continue;throw 0;
    }
  }
  
  /* Error */
  private void jdMethod_enum(OA a)
  {
    // Byte code:
    //   0: aload_0
    //   1: getfield 69	z/v:jdField_void_of_type_JavaUtilMap	Ljava/util/Map;
    //   4: aload_1
    //   5: invokeinterface 210 2 0
    //   10: ifeq +5 -> 15
    //   13: return
    //   14: athrow
    //   15: aload_0
    //   16: getfield 69	z/v:jdField_void_of_type_JavaUtilMap	Ljava/util/Map;
    //   19: new 60	java/util/ArrayList
    //   22: aload_1
    //   23: dup_x1
    //   24: dup
    //   25: pop2
    //   26: dup
    //   27: aload_0
    //   28: getfield 64	z/v:new	Ljava/util/List;
    //   31: invokespecial 220	java/util/ArrayList:<init>	(Ljava/util/Collection;)V
    //   34: invokeinterface 216 3 0
    //   39: pop
    //   40: return
    // Line number table:
    //   Java source line #574	-> byte code offset #0
    //   Java source line #575	-> byte code offset #13
    //   Java source line #577	-> byte code offset #15
    //   Java source line #578	-> byte code offset #40
    // Local variable table:
    //   start	length	slot	name	signature
    //   0	41	0	a	v
    //   0	41	1	a	OA
  }
  
  private Object jdMethod_true()
  {
    int tmp15_14 = 1; int tmp16_15 = tmp15_14;tmp16_15;return jdField_new.size().remove(tmp15_14 - tmp16_15);
  }
  
  private Object jdMethod_this() {
    int tmp15_14 = 1; int tmp16_15 = tmp15_14;tmp16_15;return jdField_new.size().get(tmp15_14 - tmp16_15);
  }
  
  private void jdMethod_true(Object a) {
    jdField_new.add(a);
  }
  
  public void jdMethod_try() {}
  
  public void jdMethod_false(int a) {}
}
