package z;





















public class wA
  extends auX
{
  private final GA jdField_void;
  



















  public wA(auX a, GA a)
  {
    a.<init>(327680, a);
    jdField_void_of_type_ZGA = a;
  }
  
  /* Error */
  public aux jdMethod_this(String a, boolean a)
  {
    // Byte code:
    //   0: iload_2
    //   1: aload_0
    //   2: getfield 15	z/wA:jdField_void_of_type_ZGA	Lz/GA;
    //   5: aload_1
    //   6: invokevirtual 26	z/GA:for	(Ljava/lang/String;)Lz/Xb;
    //   9: pop
    //   10: ifeq +20 -> 30
    //   13: aload_0
    //   14: getfield 15	z/wA:jdField_void_of_type_ZGA	Lz/GA;
    //   17: ldc 28
    //   19: invokestatic 33	org/powerbot/bot/rt4/HashTable:this	(Ljava/lang/Object;)Ljava/lang/String;
    //   22: invokevirtual 26	z/GA:for	(Ljava/lang/String;)Lz/Xb;
    //   25: pop
    //   26: goto +17 -> 43
    //   29: athrow
    //   30: aload_0
    //   31: getfield 15	z/wA:jdField_void_of_type_ZGA	Lz/GA;
    //   34: ldc 35
    //   36: invokestatic 38	org/powerbot/script/rt6/BasicObject:this	(Ljava/lang/Object;)Ljava/lang/String;
    //   39: invokevirtual 26	z/GA:for	(Ljava/lang/String;)Lz/Xb;
    //   42: pop
    //   43: new 40	z/LA
    //   46: dup
    //   47: aload_0
    //   48: getfield 42	z/wA:jdField_void_of_type_ZAuX	Lz/auX;
    //   51: aload_1
    //   52: iload_2
    //   53: invokevirtual 44	z/auX:this	(Ljava/lang/String;Z)Lz/aux;
    //   56: aload_0
    //   57: getfield 15	z/wA:jdField_void_of_type_ZGA	Lz/GA;
    //   60: invokespecial 47	z/LA:<init>	(Lz/aux;Lz/GA;)V
    //   63: areturn
    // Line number table:
    //   Java source line #56	-> byte code offset #1
    //   Java source line #57	-> byte code offset #10
    //   Java source line #58	-> byte code offset #13
    //   Java source line #60	-> byte code offset #30
    //   Java source line #62	-> byte code offset #43
    // Local variable table:
    //   start	length	slot	name	signature
    //   0	64	0	a	wA
    //   0	64	1	a	String
    //   0	64	2	a	int
  }
  
  /* Error */
  public aux jdMethod_this(int a, Qa a, String a, boolean a)
  {
    // Byte code:
    //   0: iload 4
    //   2: aload_0
    //   3: getfield 15	z/wA:jdField_void_of_type_ZGA	Lz/GA;
    //   6: aload_3
    //   7: invokevirtual 26	z/GA:for	(Ljava/lang/String;)Lz/Xb;
    //   10: pop
    //   11: ifeq +20 -> 31
    //   14: aload_0
    //   15: getfield 15	z/wA:jdField_void_of_type_ZGA	Lz/GA;
    //   18: ldc 56
    //   20: invokestatic 33	org/powerbot/bot/rt4/HashTable:this	(Ljava/lang/Object;)Ljava/lang/String;
    //   23: invokevirtual 26	z/GA:for	(Ljava/lang/String;)Lz/Xb;
    //   26: pop
    //   27: goto +17 -> 44
    //   30: athrow
    //   31: aload_0
    //   32: getfield 15	z/wA:jdField_void_of_type_ZGA	Lz/GA;
    //   35: ldc 58
    //   37: invokestatic 38	org/powerbot/script/rt6/BasicObject:this	(Ljava/lang/Object;)Ljava/lang/String;
    //   40: invokevirtual 26	z/GA:for	(Ljava/lang/String;)Lz/Xb;
    //   43: pop
    //   44: new 40	z/LA
    //   47: dup
    //   48: aload_0
    //   49: getfield 42	z/wA:jdField_void_of_type_ZAuX	Lz/auX;
    //   52: aload_3
    //   53: iload 4
    //   55: invokevirtual 44	z/auX:this	(Ljava/lang/String;Z)Lz/aux;
    //   58: aload_0
    //   59: getfield 15	z/wA:jdField_void_of_type_ZGA	Lz/GA;
    //   62: invokespecial 47	z/LA:<init>	(Lz/aux;Lz/GA;)V
    //   65: areturn
    // Line number table:
    //   Java source line #69	-> byte code offset #2
    //   Java source line #70	-> byte code offset #11
    //   Java source line #71	-> byte code offset #14
    //   Java source line #73	-> byte code offset #31
    //   Java source line #75	-> byte code offset #44
    // Local variable table:
    //   start	length	slot	name	signature
    //   0	66	0	a	wA
    //   0	66	1	a	int
    //   0	66	2	a	Qa
    //   0	66	3	a	String
    //   0	66	4	a	int
  }
  
  public void jdMethod_this(lpt6 a)
  {
    jdField_void_of_type_ZAuX.jdMethod_this(a);
  }
  
  public void jdMethod_this()
  {
    jdField_void_of_type_ZAuX.jdMethod_this();
  }
}
