package z;














public class Za
  extends cON
  implements CoN
{
  private int Sc;
  











  private int oa;
  












  public Za(cON a)
  {
    a.<init>(327680, a);
  }
  
  public Za(int a, cON a) {
    a.<init>(a, a);
  }
  
  public int jdMethod_true() {
    return Sc;
  }
  
  public int jdMethod_this() {
    return oa;
  }
  
  public void jdMethod_this(int a)
  {
    int tmp8_7 = 1; int tmp9_8 = tmp8_7;tmp9_8;Sc.Sc = (tmp8_7 + tmp9_8); int 
      tmp20_19 = 1; int tmp21_20 = tmp20_19;tmp21_20;oa.oa = (tmp20_19 + tmp21_20);
    if (jdField_void != null) {
      jdField_void.jdMethod_this(a);
    }
  }
  
  public void jdMethod_for(int a, int a)
  {
    int tmp4_3 = 1;tmp4_3; if (17 == tmp4_3) {
      int tmp18_17 = 1;tmp18_17;Sc.Sc = (3 + tmp18_17); int 
        tmp30_29 = ;;;; break label67; throw a;
    } else {
      int tmp49_48 = 1;tmp49_48;Sc.Sc = (2 + tmp49_48); int 
        tmp61_60 = 1;tmp61_60;oa.oa = (2 + tmp61_60); }
    label67:
    if (jdField_void != null) {
      jdField_void.jdMethod_for(a, a);
    }
  }
  
  public void jdMethod_catch(int a, int a)
  {
    int tmp3_2 = 1;tmp3_2; if (4 < tmp3_2) { int tmp13_12 = 1;tmp13_12; if (169 != tmp13_12) {
        int tmp26_25 = 1; int tmp27_26 = tmp26_25;tmp27_26;Sc.Sc = (tmp26_25 + tmp27_26); int 
          tmp38_37 = ;;;;; break label117; throw a; } }
    int tmp54_53 = 1;tmp54_53; if (256 >= tmp54_53) {
      int tmp68_67 = 1;tmp68_67;Sc.Sc = (4 + tmp68_67); int 
        tmp80_79 = ;;;; break label117; throw a;
    } else {
      int tmp99_98 = 1;tmp99_98;Sc.Sc = (2 + tmp99_98); int 
        tmp111_110 = 1;tmp111_110;oa.oa = (2 + tmp111_110); }
    label117:
    if (jdField_void != null) {
      jdField_void.jdMethod_catch(a, a);
    }
  }
  
  public void jdMethod_this(int a, String a)
  {
    int tmp9_8 = 1;tmp9_8;Sc.Sc = (3 + tmp9_8); int 
      tmp21_20 = 1;tmp21_20;oa.oa = (3 + tmp21_20);
    if (jdField_void != null) {
      jdField_void.jdMethod_this(a, a);
    }
  }
  

  public void jdMethod_true(int a, String a, String a, String a)
  {
    int tmp9_8 = 1;tmp9_8;Sc.Sc = (3 + tmp9_8); int 
      tmp21_20 = 1;tmp21_20;oa.oa = (3 + tmp21_20);
    if (jdField_void != null) {
      jdField_void.jdMethod_true(a, a, a, a);
    }
  }
  
  /* Error */
  @Deprecated
  public void jdMethod_this(int a, String a, String a, String a)
  {
    // Byte code:
    //   0: aload_0
    //   1: getfield 53	z/Za:pB	I
    //   4: ldc 13
    //   6: if_icmplt +14 -> 20
    //   9: aload_0
    //   10: iload_1
    //   11: aload_2
    //   12: aload_3
    //   13: aload 4
    //   15: invokespecial 55	z/cON:this	(ILjava/lang/String;Ljava/lang/String;Ljava/lang/String;)V
    //   18: return
    //   19: athrow
    //   20: aload_0
    //   21: iload_1
    //   22: aload_2
    //   23: aload_3
    //   24: aload 4
    //   26: iload_1
    //   27: sipush 185
    //   30: iconst_1
    //   31: dup
    //   32: pop2
    //   33: if_icmpne +11 -> 44
    //   36: iconst_1
    //   37: dup
    //   38: dup
    //   39: pop2
    //   40: goto +8 -> 48
    //   43: athrow
    //   44: iconst_0
    //   45: iconst_1
    //   46: dup
    //   47: pop2
    //   48: invokespecial 58	z/Za:true	(ILjava/lang/String;Ljava/lang/String;Ljava/lang/String;Z)V
    //   51: return
    // Line number table:
    //   Java source line #127	-> byte code offset #0
    //   Java source line #128	-> byte code offset #9
    //   Java source line #129	-> byte code offset #18
    //   Java source line #131	-> byte code offset #20
    //   Java source line #133	-> byte code offset #51
    // Local variable table:
    //   start	length	slot	name	signature
    //   0	52	0	a	Za
    //   0	52	1	a	int
    //   0	52	2	a	String
    //   0	52	3	a	String
    //   0	52	4	a	String
  }
  
  /* Error */
  public void jdMethod_this(int a, String a, String a, String a, boolean a)
  {
    // Byte code:
    //   0: aload_0
    //   1: getfield 53	z/Za:pB	I
    //   4: ldc 13
    //   6: if_icmpge +16 -> 22
    //   9: aload_0
    //   10: iload_1
    //   11: aload_2
    //   12: aload_3
    //   13: aload 4
    //   15: iload 5
    //   17: invokespecial 62	z/cON:this	(ILjava/lang/String;Ljava/lang/String;Ljava/lang/String;Z)V
    //   20: return
    //   21: athrow
    //   22: aload_0
    //   23: iload_1
    //   24: aload_2
    //   25: aload_3
    //   26: aload 4
    //   28: iload 5
    //   30: invokespecial 58	z/Za:true	(ILjava/lang/String;Ljava/lang/String;Ljava/lang/String;Z)V
    //   33: return
    // Line number table:
    //   Java source line #138	-> byte code offset #0
    //   Java source line #139	-> byte code offset #9
    //   Java source line #140	-> byte code offset #20
    //   Java source line #142	-> byte code offset #22
    //   Java source line #143	-> byte code offset #33
    // Local variable table:
    //   start	length	slot	name	signature
    //   0	34	0	a	Za
    //   0	34	1	a	int
    //   0	34	2	a	String
    //   0	34	3	a	String
    //   0	34	4	a	String
    //   0	34	5	a	int
  }
  
  private void jdMethod_true(int a, String a, String a, String a, boolean a)
  {
    int tmp5_4 = 1;tmp5_4; if (185 == tmp5_4) {
      int tmp19_18 = 1;tmp19_18;Sc.Sc = (5 + tmp19_18); int 
        tmp31_30 = ;;;; break label68; throw a;
    } else {
      int tmp50_49 = 1;tmp50_49;Sc.Sc = (3 + tmp50_49); int 
        tmp62_61 = 1;tmp62_61;oa.oa = (3 + tmp62_61); }
    label68:
    if (jdField_void != null) {
      jdField_void.jdMethod_this(a, a, a, a, a);
    }
  }
  

  public void jdMethod_this(String a, String a, RA a, Object... a)
  {
    int tmp9_8 = 1;tmp9_8;Sc.Sc = (5 + tmp9_8); int 
      tmp21_20 = 1;tmp21_20;oa.oa = (5 + tmp21_20);
    if (jdField_void != null) {
      jdField_void.jdMethod_this(a, a, a, a);
    }
  }
  
  public void jdMethod_true(int a, OA a)
  {
    int tmp8_7 = 1;tmp8_7;Sc.Sc = (3 + tmp8_7); int 
      tmp18_17 = 1;tmp18_17; if (167 != tmp18_17) { int tmp28_27 = 1;tmp28_27; if (168 != tmp28_27) {}
    } else { int tmp41_40 = ;;;; break label66; throw a;
    }
    int tmp60_59 = 1;tmp60_59;oa.oa = (8 + tmp60_59);
    label66:
    if (jdField_void != null) {
      jdField_void.jdMethod_true(a, a);
    }
  }
  
  public void jdMethod_this(Object a)
  {
    if (((a instanceof Long)) || ((a instanceof Double))) {
      int tmp23_22 = 1;tmp23_22;Sc.Sc = (3 + tmp23_22); int 
        tmp35_34 = ;;;; break label72; throw a;
    } else {
      int tmp54_53 = 1;tmp54_53;Sc.Sc = (2 + tmp54_53); int 
        tmp66_65 = 1;tmp66_65;oa.oa = (3 + tmp66_65); }
    label72:
    if (jdField_void != null) {
      jdField_void.jdMethod_this(a);
    }
  }
  
  public void jdMethod_true(int a, int a)
  {
    int tmp5_4 = 1;tmp5_4; if (255 <= tmp5_4) { int tmp14_13 = 1;tmp14_13; if (127 <= tmp14_13) { int tmp23_22 = 1;tmp23_22; if (-128 >= tmp23_22) break label61; } }
    int tmp38_37 = 1;tmp38_37;Sc.Sc = (6 + tmp38_37); int 
      tmp51_50 = ;;;; break label88; throw a;
    label61:
    tmp70_69 = 1; tmp70_69;Sc.Sc = (3 + tmp70_69); int 
      tmp82_81 = 1;tmp82_81;oa.oa = (3 + tmp82_81);
    label88:
    if (jdField_void != null) {
      jdField_void.jdMethod_true(a, a);
    }
  }
  

  public void jdMethod_this(int a, int a, OA a, OA... a)
  {
    int tmp8_7 = 1;tmp8_7; int tmp15_14 = 1;tmp15_14;13Sc = (tmp8_7 + (a.length + 4 * tmp15_14)); int 
      tmp31_30 = 1;tmp31_30; int tmp38_37 = 1;tmp38_37;16oa = (tmp31_30 + (a.length + 4 * tmp38_37));
    if (jdField_void != null) {
      jdField_void.jdMethod_this(a, a, a, a);
    }
  }
  

  public void jdMethod_this(OA a, int[] a, OA[] a)
  {
    int tmp8_7 = 1;tmp8_7; int tmp15_14 = 1;tmp15_14;9Sc = (tmp8_7 + (a.length + 8 * tmp15_14)); int 
      tmp31_30 = 1;tmp31_30; int tmp38_37 = 1;tmp38_37;12oa = (tmp31_30 + (a.length + 8 * tmp38_37));
    if (jdField_void != null) {
      jdField_void.jdMethod_this(a, a, a);
    }
  }
  
  public void jdMethod_this(String a, int a)
  {
    int tmp9_8 = 1;tmp9_8;Sc.Sc = (4 + tmp9_8); int 
      tmp21_20 = 1;tmp21_20;oa.oa = (4 + tmp21_20);
    if (jdField_void != null) {
      jdField_void.jdMethod_this(a, a);
    }
  }
}
